Workbook

Sheet Read Me
A1: County Watch 2026
A2: What this is
A3: A county-by-county read of the competitive Senate races (AK, GA, IA, KS, ME, MI, MN, MS, NC, NE, NH, OH, SC, TX, FL), plus Virginia and Kentucky as early-closing bellwethers for the national swing.
A4: Before election night it holds the benchmarks (2024 and 2022 results by county, demographics, break-even margins) and the early vote. On the night it projects each race from the counties that have finished counting.
A5: Sheets
A6: Dashboard: one row per state with the projection, swing, confidence and the bot's written read.
A7: Key Counties: 6 to 11 counties per state, on both sides (Democratic vote banks and Republican bases), with why they matter, what to watch, and live status on margin and on turnout. Each state ends with an 'All rural' row: every small-town and rural county together.
A8: County Benchmarks: for each key county, the final margin and net votes that match each statewide outcome (R+5, R+1, tie, D+1, D+5), plus a plain-English line on what to look for. Read final county numbers against these.
A9: First Counties: the first counties to report in each state, in poll-closing order. Shows what arrives first (early, mail or Election Day votes), how lopsided that batch was in 2022, and the first-batch number that only means break-even.
A10: Counties: every county. Grey Feed columns are filled by the bot for GA, NC, MN and NE. Yellow Manual columns are yours: type D and R votes from any source (NYT, AP, a county site) and put Y in 'Manual complete' when a county is fully counted. Manual numbers override the feed.
A11: Types: each kind of county (metro cores, college suburbs, Black Belt, Hispanic, rural...) as a block: its share of the vote, the margin it needs for each statewide outcome, what weaker or stronger turnout does to that, and live swing and turnout. Its swing and turnout pace fill in counties that haven't reported.
A12: Early Vote: statewide early vote for each state, plus North Carolina county by county compared with 2022 at the same point.
... A37: Key county notes are the bot author's judgment; the numbers next to them come from the data above.

Sheet Dashboard
A1: County Watch 2026: competitive Senate races
A2: Projection = counted margin in fully reported counties + every other county's 2024 margin moved by the swing seen in counties of its type. Margins are two-party. Yellow cells are yours to change.
A3: Last bot update: Oct 29 06:09 PM
A5: State | B5: Senate race | C5: Democratic side | D5: Republican | E5: 2024 margin | F5: Swing D needs vs 2024 | G5: Turnout factor (vs 2022) | H5: Expected 2-party votes | I5: Counted 2-party votes | J5: % counted | K5: Counties complete | L5: of | M5: % of expected vote complete | N5: Swing in complete counties | O5: Ahead / behind needed swing | P5: Raw margin | Q5: Projected margin | R5: Leader (projected) | S5: Call | T5: Confidence | U5: Early votes so far | V5: Early vote as % of 2022 turnout | W5: Turnout pace in complete counties (vs 2022) | X5: Turnout pace used for uncounted | Y5: Projected turnout (vs 2022) | Z5: Turnout index: D-leaning complete counties | AA5: Turnout index: R-leaning complete counties | AB5: Latest read (bot)
A6: AK | B6: Alaska Senate | C6: Mary Peltola | D6: Dan Sullivan | E6: =(SUMIFS(Counties!$F$2:$F$1583,Counties!$A$2:$A$1583,$A6)-SUMIFS(Counties!$G$2:$G$1583,Counties!$A$2:$A$1583,$A6))/(SUMIFS(Counties!$F$2:$F$1583,Counties!$A$2:$A$1583,$A6)+SUMIFS(Counties!$G$2:$G$1583,Counties!$A$2:$A$1583,$A6)) | F6: =-SUMIFS(Counties!$AR$2:$AR$1583,Counties!$A$2:$A$1583,$A6)/SUMIFS(Counties!$AQ$2:$AQ$1583,Counties!$A$2:$A$1583,$A6) | G6: 1 | H6: =SUMIFS(Counties!$U$2:$U$1583,Counties!$A$2:$A$1583,$A6) | I6: =SUMIFS(Counties!$AF$2:$AF$1583,Counties!$A$2:$A$1583,$A6) | J6: =IF(H6>0,I6/H6,0) | K6: =COUNTIFS(Counties!$A$2:$A$1583,$A6,Counties!$AG$2:$AG$1583,1) | L6: =COUNTIF(Counties!$A$2:$A$1583,$A6) | M6: =IF(H6>0,SUMIFS(Counties!$U$2:$U$1583,Counties!$A$2:$A$1583,$A6,Counties!$AG$2:$AG$1583,1)/H6,0) | N6: =IF(K6>0,SUMIFS(Counties!$AP$2:$AP$1583,Counties!$A$2:$A$1583,$A6)/SUMIFS(Counties!$AF$2:$AF$1583,Counties!$A$2:$A$1583,$A6,Counties!$AG$2:$AG$1583,1),"") | O6: =IF(N6="","",N6-F6) | P6: =IF(I6>0,(SUMIFS(Counties!$AD$2:$AD$1583,Counties!$A$2:$A$1583,$A6)-SUMIFS(Counties!$AE$2:$AE$1583,Counties!$A$2:$A$1583,$A6))/I6,"") | Q6: =IF(K6>0,(SUMIFS(Counties!$AL$2:$AL$1583,Counties!$A$2:$A$1583,$A6)-SUMIFS(Counties!$AM$2:$AM$1583,Counties!$A$2:$A$1583,$A6))/(SUMIFS(Counties!$AL$2:$AL$1583,Counties!$A$2:$A$1583,$A6)+SUMIFS(Counties!$AM$2:$AM$1583,Counties!$A$2:$A$1583,$A6)),"") | R6: =IF(Q6="","",IF(Q6>=0,C6,D6)&" +"&TEXT(ABS(Q6)*100,"0.0")) | S6: =IF(Q6="","",IF(Q6>=0.05,"Great for "&TRIM(RIGHT(SUBSTITUTE(C6," ",REPT(" ",50)),50)),IF(Q6>=0.01,TRIM(RIGHT(SUBSTITUTE(C6," ",REPT(" ",50)),50))&" on track",IF(Q6>-0.01,"Toss-up",IF(Q6>-0.05,TRIM(RIGHT(SUBSTITUTE(D6," ",REPT(" ",50)),50))&" on track","Great for "&TRIM(RIGHT(SUBSTITUTE(D6," ",REPT(" ",50)),50))))))) | T6: =IF(K6=0,"none",IF(OR(M6<0.1,K6<5),"low",IF(M6<0.4,"medium","high"))) | U6: =IFERROR(INDEX('Early Vote'!$C$6:$C$22,MATCH($A6,'Early Vote'!$A$6:$A$22,0)),"") | V6: =IFERROR(INDEX('Early Vote'!$E$6:$E$22,MATCH($A6,'Early Vote'!$A$6:$A$22,0)),"") | W6: =IF(K6>0,SUMIFS(Counties!$AF$2:$AF$1583,Counties!$A$2:$A$1583,$A6,Counties!$AG$2:$AG$1583,1)/SUMIFS(Counties!$AQ$2:$AQ$1583,Counties!$A$2:$A$1583,$A6,Counties!$AG$2:$AG$1583,1),"") | X6: =IF(K6>=3,W6,G6) | Y6: =SUMIFS(Counties!$AK$2:$AK$1583,Counties!$A$2:$A$1583,$A6)/SUMIFS(Counties!$AQ$2:$AQ$1583,Counties!$A$2:$A$1583,$A6) | Z6: =IFERROR(100*SUMIFS(Counties!$AF$2:$AF$1583,Counties!$A$2:$A$1583,$A6,Counties!$AG$2:$AG$1583,1,Counties!$T$2:$T$1583,">=0.1")/SUMIFS(Counties!$AT$2:$AT$1583,Counties!$A$2:$A$1583,$A6,Counties!$AG$2:$AG$1583,1,Counties!$T$2:$T$1583,">=0.1"),"") | AA6: =IFERROR(100*SUMIFS(Counties!$AF$2:$AF$1583,Counties!$A$2:$A$1583,$A6,Counties!$AG$2:$AG$1583,1,Counties!$T$2:$T$1583,"<=-0.1")/SUMIFS(Counties!$AT$2:$AT$1583,Counties!$A$2:$A$1583,$A6,Counties!$AG$2:$AG$1583,1,Counties!$T$2:$T$1583,"<=-0.1"),"") | AB6: No votes counted yet. 2024: R+13.8; with 2022's turnout pattern R+14.0, so Peltola needs a 14.0-pt swing toward D from 2024 to win.
A7: GA | B7: Georgia Senate | C7: Jon Ossoff | D7: Mike Collins | E7: =(SUMIFS(Counties!$F$2:$F$1583,Counties!$A$2:$A$1583,$A7)-SUMIFS(Counties!$G$2:$G$1583,Counties!$A$2:$A$1583,$A7))/(SUMIFS(Counties!$F$2:$F$1583,Counties!$A$2:$A$1583,$A7)+SUMIFS(Counties!$G$2:$G$1583,Counties!$A$2:$A$1583,$A7)) | F7: =-SUMIFS(Counties!$AR$2:$AR$1583,Counties!$A$2:$A$1583,$A7)/SUMIFS(Counties!$AQ$2:$AQ$1583,Counties!$A$2:$A$1583,$A7) | G7: 1 | H7: =SUMIFS(Counties!$U$2:$U$1583,Counties!$A$2:$A$1583,$A7) | I7: =SUMIFS(Counties!$AF$2:$AF$1583,Counties!$A$2:$A$1583,$A7) | J7: =IF(H7>0,I7/H7,0) | K7: =COUNTIFS(Counties!$A$2:$A$1583,$A7,Counties!$AG$2:$AG$1583,1) | L7: =COUNTIF(Counties!$A$2:$A$1583,$A7) | M7: =IF(H7>0,SUMIFS(Counties!$U$2:$U$1583,Counties!$A$2:$A$1583,$A7,Counties!$AG$2:$AG$1583,1)/H7,0) | N7: =IF(K7>0,SUMIFS(Counties!$AP$2:$AP$1583,Counties!$A$2:$A$1583,$A7)/SUMIFS(Counties!$AF$2:$AF$1583,Counties!$A$2:$A$1583,$A7,Counties!$AG$2:$AG$1583,1),"") | O7: =IF(N7="","",N7-F7) | P7: =IF(I7>0,(SUMIFS(Counties!$AD$2:$AD$1583,Counties!$A$2:$A$1583,$A7)-SUMIFS(Counties!$AE$2:$AE$1583,Counties!$A$2:$A$1583,$A7))/I7,"") | Q7: =IF(K7>0,(SUMIFS(Counties!$AL$2:$AL$1583,Counties!$A$2:$A$1583,$A7)-SUMIFS(Counties!$AM$2:$AM$1583,Counties!$A$2:$A$1583,$A7))/(SUMIFS(Counties!$AL$2:$AL$1583,Counties!$A$2:$A$1583,$A7)+SUMIFS(Counties!$AM$2:$AM$1583,Counties!$A$2:$A$1583,$A7)),"") | R7: =IF(Q7="","",IF(Q7>=0,C7,D7)&" +"&TEXT(ABS(Q7)*100,"0.0")) | S7: =IF(Q7="","",IF(Q7>=0.05,"Great for "&TRIM(RIGHT(SUBSTITUTE(C7," ",REPT(" ",50)),50)),IF(Q7>=0.01,TRIM(RIGHT(SUBSTITUTE(C7," ",REPT(" ",50)),50))&" on track",IF(Q7>-0.01,"Toss-up",IF(Q7>-0.05,TRIM(RIGHT(SUBSTITUTE(D7," ",REPT(" ",50)),50))&" on track","Great for "&TRIM(RIGHT(SUBSTITUTE(D7," ",REPT(" ",50)),50))))))) | T7: =IF(K7=0,"none",IF(OR(M7<0.1,K7<5),"low",IF(M7<0.4,"medium","high"))) | U7: =IFERROR(INDEX('Early Vote'!$C$6:$C$22,MATCH($A7,'Early Vote'!$A$6:$A$22,0)),"") | V7: =IFERROR(INDEX('Early Vote'!$E$6:$E$22,MATCH($A7,'Early Vote'!$A$6:$A$22,0)),"") | W7: =IF(K7>0,SUMIFS(Counties!$AF$2:$AF$1583,Counties!$A$2:$A$1583,$A7,Counties!$AG$2:$AG$1583,1)/SUMIFS(Counties!$AQ$2:$AQ$1583,Counties!$A$2:$A$1583,$A7,Counties!$AG$2:$AG$1583,1),"") | X7: =IF(K7>=3,W7,G7) | Y7: =SUMIFS(Counties!$AK$2:$AK$1583,Counties!$A$2:$A$1583,$A7)/SUMIFS(Counties!$AQ$2:$AQ$1583,Counties!$A$2:$A$1583,$A7) | Z7: =IFERROR(100*SUMIFS(Counties!$AF$2:$AF$1583,Counties!$A$2:$A$1583,$A7,Counties!$AG$2:$AG$1583,1,Counties!$T$2:$T$1583,">=0.1")/SUMIFS(Counties!$AT$2:$AT$1583,Counties!$A$2:$A$1583,$A7,Counties!$AG$2:$AG$1583,1,Counties!$T$2:$T$1583,">=0.1"),"") | AA7: =IFERROR(100*SUMIFS(Counties!$AF$2:$AF$1583,Counties!$A$2:$A$1583,$A7,Counties!$AG$2:$AG$1583,1,Counties!$T$2:$T$1583,"<=-0.1")/SUMIFS(Counties!$AT$2:$AT$1583,Counties!$A$2:$A$1583,$A7,Counties!$AG$2:$AG$1583,1,Counties!$T$2:$T$1583,"<=-0.1"),"") | AB7: No votes counted yet. 2024: R+2.2; with 2022's turnout pattern R+1.1, so Ossoff needs a 1.1-pt swing toward D from 2024 to win. In 2022 the advance vote was D+10.3 and the Election Day vote R+15.9, so counts that are mostly advance votes flatter Democrats.
A8: IA | B8: Iowa Senate | C8: Josh Turek | D8: Ashley Hinson | E8: =(SUMIFS(Counties!$F$2:$F$1583,Counties!$A$2:$A$1583,$A8)-SUMIFS(Counties!$G$2:$G$1583,Counties!$A$2:$A$1583,$A8))/(SUMIFS(Counties!$F$2:$F$1583,Counties!$A$2:$A$1583,$A8)+SUMIFS(Counties!$G$2:$G$1583,Counties!$A$2:$A$1583,$A8)) | F8: =-SUMIFS(Counties!$AR$2:$AR$1583,Counties!$A$2:$A$1583,$A8)/SUMIFS(Counties!$AQ$2:$AQ$1583,Counties!$A$2:$A$1583,$A8) | G8: 1 | H8: =SUMIFS(Counties!$U$2:$U$1583,Counties!$A$2:$A$1583,$A8) | I8: =SUMIFS(Counties!$AF$2:$AF$1583,Counties!$A$2:$A$1583,$A8) | J8: =IF(H8>0,I8/H8,0) | K8: =COUNTIFS(Counties!$A$2:$A$1583,$A8,Counties!$AG$2:$AG$1583,1) | L8: =COUNTIF(Counties!$A$2:$A$1583,$A8) | M8: =IF(H8>0,SUMIFS(Counties!$U$2:$U$1583,Counties!$A$2:$A$1583,$A8,Counties!$AG$2:$AG$1583,1)/H8,0) | N8: =IF(K8>0,SUMIFS(Counties!$AP$2:$AP$1583,Counties!$A$2:$A$1583,$A8)/SUMIFS(Counties!$AF$2:$AF$1583,Counties!$A$2:$A$1583,$A8,Counties!$AG$2:$AG$1583,1),"") | O8: =IF(N8="","",N8-F8) | P8: =IF(I8>0,(SUMIFS(Counties!$AD$2:$AD$1583,Counties!$A$2:$A$1583,$A8)-SUMIFS(Counties!$AE$2:$AE$1583,Counties!$A$2:$A$1583,$A8))/I8,"") | Q8: =IF(K8>0,(SUMIFS(Counties!$AL$2:$AL$1583,Counties!$A$2:$A$1583,$A8)-SUMIFS(Counties!$AM$2:$AM$1583,Counties!$A$2:$A$1583,$A8))/(SUMIFS(Counties!$AL$2:$AL$1583,Counties!$A$2:$A$1583,$A8)+SUMIFS(Counties!$AM$2:$AM$1583,Counties!$A$2:$A$1583,$A8)),"") | R8: =IF(Q8="","",IF(Q8>=0,C8,D8)&" +"&TEXT(ABS(Q8)*100,"0.0")) | S8: =IF(Q8="","",IF(Q8>=0.05,"Great for "&TRIM(RIGHT(SUBSTITUTE(C8," ",REPT(" ",50)),50)),IF(Q8>=0.01,TRIM(RIGHT(SUBSTITUTE(C8," ",REPT(" ",50)),50))&" on track",IF(Q8>-0.01,"Toss-up",IF(Q8>-0.05,TRIM(RIGHT(SUBSTITUTE(D8," ",REPT(" ",50)),50))&" on track","Great for "&TRIM(RIGHT(SUBSTITUTE(D8," ",REPT(" ",50)),50))))))) | T8: =IF(K8=0,"none",IF(OR(M8<0.1,K8<5),"low",IF(M8<0.4,"medium","high"))) | U8: =IFERROR(INDEX('Early Vote'!$C$6:$C$22,MATCH($A8,'Early Vote'!$A$6:$A$22,0)),"") | V8: =IFERROR(INDEX('Early Vote'!$E$6:$E$22,MATCH($A8,'Early Vote'!$A$6:$A$22,0)),"") | W8: =IF(K8>0,SUMIFS(Counties!$AF$2:$AF$1583,Counties!$A$2:$A$1583,$A8,Counties!$AG$2:$AG$1583,1)/SUMIFS(Counties!$AQ$2:$AQ$1583,Counties!$A$2:$A$1583,$A8,Counties!$AG$2:$AG$1583,1),"") | X8: =IF(K8>=3,W8,G8) | Y8: =SUMIFS(Counties!$AK$2:$AK$1583,Counties!$A$2:$A$1583,$A8)/SUMIFS(Counties!$AQ$2:$AQ$1583,Counties!$A$2:$A$1583,$A8) | Z8: =IFERROR(100*SUMIFS(Counties!$AF$2:$AF$1583,Counties!$A$2:$A$1583,$A8,Counties!$AG$2:$AG$1583,1,Counties!$T$2:$T$1583,">=0.1")/SUMIFS(Counties!$AT$2:$AT$1583,Counties!$A$2:$A$1583,$A8,Counties!$AG$2:$AG$1583,1,Counties!$T$2:$T$1583,">=0.1"),"") | AA8: =IFERROR(100*SUMIFS(Counties!$AF$2:$AF$1583,Counties!$A$2:$A$1583,$A8,Counties!$AG$2:$AG$1583,1,Counties!$T$2:$T$1583,"<=-0.1")/SUMIFS(Counties!$AT$2:$AT$1583,Counties!$A$2:$A$1583,$A8,Counties!$AG$2:$AG$1583,1,Counties!$T$2:$T$1583,"<=-0.1"),"") | AB8: No votes counted yet. 2024: R+13.4; with 2022's turnout pattern R+13.2, so Turek needs a 13.2-pt swing toward D from 2024 to win. In 2022 the early/absentee vote was D+19.7 and the Election Day vote R+25.9, so counts that are mostly early/absentee votes flatter Democrats.
A9: KS | B9: Kansas Senate | C9: Adam Hamilton | D9: Roger Marshall | E9: =(SUMIFS(Counties!$F$2:$F$1583,Counties!$A$2:$A$1583,$A9)-SUMIFS(Counties!$G$2:$G$1583,Counties!$A$2:$A$1583,$A9))/(SUMIFS(Counties!$F$2:$F$1583,Counties!$A$2:$A$1583,$A9)+SUMIFS(Counties!$G$2:$G$1583,Counties!$A$2:$A$1583,$A9)) | F9: =-SUMIFS(Counties!$AR$2:$AR$1583,Counties!$A$2:$A$1583,$A9)/SUMIFS(Counties!$AQ$2:$AQ$1583,Counties!$A$2:$A$1583,$A9) | G9: 1 | H9: =SUMIFS(Counties!$U$2:$U$1583,Counties!$A$2:$A$1583,$A9) | I9: =SUMIFS(Counties!$AF$2:$AF$1583,Counties!$A$2:$A$1583,$A9) | J9: =IF(H9>0,I9/H9,0) | K9: =COUNTIFS(Counties!$A$2:$A$1583,$A9,Counties!$AG$2:$AG$1583,1) | L9: =COUNTIF(Counties!$A$2:$A$1583,$A9) | M9: =IF(H9>0,SUMIFS(Counties!$U$2:$U$1583,Counties!$A$2:$A$1583,$A9,Counties!$AG$2:$AG$1583,1)/H9,0) | N9: =IF(K9>0,SUMIFS(Counties!$AP$2:$AP$1583,Counties!$A$2:$A$1583,$A9)/SUMIFS(Counties!$AF$2:$AF$1583,Counties!$A$2:$A$1583,$A9,Counties!$AG$2:$AG$1583,1),"") | O9: =IF(N9="","",N9-F9) | P9: =IF(I9>0,(SUMIFS(Counties!$AD$2:$AD$1583,Counties!$A$2:$A$1583,$A9)-SUMIFS(Counties!$AE$2:$AE$1583,Counties!$A$2:$A$1583,$A9))/I9,"") | Q9: =IF(K9>0,(SUMIFS(Counties!$AL$2:$AL$1583,Counties!$A$2:$A$1583,$A9)-SUMIFS(Counties!$AM$2:$AM$1583,Counties!$A$2:$A$1583,$A9))/(SUMIFS(Counties!$AL$2:$AL$1583,Counties!$A$2:$A$1583,$A9)+SUMIFS(Counties!$AM$2:$AM$1583,Counties!$A$2:$A$1583,$A9)),"") | R9: =IF(Q9="","",IF(Q9>=0,C9,D9)&" +"&TEXT(ABS(Q9)*100,"0.0")) | S9: =IF(Q9="","",IF(Q9>=0.05,"Great for "&TRIM(RIGHT(SUBSTITUTE(C9," ",REPT(" ",50)),50)),IF(Q9>=0.01,TRIM(RIGHT(SUBSTITUTE(C9," ",REPT(" ",50)),50))&" on track",IF(Q9>-0.01,"Toss-up",IF(Q9>-0.05,TRIM(RIGHT(SUBSTITUTE(D9," ",REPT(" ",50)),50))&" on track","Great for "&TRIM(RIGHT(SUBSTITUTE(D9," ",REPT(" ",50)),50))))))) | T9: =IF(K9=0,"none",IF(OR(M9<0.1,K9<5),"low",IF(M9<0.4,"medium","high"))) | U9: =IFERROR(INDEX('Early Vote'!$C$6:$C$22,MATCH($A9,'Early Vote'!$A$6:$A$22,0)),"") | V9: =IFERROR(INDEX('Early Vote'!$E$6:$E$22,MATCH($A9,'Early Vote'!$A$6:$A$22,0)),"") | W9: =IF(K9>0,SUMIFS(Counties!$AF$2:$AF$1583,Counties!$A$2:$A$1583,$A9,Counties!$AG$2:$AG$1583,1)/SUMIFS(Counties!$AQ$2:$AQ$1583,Counties!$A$2:$A$1583,$A9,Counties!$AG$2:$AG$1583,1),"") | X9: =IF(K9>=3,W9,G9) | Y9: =SUMIFS(Counties!$AK$2:$AK$1583,Counties!$A$2:$A$1583,$A9)/SUMIFS(Counties!$AQ$2:$AQ$1583,Counties!$A$2:$A$1583,$A9) | Z9: =IFERROR(100*SUMIFS(Counties!$AF$2:$AF$1583,Counties!$A$2:$A$1583,$A9,Counties!$AG$2:$AG$1583,1,Counties!$T$2:$T$1583,">=0.1")/SUMIFS(Counties!$AT$2:$AT$1583,Counties!$A$2:$A$1583,$A9,Counties!$AG$2:$AG$1583,1,Counties!$T$2:$T$1583,">=0.1"),"") | AA9: =IFERROR(100*SUMIFS(Counties!$AF$2:$AF$1583,Counties!$A$2:$A$1583,$A9,Counties!$AG$2:$AG$1583,1,Counties!$T$2:$T$1583,"<=-0.1")/SUMIFS(Counties!$AT$2:$AT$1583,Counties!$A$2:$A$1583,$A9,Counties!$AG$2:$AG$1583,1,Counties!$T$2:$T$1583,"<=-0.1"),"") | AB9: No votes counted yet. 2024: R+16.4; with 2022's turnout pattern R+16.5, so Hamilton needs a 16.5-pt swing toward D from 2024 to win.
A10: ME | B10: Maine Senate | C10: Troy Jackson | D10: Susan Collins | E10: =(SUMIFS(Counties!$F$2:$F$1583,Counties!$A$2:$A$1583,$A10)-SUMIFS(Counties!$G$2:$G$1583,Counties!$A$2:$A$1583,$A10))/(SUMIFS(Counties!$F$2:$F$1583,Counties!$A$2:$A$1583,$A10)+SUMIFS(Counties!$G$2:$G$1583,Counties!$A$2:$A$1583,$A10)) | F10: =-SUMIFS(Counties!$AR$2:$AR$1583,Counties!$A$2:$A$1583,$A10)/SUMIFS(Counties!$AQ$2:$AQ$1583,Counties!$A$2:$A$1583,$A10) | G10: 1 | H10: =SUMIFS(Counties!$U$2:$U$1583,Counties!$A$2:$A$1583,$A10) | I10: =SUMIFS(Counties!$AF$2:$AF$1583,Counties!$A$2:$A$1583,$A10) | J10: =IF(H10>0,I10/H10,0) | K10: =COUNTIFS(Counties!$A$2:$A$1583,$A10,Counties!$AG$2:$AG$1583,1) | L10: =COUNTIF(Counties!$A$2:$A$1583,$A10) | M10: =IF(H10>0,SUMIFS(Counties!$U$2:$U$1583,Counties!$A$2:$A$1583,$A10,Counties!$AG$2:$AG$1583,1)/H10,0) | N10: =IF(K10>0,SUMIFS(Counties!$AP$2:$AP$1583,Counties!$A$2:$A$1583,$A10)/SUMIFS(Counties!$AF$2:$AF$1583,Counties!$A$2:$A$1583,$A10,Counties!$AG$2:$AG$1583,1),"") | O10: =IF(N10="","",N10-F10) | P10: =IF(I10>0,(SUMIFS(Counties!$AD$2:$AD$1583,Counties!$A$2:$A$1583,$A10)-SUMIFS(Counties!$AE$2:$AE$1583,Counties!$A$2:$A$1583,$A10))/I10,"") | Q10: =IF(K10>0,(SUMIFS(Counties!$AL$2:$AL$1583,Counties!$A$2:$A$1583,$A10)-SUMIFS(Counties!$AM$2:$AM$1583,Counties!$A$2:$A$1583,$A10))/(SUMIFS(Counties!$AL$2:$AL$1583,Counties!$A$2:$A$1583,$A10)+SUMIFS(Counties!$AM$2:$AM$1583,Counties!$A$2:$A$1583,$A10)),"") | R10: =IF(Q10="","",IF(Q10>=0,C10,D10)&" +"&TEXT(ABS(Q10)*100,"0.0")) | S10: =IF(Q10="","",IF(Q10>=0.05,"Great for "&TRIM(RIGHT(SUBSTITUTE(C10," ",REPT(" ",50)),50)),IF(Q10>=0.01,TRIM(RIGHT(SUBSTITUTE(C10," ",REPT(" ",50)),50))&" on track",IF(Q10>-0.01,"Toss-up",IF(Q10>-0.05,TRIM(RIGHT(SUBSTITUTE(D10," ",REPT(" ",50)),50))&" on track","Great for "&TRIM(RIGHT(SUBSTITUTE(D10," ",REPT(" ",50)),50))))))) | T10: =IF(K10=0,"none",IF(OR(M10<0.1,K10<5),"low",IF(M10<0.4,"medium","high"))) | U10: =IFERROR(INDEX('Early Vote'!$C$6:$C$22,MATCH($A10,'Early Vote'!$A$6:$A$22,0)),"") | V10: =IFERROR(INDEX('Early Vote'!$E$6:$E$22,MATCH($A10,'Early Vote'!$A$6:$A$22,0)),"") | W10: =IF(K10>0,SUMIFS(Counties!$AF$2:$AF$1583,Counties!$A$2:$A$1583,$A10,Counties!$AG$2:$AG$1583,1)/SUMIFS(Counties!$AQ$2:$AQ$1583,Counties!$A$2:$A$1583,$A10,Counties!$AG$2:$AG$1583,1),"") | X10: =IF(K10>=3,W10,G10) | Y10: =SUMIFS(Counties!$AK$2:$AK$1583,Counties!$A$2:$A$1583,$A10)/SUMIFS(Counties!$AQ$2:$AQ$1583,Counties!$A$2:$A$1583,$A10) | Z10: =IFERROR(100*SUMIFS(Counties!$AF$2:$AF$1583,Counties!$A$2:$A$1583,$A10,Counties!$AG$2:$AG$1583,1,Counties!$T$2:$T$1583,">=0.1")/SUMIFS(Counties!$AT$2:$AT$1583,Counties!$A$2:$A$1583,$A10,Counties!$AG$2:$AG$1583,1,Counties!$T$2:$T$1583,">=0.1"),"") | AA10: =IFERROR(100*SUMIFS(Counties!$AF$2:$AF$1583,Counties!$A$2:$A$1583,$A10,Counties!$AG$2:$AG$1583,1,Counties!$T$2:$T$1583,"<=-0.1")/SUMIFS(Counties!$AT$2:$AT$1583,Counties!$A$2:$A$1583,$A10,Counties!$AG$2:$AG$1583,1,Counties!$T$2:$T$1583,"<=-0.1"),"") | AB10: No votes counted yet. 2024: D+7.1; with 2022's turnout pattern D+7.2, so Jackson can absorb up to a 7.2-pt swing toward R from 2024 and still win.
A11: MI | B11: Michigan Senate | C11: Abdul El-Sayed | D11: Mike Rogers | E11: =(SUMIFS(Counties!$F$2:$F$1583,Counties!$A$2:$A$1583,$A11)-SUMIFS(Counties!$G$2:$G$1583,Counties!$A$2:$A$1583,$A11))/(SUMIFS(Counties!$F$2:$F$1583,Counties!$A$2:$A$1583,$A11)+SUMIFS(Counties!$G$2:$G$1583,Counties!$A$2:$A$1583,$A11)) | F11: =-SUMIFS(Counties!$AR$2:$AR$1583,Counties!$A$2:$A$1583,$A11)/SUMIFS(Counties!$AQ$2:$AQ$1583,Counties!$A$2:$A$1583,$A11) | G11: 1 | H11: =SUMIFS(Counties!$U$2:$U$1583,Counties!$A$2:$A$1583,$A11) | I11: =SUMIFS(Counties!$AF$2:$AF$1583,Counties!$A$2:$A$1583,$A11) | J11: =IF(H11>0,I11/H11,0) | K11: =COUNTIFS(Counties!$A$2:$A$1583,$A11,Counties!$AG$2:$AG$1583,1) | L11: =COUNTIF(Counties!$A$2:$A$1583,$A11) | M11: =IF(H11>0,SUMIFS(Counties!$U$2:$U$1583,Counties!$A$2:$A$1583,$A11,Counties!$AG$2:$AG$1583,1)/H11,0) | N11: =IF(K11>0,SUMIFS(Counties!$AP$2:$AP$1583,Counties!$A$2:$A$1583,$A11)/SUMIFS(Counties!$AF$2:$AF$1583,Counties!$A$2:$A$1583,$A11,Counties!$AG$2:$AG$1583,1),"") | O11: =IF(N11="","",N11-F11) | P11: =IF(I11>0,(SUMIFS(Counties!$AD$2:$AD$1583,Counties!$A$2:$A$1583,$A11)-SUMIFS(Counties!$AE$2:$AE$1583,Counties!$A$2:$A$1583,$A11))/I11,"") | Q11: =IF(K11>0,(SUMIFS(Counties!$AL$2:$AL$1583,Counties!$A$2:$A$1583,$A11)-SUMIFS(Counties!$AM$2:$AM$1583,Counties!$A$2:$A$1583,$A11))/(SUMIFS(Counties!$AL$2:$AL$1583,Counties!$A$2:$A$1583,$A11)+SUMIFS(Counties!$AM$2:$AM$1583,Counties!$A$2:$A$1583,$A11)),"") | R11: =IF(Q11="","",IF(Q11>=0,C11,D11)&" +"&TEXT(ABS(Q11)*100,"0.0")) | S11: =IF(Q11="","",IF(Q11>=0.05,"Great for "&TRIM(RIGHT(SUBSTITUTE(C11," ",REPT(" ",50)),50)),IF(Q11>=0.01,TRIM(RIGHT(SUBSTITUTE(C11," ",REPT(" ",50)),50))&" on track",IF(Q11>-0.01,"Toss-up",IF(Q11>-0.05,TRIM(RIGHT(SUBSTITUTE(D11," ",REPT(" ",50)),50))&" on track","Great for "&TRIM(RIGHT(SUBSTITUTE(D11," ",REPT(" ",50)),50))))))) | T11: =IF(K11=0,"none",IF(OR(M11<0.1,K11<5),"low",IF(M11<0.4,"medium","high"))) | U11: =IFERROR(INDEX('Early Vote'!$C$6:$C$22,MATCH($A11,'Early Vote'!$A$6:$A$22,0)),"") | V11: =IFERROR(INDEX('Early Vote'!$E$6:$E$22,MATCH($A11,'Early Vote'!$A$6:$A$22,0)),"") | W11: =IF(K11>0,SUMIFS(Counties!$AF$2:$AF$1583,Counties!$A$2:$A$1583,$A11,Counties!$AG$2:$AG$1583,1)/SUMIFS(Counties!$AQ$2:$AQ$1583,Counties!$A$2:$A$1583,$A11,Counties!$AG$2:$AG$1583,1),"") | X11: =IF(K11>=3,W11,G11) | Y11: =SUMIFS(Counties!$AK$2:$AK$1583,Counties!$A$2:$A$1583,$A11)/SUMIFS(Counties!$AQ$2:$AQ$1583,Counties!$A$2:$A$1583,$A11) | Z11: =IFERROR(100*SUMIFS(Counties!$AF$2:$AF$1583,Counties!$A$2:$A$1583,$A11,Counties!$AG$2:$AG$1583,1,Counties!$T$2:$T$1583,">=0.1")/SUMIFS(Counties!$AT$2:$AT$1583,Counties!$A$2:$A$1583,$A11,Counties!$AG$2:$AG$1583,1,Counties!$T$2:$T$1583,">=0.1"),"") | AA11: =IFERROR(100*SUMIFS(Counties!$AF$2:$AF$1583,Counties!$A$2:$A$1583,$A11,Counties!$AG$2:$AG$1583,1,Counties!$T$2:$T$1583,"<=-0.1")/SUMIFS(Counties!$AT$2:$AT$1583,Counties!$A$2:$A$1583,$A11,Counties!$AG$2:$AG$1583,1,Counties!$T$2:$T$1583,"<=-0.1"),"") | AB11: No votes counted yet. 2024: R+1.4; with 2022's turnout pattern R+1.8, so El-Sayed needs a 1.8-pt swing toward D from 2024 to win.
A12: MN | B12: Minnesota Senate | C12: Peggy Flanagan | D12: Michele Tafoya | E12: =(SUMIFS(Counties!$F$2:$F$1583,Counties!$A$2:$A$1583,$A12)-SUMIFS(Counties!$G$2:$G$1583,Counties!$A$2:$A$1583,$A12))/(SUMIFS(Counties!$F$2:$F$1583,Counties!$A$2:$A$1583,$A12)+SUMIFS(Counties!$G$2:$G$1583,Counties!$A$2:$A$1583,$A12)) | F12: =-SUMIFS(Counties!$AR$2:$AR$1583,Counties!$A$2:$A$1583,$A12)/SUMIFS(Counties!$AQ$2:$AQ$1583,Counties!$A$2:$A$1583,$A12) | G12: 1 | H12: =SUMIFS(Counties!$U$2:$U$1583,Counties!$A$2:$A$1583,$A12) | I12: =SUMIFS(Counties!$AF$2:$AF$1583,Counties!$A$2:$A$1583,$A12) | J12: =IF(H12>0,I12/H12,0) | K12: =COUNTIFS(Counties!$A$2:$A$1583,$A12,Counties!$AG$2:$AG$1583,1) | L12: =COUNTIF(Counties!$A$2:$A$1583,$A12) | M12: =IF(H12>0,SUMIFS(Counties!$U$2:$U$1583,Counties!$A$2:$A$1583,$A12,Counties!$AG$2:$AG$1583,1)/H12,0) | N12: =IF(K12>0,SUMIFS(Counties!$AP$2:$AP$1583,Counties!$A$2:$A$1583,$A12)/SUMIFS(Counties!$AF$2:$AF$1583,Counties!$A$2:$A$1583,$A12,Counties!$AG$2:$AG$1583,1),"") | O12: =IF(N12="","",N12-F12) | P12: =IF(I12>0,(SUMIFS(Counties!$AD$2:$AD$1583,Counties!$A$2:$A$1583,$A12)-SUMIFS(Counties!$AE$2:$AE$1583,Counties!$A$2:$A$1583,$A12))/I12,"") | Q12: =IF(K12>0,(SUMIFS(Counties!$AL$2:$AL$1583,Counties!$A$2:$A$1583,$A12)-SUMIFS(Counties!$AM$2:$AM$1583,Counties!$A$2:$A$1583,$A12))/(SUMIFS(Counties!$AL$2:$AL$1583,Counties!$A$2:$A$1583,$A12)+SUMIFS(Counties!$AM$2:$AM$1583,Counties!$A$2:$A$1583,$A12)),"") | R12: =IF(Q12="","",IF(Q12>=0,C12,D12)&" +"&TEXT(ABS(Q12)*100,"0.0")) | S12: =IF(Q12="","",IF(Q12>=0.05,"Great for "&TRIM(RIGHT(SUBSTITUTE(C12," ",REPT(" ",50)),50)),IF(Q12>=0.01,TRIM(RIGHT(SUBSTITUTE(C12," ",REPT(" ",50)),50))&" on track",IF(Q12>-0.01,"Toss-up",IF(Q12>-0.05,TRIM(RIGHT(SUBSTITUTE(D12," ",REPT(" ",50)),50))&" on track","Great for "&TRIM(RIGHT(SUBSTITUTE(D12," ",REPT(" ",50)),50))))))) | T12: =IF(K12=0,"none",IF(OR(M12<0.1,K12<5),"low",IF(M12<0.4,"medium","high"))) | U12: =IFERROR(INDEX('Early Vote'!$C$6:$C$22,MATCH($A12,'Early Vote'!$A$6:$A$22,0)),"") | V12: =IFERROR(INDEX('Early Vote'!$E$6:$E$22,MATCH($A12,'Early Vote'!$A$6:$A$22,0)),"") | W12: =IF(K12>0,SUMIFS(Counties!$AF$2:$AF$1583,Counties!$A$2:$A$1583,$A12,Counties!$AG$2:$AG$1583,1)/SUMIFS(Counties!$AQ$2:$AQ$1583,Counties!$A$2:$A$1583,$A12,Counties!$AG$2:$AG$1583,1),"") | X12: =IF(K12>=3,W12,G12) | Y12: =SUMIFS(Counties!$AK$2:$AK$1583,Counties!$A$2:$A$1583,$A12)/SUMIFS(Counties!$AQ$2:$AQ$1583,Counties!$A$2:$A$1583,$A12) | Z12: =IFERROR(100*SUMIFS(Counties!$AF$2:$AF$1583,Counties!$A$2:$A$1583,$A12,Counties!$AG$2:$AG$1583,1,Counties!$T$2:$T$1583,">=0.1")/SUMIFS(Counties!$AT$2:$AT$1583,Counties!$A$2:$A$1583,$A12,Counties!$AG$2:$AG$1583,1,Counties!$T$2:$T$1583,">=0.1"),"") | AA12: =IFERROR(100*SUMIFS(Counties!$AF$2:$AF$1583,Counties!$A$2:$A$1583,$A12,Counties!$AG$2:$AG$1583,1,Counties!$T$2:$T$1583,"<=-0.1")/SUMIFS(Counties!$AT$2:$AT$1583,Counties!$A$2:$A$1583,$A12,Counties!$AG$2:$AG$1583,1,Counties!$T$2:$T$1583,"<=-0.1"),"") | AB12: No votes counted yet. 2024: D+4.3; with 2022's turnout pattern D+4.9, so Flanagan can absorb up to a 4.9-pt swing toward R from 2024 and still win.
A13: MS | B13: Mississippi Senate | C13: Scott Colom | D13: Cindy Hyde-Smith | E13: =(SUMIFS(Counties!$F$2:$F$1583,Counties!$A$2:$A$1583,$A13)-SUMIFS(Counties!$G$2:$G$1583,Counties!$A$2:$A$1583,$A13))/(SUMIFS(Counties!$F$2:$F$1583,Counties!$A$2:$A$1583,$A13)+SUMIFS(Counties!$G$2:$G$1583,Counties!$A$2:$A$1583,$A13)) | F13: =-SUMIFS(Counties!$AR$2:$AR$1583,Counties!$A$2:$A$1583,$A13)/SUMIFS(Counties!$AQ$2:$AQ$1583,Counties!$A$2:$A$1583,$A13) | G13: 1 | H13: =SUMIFS(Counties!$U$2:$U$1583,Counties!$A$2:$A$1583,$A13) | I13: =SUMIFS(Counties!$AF$2:$AF$1583,Counties!$A$2:$A$1583,$A13) | J13: =IF(H13>0,I13/H13,0) | K13: =COUNTIFS(Counties!$A$2:$A$1583,$A13,Counties!$AG$2:$AG$1583,1) | L13: =COUNTIF(Counties!$A$2:$A$1583,$A13) | M13: =IF(H13>0,SUMIFS(Counties!$U$2:$U$1583,Counties!$A$2:$A$1583,$A13,Counties!$AG$2:$AG$1583,1)/H13,0) | N13: =IF(K13>0,SUMIFS(Counties!$AP$2:$AP$1583,Counties!$A$2:$A$1583,$A13)/SUMIFS(Counties!$AF$2:$AF$1583,Counties!$A$2:$A$1583,$A13,Counties!$AG$2:$AG$1583,1),"") | O13: =IF(N13="","",N13-F13) | P13: =IF(I13>0,(SUMIFS(Counties!$AD$2:$AD$1583,Counties!$A$2:$A$1583,$A13)-SUMIFS(Counties!$AE$2:$AE$1583,Counties!$A$2:$A$1583,$A13))/I13,"") | Q13: =IF(K13>0,(SUMIFS(Counties!$AL$2:$AL$1583,Counties!$A$2:$A$1583,$A13)-SUMIFS(Counties!$AM$2:$AM$1583,Counties!$A$2:$A$1583,$A13))/(SUMIFS(Counties!$AL$2:$AL$1583,Counties!$A$2:$A$1583,$A13)+SUMIFS(Counties!$AM$2:$AM$1583,Counties!$A$2:$A$1583,$A13)),"") | R13: =IF(Q13="","",IF(Q13>=0,C13,D13)&" +"&TEXT(ABS(Q13)*100,"0.0")) | S13: =IF(Q13="","",IF(Q13>=0.05,"Great for "&TRIM(RIGHT(SUBSTITUTE(C13," ",REPT(" ",50)),50)),IF(Q13>=0.01,TRIM(RIGHT(SUBSTITUTE(C13," ",REPT(" ",50)),50))&" on track",IF(Q13>-0.01,"Toss-up",IF(Q13>-0.05,TRIM(RIGHT(SUBSTITUTE(D13," ",REPT(" ",50)),50))&" on track","Great for "&TRIM(RIGHT(SUBSTITUTE(D13," ",REPT(" ",50)),50))))))) | T13: =IF(K13=0,"none",IF(OR(M13<0.1,K13<5),"low",IF(M13<0.4,"medium","high"))) | U13: =IFERROR(INDEX('Early Vote'!$C$6:$C$22,MATCH($A13,'Early Vote'!$A$6:$A$22,0)),"") | V13: =IFERROR(INDEX('Early Vote'!$E$6:$E$22,MATCH($A13,'Early Vote'!$A$6:$A$22,0)),"") | W13: =IF(K13>0,SUMIFS(Counties!$AF$2:$AF$1583,Counties!$A$2:$A$1583,$A13,Counties!$AG$2:$AG$1583,1)/SUMIFS(Counties!$AQ$2:$AQ$1583,Counties!$A$2:$A$1583,$A13,Counties!$AG$2:$AG$1583,1),"") | X13: =IF(K13>=3,W13,G13) | Y13: =SUMIFS(Counties!$AK$2:$AK$1583,Counties!$A$2:$A$1583,$A13)/SUMIFS(Counties!$AQ$2:$AQ$1583,Counties!$A$2:$A$1583,$A13) | Z13: =IFERROR(100*SUMIFS(Counties!$AF$2:$AF$1583,Counties!$A$2:$A$1583,$A13,Counties!$AG$2:$AG$1583,1,Counties!$T$2:$T$1583,">=0.1")/SUMIFS(Counties!$AT$2:$AT$1583,Counties!$A$2:$A$1583,$A13,Counties!$AG$2:$AG$1583,1,Counties!$T$2:$T$1583,">=0.1"),"") | AA13: =IFERROR(100*SUMIFS(Counties!$AF$2:$AF$1583,Counties!$A$2:$A$1583,$A13,Counties!$AG$2:$AG$1583,1,Counties!$T$2:$T$1583,"<=-0.1")/SUMIFS(Counties!$AT$2:$AT$1583,Counties!$A$2:$A$1583,$A13,Counties!$AG$2:$AG$1583,1,Counties!$T$2:$T$1583,"<=-0.1"),"") | AB13: No votes counted yet. 2024: R+23.1; with 2022's turnout pattern R+21.8, so Colom needs a 21.8-pt swing toward D from 2024 to win.
A14: NC | B14: North Carolina Senate | C14: Roy Cooper | D14: Michael Whatley | E14: =(SUMIFS(Counties!$F$2:$F$1583,Counties!$A$2:$A$1583,$A14)-SUMIFS(Counties!$G$2:$G$1583,Counties!$A$2:$A$1583,$A14))/(SUMIFS(Counties!$F$2:$F$1583,Counties!$A$2:$A$1583,$A14)+SUMIFS(Counties!$G$2:$G$1583,Counties!$A$2:$A$1583,$A14)) | F14: =-SUMIFS(Counties!$AR$2:$AR$1583,Counties!$A$2:$A$1583,$A14)/SUMIFS(Counties!$AQ$2:$AQ$1583,Counties!$A$2:$A$1583,$A14) | G14: 1 | H14: =SUMIFS(Counties!$U$2:$U$1583,Counties!$A$2:$A$1583,$A14) | I14: =SUMIFS(Counties!$AF$2:$AF$1583,Counties!$A$2:$A$1583,$A14) | J14: =IF(H14>0,I14/H14,0) | K14: =COUNTIFS(Counties!$A$2:$A$1583,$A14,Counties!$AG$2:$AG$1583,1) | L14: =COUNTIF(Counties!$A$2:$A$1583,$A14) | M14: =IF(H14>0,SUMIFS(Counties!$U$2:$U$1583,Counties!$A$2:$A$1583,$A14,Counties!$AG$2:$AG$1583,1)/H14,0) | N14: =IF(K14>0,SUMIFS(Counties!$AP$2:$AP$1583,Counties!$A$2:$A$1583,$A14)/SUMIFS(Counties!$AF$2:$AF$1583,Counties!$A$2:$A$1583,$A14,Counties!$AG$2:$AG$1583,1),"") | O14: =IF(N14="","",N14-F14) | P14: =IF(I14>0,(SUMIFS(Counties!$AD$2:$AD$1583,Counties!$A$2:$A$1583,$A14)-SUMIFS(Counties!$AE$2:$AE$1583,Counties!$A$2:$A$1583,$A14))/I14,"") | Q14: =IF(K14>0,(SUMIFS(Counties!$AL$2:$AL$1583,Counties!$A$2:$A$1583,$A14)-SUMIFS(Counties!$AM$2:$AM$1583,Counties!$A$2:$A$1583,$A14))/(SUMIFS(Counties!$AL$2:$AL$1583,Counties!$A$2:$A$1583,$A14)+SUMIFS(Counties!$AM$2:$AM$1583,Counties!$A$2:$A$1583,$A14)),"") | R14: =IF(Q14="","",IF(Q14>=0,C14,D14)&" +"&TEXT(ABS(Q14)*100,"0.0")) | S14: =IF(Q14="","",IF(Q14>=0.05,"Great for "&TRIM(RIGHT(SUBSTITUTE(C14," ",REPT(" ",50)),50)),IF(Q14>=0.01,TRIM(RIGHT(SUBSTITUTE(C14," ",REPT(" ",50)),50))&" on track",IF(Q14>-0.01,"Toss-up",IF(Q14>-0.05,TRIM(RIGHT(SUBSTITUTE(D14," ",REPT(" ",50)),50))&" on track","Great for "&TRIM(RIGHT(SUBSTITUTE(D14," ",REPT(" ",50)),50))))))) | T14: =IF(K14=0,"none",IF(OR(M14<0.1,K14<5),"low",IF(M14<0.4,"medium","high"))) | U14: =IFERROR(INDEX('Early Vote'!$C$6:$C$22,MATCH($A14,'Early Vote'!$A$6:$A$22,0)),"") | V14: =IFERROR(INDEX('Early Vote'!$E$6:$E$22,MATCH($A14,'Early Vote'!$A$6:$A$22,0)),"") | W14: =IF(K14>0,SUMIFS(Counties!$AF$2:$AF$1583,Counties!$A$2:$A$1583,$A14,Counties!$AG$2:$AG$1583,1)/SUMIFS(Counties!$AQ$2:$AQ$1583,Counties!$A$2:$A$1583,$A14,Counties!$AG$2:$AG$1583,1),"") | X14: =IF(K14>=3,W14,G14) | Y14: =SUMIFS(Counties!$AK$2:$AK$1583,Counties!$A$2:$A$1583,$A14)/SUMIFS(Counties!$AQ$2:$AQ$1583,Counties!$A$2:$A$1583,$A14) | Z14: =IFERROR(100*SUMIFS(Counties!$AF$2:$AF$1583,Counties!$A$2:$A$1583,$A14,Counties!$AG$2:$AG$1583,1,Counties!$T$2:$T$1583,">=0.1")/SUMIFS(Counties!$AT$2:$AT$1583,Counties!$A$2:$A$1583,$A14,Counties!$AG$2:$AG$1583,1,Counties!$T$2:$T$1583,">=0.1"),"") | AA14: =IFERROR(100*SUMIFS(Counties!$AF$2:$AF$1583,Counties!$A$2:$A$1583,$A14,Counties!$AG$2:$AG$1583,1,Counties!$T$2:$T$1583,"<=-0.1")/SUMIFS(Counties!$AT$2:$AT$1583,Counties!$A$2:$A$1583,$A14,Counties!$AG$2:$AG$1583,1,Counties!$T$2:$T$1583,"<=-0.1"),"") | AB14: No votes counted yet. 2024: R+3.3; with 2022's turnout pattern R+2.8, so Cooper needs a 2.8-pt swing toward D from 2024 to win. In 2022 the early vote was D+9.0 and the Election Day vote R+20.7, so counts that are mostly early votes flatter Democrats.
A15: NE | B15: Nebraska Senate | C15: Dan Osborn | D15: Pete Ricketts | E15: =(SUMIFS(Counties!$F$2:$F$1583,Counties!$A$2:$A$1583,$A15)-SUMIFS(Counties!$G$2:$G$1583,Counties!$A$2:$A$1583,$A15))/(SUMIFS(Counties!$F$2:$F$1583,Counties!$A$2:$A$1583,$A15)+SUMIFS(Counties!$G$2:$G$1583,Counties!$A$2:$A$1583,$A15)) | F15: =-SUMIFS(Counties!$AR$2:$AR$1583,Counties!$A$2:$A$1583,$A15)/SUMIFS(Counties!$AQ$2:$AQ$1583,Counties!$A$2:$A$1583,$A15) | G15: 1 | H15: =SUMIFS(Counties!$U$2:$U$1583,Counties!$A$2:$A$1583,$A15) | I15: =SUMIFS(Counties!$AF$2:$AF$1583,Counties!$A$2:$A$1583,$A15) | J15: =IF(H15>0,I15/H15,0) | K15: =COUNTIFS(Counties!$A$2:$A$1583,$A15,Counties!$AG$2:$AG$1583,1) | L15: =COUNTIF(Counties!$A$2:$A$1583,$A15) | M15: =IF(H15>0,SUMIFS(Counties!$U$2:$U$1583,Counties!$A$2:$A$1583,$A15,Counties!$AG$2:$AG$1583,1)/H15,0) | N15: =IF(K15>0,SUMIFS(Counties!$AP$2:$AP$1583,Counties!$A$2:$A$1583,$A15)/SUMIFS(Counties!$AF$2:$AF$1583,Counties!$A$2:$A$1583,$A15,Counties!$AG$2:$AG$1583,1),"") | O15: =IF(N15="","",N15-F15) | P15: =IF(I15>0,(SUMIFS(Counties!$AD$2:$AD$1583,Counties!$A$2:$A$1583,$A15)-SUMIFS(Counties!$AE$2:$AE$1583,Counties!$A$2:$A$1583,$A15))/I15,"") | Q15: =IF(K15>0,(SUMIFS(Counties!$AL$2:$AL$1583,Counties!$A$2:$A$1583,$A15)-SUMIFS(Counties!$AM$2:$AM$1583,Counties!$A$2:$A$1583,$A15))/(SUMIFS(Counties!$AL$2:$AL$1583,Counties!$A$2:$A$1583,$A15)+SUMIFS(Counties!$AM$2:$AM$1583,Counties!$A$2:$A$1583,$A15)),"") | R15: =IF(Q15="","",IF(Q15>=0,C15,D15)&" +"&TEXT(ABS(Q15)*100,"0.0")) | S15: =IF(Q15="","",IF(Q15>=0.05,"Great for "&TRIM(RIGHT(SUBSTITUTE(C15," ",REPT(" ",50)),50)),IF(Q15>=0.01,TRIM(RIGHT(SUBSTITUTE(C15," ",REPT(" ",50)),50))&" on track",IF(Q15>-0.01,"Toss-up",IF(Q15>-0.05,TRIM(RIGHT(SUBSTITUTE(D15," ",REPT(" ",50)),50))&" on track","Great for "&TRIM(RIGHT(SUBSTITUTE(D15," ",REPT(" ",50)),50))))))) | T15: =IF(K15=0,"none",IF(OR(M15<0.1,K15<5),"low",IF(M15<0.4,"medium","high"))) | U15: =IFERROR(INDEX('Early Vote'!$C$6:$C$22,MATCH($A15,'Early Vote'!$A$6:$A$22,0)),"") | V15: =IFERROR(INDEX('Early Vote'!$E$6:$E$22,MATCH($A15,'Early Vote'!$A$6:$A$22,0)),"") | W15: =IF(K15>0,SUMIFS(Counties!$AF$2:$AF$1583,Counties!$A$2:$A$1583,$A15,Counties!$AG$2:$AG$1583,1)/SUMIFS(Counties!$AQ$2:$AQ$1583,Counties!$A$2:$A$1583,$A15,Counties!$AG$2:$AG$1583,1),"") | X15: =IF(K15>=3,W15,G15) | Y15: =SUMIFS(Counties!$AK$2:$AK$1583,Counties!$A$2:$A$1583,$A15)/SUMIFS(Counties!$AQ$2:$AQ$1583,Counties!$A$2:$A$1583,$A15) | Z15: =IFERROR(100*SUMIFS(Counties!$AF$2:$AF$1583,Counties!$A$2:$A$1583,$A15,Counties!$AG$2:$AG$1583,1,Counties!$T$2:$T$1583,">=0.1")/SUMIFS(Counties!$AT$2:$AT$1583,Counties!$A$2:$A$1583,$A15,Counties!$AG$2:$AG$1583,1,Counties!$T$2:$T$1583,">=0.1"),"") | AA15: =IFERROR(100*SUMIFS(Counties!$AF$2:$AF$1583,Counties!$A$2:$A$1583,$A15,Counties!$AG$2:$AG$1583,1,Counties!$T$2:$T$1583,"<=-0.1")/SUMIFS(Counties!$AT$2:$AT$1583,Counties!$A$2:$A$1583,$A15,Counties!$AG$2:$AG$1583,1,Counties!$T$2:$T$1583,"<=-0.1"),"") | AB15: No votes counted yet. 2024: R+20.8; with 2022's turnout pattern R+21.3, so Osborn needs a 21.3-pt swing toward D from 2024 to win.
A16: NH | B16: New Hampshire Senate | C16: Chris Pappas | D16: John E. Sununu | E16: =(SUMIFS(Counties!$F$2:$F$1583,Counties!$A$2:$A$1583,$A16)-SUMIFS(Counties!$G$2:$G$1583,Counties!$A$2:$A$1583,$A16))/(SUMIFS(Counties!$F$2:$F$1583,Counties!$A$2:$A$1583,$A16)+SUMIFS(Counties!$G$2:$G$1583,Counties!$A$2:$A$1583,$A16)) | F16: =-SUMIFS(Counties!$AR$2:$AR$1583,Counties!$A$2:$A$1583,$A16)/SUMIFS(Counties!$AQ$2:$AQ$1583,Counties!$A$2:$A$1583,$A16) | G16: 1 | H16: =SUMIFS(Counties!$U$2:$U$1583,Counties!$A$2:$A$1583,$A16) | I16: =SUMIFS(Counties!$AF$2:$AF$1583,Counties!$A$2:$A$1583,$A16) | J16: =IF(H16>0,I16/H16,0) | K16: =COUNTIFS(Counties!$A$2:$A$1583,$A16,Counties!$AG$2:$AG$1583,1) | L16: =COUNTIF(Counties!$A$2:$A$1583,$A16) | M16: =IF(H16>0,SUMIFS(Counties!$U$2:$U$1583,Counties!$A$2:$A$1583,$A16,Counties!$AG$2:$AG$1583,1)/H16,0) | N16: =IF(K16>0,SUMIFS(Counties!$AP$2:$AP$1583,Counties!$A$2:$A$1583,$A16)/SUMIFS(Counties!$AF$2:$AF$1583,Counties!$A$2:$A$1583,$A16,Counties!$AG$2:$AG$1583,1),"") | O16: =IF(N16="","",N16-F16) | P16: =IF(I16>0,(SUMIFS(Counties!$AD$2:$AD$1583,Counties!$A$2:$A$1583,$A16)-SUMIFS(Counties!$AE$2:$AE$1583,Counties!$A$2:$A$1583,$A16))/I16,"") | Q16: =IF(K16>0,(SUMIFS(Counties!$AL$2:$AL$1583,Counties!$A$2:$A$1583,$A16)-SUMIFS(Counties!$AM$2:$AM$1583,Counties!$A$2:$A$1583,$A16))/(SUMIFS(Counties!$AL$2:$AL$1583,Counties!$A$2:$A$1583,$A16)+SUMIFS(Counties!$AM$2:$AM$1583,Counties!$A$2:$A$1583,$A16)),"") | R16: =IF(Q16="","",IF(Q16>=0,C16,D16)&" +"&TEXT(ABS(Q16)*100,"0.0")) | S16: =IF(Q16="","",IF(Q16>=0.05,"Great for "&TRIM(RIGHT(SUBSTITUTE(C16," ",REPT(" ",50)),50)),IF(Q16>=0.01,TRIM(RIGHT(SUBSTITUTE(C16," ",REPT(" ",50)),50))&" on track",IF(Q16>-0.01,"Toss-up",IF(Q16>-0.05,TRIM(RIGHT(SUBSTITUTE(D16," ",REPT(" ",50)),50))&" on track","Great for "&TRIM(RIGHT(SUBSTITUTE(D16," ",REPT(" ",50)),50))))))) | T16: =IF(K16=0,"none",IF(OR(M16<0.1,K16<5),"low",IF(M16<0.4,"medium","high"))) | U16: =IFERROR(INDEX('Early Vote'!$C$6:$C$22,MATCH($A16,'Early Vote'!$A$6:$A$22,0)),"") | V16: =IFERROR(INDEX('Early Vote'!$E$6:$E$22,MATCH($A16,'Early Vote'!$A$6:$A$22,0)),"") | W16: =IF(K16>0,SUMIFS(Counties!$AF$2:$AF$1583,Counties!$A$2:$A$1583,$A16,Counties!$AG$2:$AG$1583,1)/SUMIFS(Counties!$AQ$2:$AQ$1583,Counties!$A$2:$A$1583,$A16,Counties!$AG$2:$AG$1583,1),"") | X16: =IF(K16>=3,W16,G16) | Y16: =SUMIFS(Counties!$AK$2:$AK$1583,Counties!$A$2:$A$1583,$A16)/SUMIFS(Counties!$AQ$2:$AQ$1583,Counties!$A$2:$A$1583,$A16) | Z16: =IFERROR(100*SUMIFS(Counties!$AF$2:$AF$1583,Counties!$A$2:$A$1583,$A16,Counties!$AG$2:$AG$1583,1,Counties!$T$2:$T$1583,">=0.1")/SUMIFS(Counties!$AT$2:$AT$1583,Counties!$A$2:$A$1583,$A16,Counties!$AG$2:$AG$1583,1,Counties!$T$2:$T$1583,">=0.1"),"") | AA16: =IFERROR(100*SUMIFS(Counties!$AF$2:$AF$1583,Counties!$A$2:$A$1583,$A16,Counties!$AG$2:$AG$1583,1,Counties!$T$2:$T$1583,"<=-0.1")/SUMIFS(Counties!$AT$2:$AT$1583,Counties!$A$2:$A$1583,$A16,Counties!$AG$2:$AG$1583,1,Counties!$T$2:$T$1583,"<=-0.1"),"") | AB16: No votes counted yet. 2024: D+2.8; with 2022's turnout pattern D+2.8, so Pappas can absorb up to a 2.8-pt swing toward R from 2024 and still win.
A17: OH | B17: Ohio Senate | C17: Sherrod Brown | D17: Jon Husted | E17: =(SUMIFS(Counties!$F$2:$F$1583,Counties!$A$2:$A$1583,$A17)-SUMIFS(Counties!$G$2:$G$1583,Counties!$A$2:$A$1583,$A17))/(SUMIFS(Counties!$F$2:$F$1583,Counties!$A$2:$A$1583,$A17)+SUMIFS(Counties!$G$2:$G$1583,Counties!$A$2:$A$1583,$A17)) | F17: =-SUMIFS(Counties!$AR$2:$AR$1583,Counties!$A$2:$A$1583,$A17)/SUMIFS(Counties!$AQ$2:$AQ$1583,Counties!$A$2:$A$1583,$A17) | G17: 1 | H17: =SUMIFS(Counties!$U$2:$U$1583,Counties!$A$2:$A$1583,$A17) | I17: =SUMIFS(Counties!$AF$2:$AF$1583,Counties!$A$2:$A$1583,$A17) | J17: =IF(H17>0,I17/H17,0) | K17: =COUNTIFS(Counties!$A$2:$A$1583,$A17,Counties!$AG$2:$AG$1583,1) | L17: =COUNTIF(Counties!$A$2:$A$1583,$A17) | M17: =IF(H17>0,SUMIFS(Counties!$U$2:$U$1583,Counties!$A$2:$A$1583,$A17,Counties!$AG$2:$AG$1583,1)/H17,0) | N17: =IF(K17>0,SUMIFS(Counties!$AP$2:$AP$1583,Counties!$A$2:$A$1583,$A17)/SUMIFS(Counties!$AF$2:$AF$1583,Counties!$A$2:$A$1583,$A17,Counties!$AG$2:$AG$1583,1),"") | O17: =IF(N17="","",N17-F17) | P17: =IF(I17>0,(SUMIFS(Counties!$AD$2:$AD$1583,Counties!$A$2:$A$1583,$A17)-SUMIFS(Counties!$AE$2:$AE$1583,Counties!$A$2:$A$1583,$A17))/I17,"") | Q17: =IF(K17>0,(SUMIFS(Counties!$AL$2:$AL$1583,Counties!$A$2:$A$1583,$A17)-SUMIFS(Counties!$AM$2:$AM$1583,Counties!$A$2:$A$1583,$A17))/(SUMIFS(Counties!$AL$2:$AL$1583,Counties!$A$2:$A$1583,$A17)+SUMIFS(Counties!$AM$2:$AM$1583,Counties!$A$2:$A$1583,$A17)),"") | R17: =IF(Q17="","",IF(Q17>=0,C17,D17)&" +"&TEXT(ABS(Q17)*100,"0.0")) | S17: =IF(Q17="","",IF(Q17>=0.05,"Great for "&TRIM(RIGHT(SUBSTITUTE(C17," ",REPT(" ",50)),50)),IF(Q17>=0.01,TRIM(RIGHT(SUBSTITUTE(C17," ",REPT(" ",50)),50))&" on track",IF(Q17>-0.01,"Toss-up",IF(Q17>-0.05,TRIM(RIGHT(SUBSTITUTE(D17," ",REPT(" ",50)),50))&" on track","Great for "&TRIM(RIGHT(SUBSTITUTE(D17," ",REPT(" ",50)),50))))))) | T17: =IF(K17=0,"none",IF(OR(M17<0.1,K17<5),"low",IF(M17<0.4,"medium","high"))) | U17: =IFERROR(INDEX('Early Vote'!$C$6:$C$22,MATCH($A17,'Early Vote'!$A$6:$A$22,0)),"") | V17: =IFERROR(INDEX('Early Vote'!$E$6:$E$22,MATCH($A17,'Early Vote'!$A$6:$A$22,0)),"") | W17: =IF(K17>0,SUMIFS(Counties!$AF$2:$AF$1583,Counties!$A$2:$A$1583,$A17,Counties!$AG$2:$AG$1583,1)/SUMIFS(Counties!$AQ$2:$AQ$1583,Counties!$A$2:$A$1583,$A17,Counties!$AG$2:$AG$1583,1),"") | X17: =IF(K17>=3,W17,G17) | Y17: =SUMIFS(Counties!$AK$2:$AK$1583,Counties!$A$2:$A$1583,$A17)/SUMIFS(Counties!$AQ$2:$AQ$1583,Counties!$A$2:$A$1583,$A17) | Z17: =IFERROR(100*SUMIFS(Counties!$AF$2:$AF$1583,Counties!$A$2:$A$1583,$A17,Counties!$AG$2:$AG$1583,1,Counties!$T$2:$T$1583,">=0.1")/SUMIFS(Counties!$AT$2:$AT$1583,Counties!$A$2:$A$1583,$A17,Counties!$AG$2:$AG$1583,1,Counties!$T$2:$T$1583,">=0.1"),"") | AA17: =IFERROR(100*SUMIFS(Counties!$AF$2:$AF$1583,Counties!$A$2:$A$1583,$A17,Counties!$AG$2:$AG$1583,1,Counties!$T$2:$T$1583,"<=-0.1")/SUMIFS(Counties!$AT$2:$AT$1583,Counties!$A$2:$A$1583,$A17,Counties!$AG$2:$AG$1583,1,Counties!$T$2:$T$1583,"<=-0.1"),"") | AB17: No votes counted yet. 2024: R+11.3; with 2022's turnout pattern R+11.2, so Brown needs a 11.2-pt swing toward D from 2024 to win.
... A22: KY | B22: Kentucky Senate (bellwether) | C22: Charles Booker | D22: Andy Barr | E22: =(SUMIFS(Counties!$F$2:$F$1583,Counties!$A$2:$A$1583,$A22)-SUMIFS(Counties!$G$2:$G$1583,Counties!$A$2:$A$1583,$A22))/(SUMIFS(Counties!$F$2:$F$1583,Counties!$A$2:$A$1583,$A22)+SUMIFS(Counties!$G$2:$G$1583,Counties!$A$2:$A$1583,$A22)) | F22: =-SUMIFS(Counties!$AR$2:$AR$1583,Counties!$A$2:$A$1583,$A22)/SUMIFS(Counties!$AQ$2:$AQ$1583,Counties!$A$2:$A$1583,$A22) | G22: 1 | H22: =SUMIFS(Counties!$U$2:$U$1583,Counties!$A$2:$A$1583,$A22) | I22: =SUMIFS(Counties!$AF$2:$AF$1583,Counties!$A$2:$A$1583,$A22) | J22: =IF(H22>0,I22/H22,0) | K22: =COUNTIFS(Counties!$A$2:$A$1583,$A22,Counties!$AG$2:$AG$1583,1) | L22: =COUNTIF(Counties!$A$2:$A$1583,$A22) | M22: =IF(H22>0,SUMIFS(Counties!$U$2:$U$1583,Counties!$A$2:$A$1583,$A22,Counties!$AG$2:$AG$1583,1)/H22,0) | N22: =IF(K22>0,SUMIFS(Counties!$AP$2:$AP$1583,Counties!$A$2:$A$1583,$A22)/SUMIFS(Counties!$AF$2:$AF$1583,Counties!$A$2:$A$1583,$A22,Counties!$AG$2:$AG$1583,1),"") | O22: =IF(N22="","",N22-F22) | P22: =IF(I22>0,(SUMIFS(Counties!$AD$2:$AD$1583,Counties!$A$2:$A$1583,$A22)-SUMIFS(Counties!$AE$2:$AE$1583,Counties!$A$2:$A$1583,$A22))/I22,"") | Q22: =IF(K22>0,(SUMIFS(Counties!$AL$2:$AL$1583,Counties!$A$2:$A$1583,$A22)-SUMIFS(Counties!$AM$2:$AM$1583,Counties!$A$2:$A$1583,$A22))/(SUMIFS(Counties!$AL$2:$AL$1583,Counties!$A$2:$A$1583,$A22)+SUMIFS(Counties!$AM$2:$AM$1583,Counties!$A$2:$A$1583,$A22)),"") | R22: =IF(Q22="","",IF(Q22>=0,C22,D22)&" +"&TEXT(ABS(Q22)*100,"0.0")) | S22: =IF(Q22="","",IF(Q22>=0.05,"Great for "&TRIM(RIGHT(SUBSTITUTE(C22," ",REPT(" ",50)),50)),IF(Q22>=0.01,TRIM(RIGHT(SUBSTITUTE(C22," ",REPT(" ",50)),50))&" on track",IF(Q22>-0.01,"Toss-up",IF(Q22>-0.05,TRIM(RIGHT(SUBSTITUTE(D22," ",REPT(" ",50)),50))&" on track","Great for "&TRIM(RIGHT(SUBSTITUTE(D22," ",REPT(" ",50)),50))))))) | T22: =IF(K22=0,"none",IF(OR(M22<0.1,K22<5),"low",IF(M22<0.4,"medium","high"))) | U22: =IFERROR(INDEX('Early Vote'!$C$6:$C$22,MATCH($A22,'Early Vote'!$A$6:$A$22,0)),"") | V22: =IFERROR(INDEX('Early Vote'!$E$6:$E$22,MATCH($A22,'Early Vote'!$A$6:$A$22,0)),"") | W22: =IF(K22>0,SUMIFS(Counties!$AF$2:$AF$1583,Counties!$A$2:$A$1583,$A22,Counties!$AG$2:$AG$1583,1)/SUMIFS(Counties!$AQ$2:$AQ$1583,Counties!$A$2:$A$1583,$A22,Counties!$AG$2:$AG$1583,1),"") | X22: =IF(K22>=3,W22,G22) | Y22: =SUMIFS(Counties!$AK$2:$AK$1583,Counties!$A$2:$A$1583,$A22)/SUMIFS(Counties!$AQ$2:$AQ$1583,Counties!$A$2:$A$1583,$A22) | Z22: =IFERROR(100*SUMIFS(Counties!$AF$2:$AF$1583,Counties!$A$2:$A$1583,$A22,Counties!$AG$2:$AG$1583,1,Counties!$T$2:$T$1583,">=0.1")/SUMIFS(Counties!$AT$2:$AT$1583,Counties!$A$2:$A$1583,$A22,Counties!$AG$2:$AG$1583,1,Counties!$T$2:$T$1583,">=0.1"),"") | AA22: =IFERROR(100*SUMIFS(Counties!$AF$2:$AF$1583,Counties!$A$2:$A$1583,$A22,Counties!$AG$2:$AG$1583,1,Counties!$T$2:$T$1583,"<=-0.1")/SUMIFS(Counties!$AT$2:$AT$1583,Counties!$A$2:$A$1583,$A22,Counties!$AG$2:$AG$1583,1,Counties!$T$2:$T$1583,"<=-0.1"),"") | AB22: No votes counted yet. 2024: R+31.0; with 2022's turnout pattern R+29.8, so Booker needs a 29.8-pt swing toward D from 2024 to win.
A24: How to read it
A25: • Before anything is fully counted there's no projection. The raw margin will mislead early on because states count one vote method first (see each state's read).
A26: • Confidence: low under 10% of the expected vote in complete counties or fewer than 5 counties; medium under 40%; high above.
A27: • Nebraska: the Democratic side is Dan Osborn (independent). His benchmarks use Harris's 2024 margins, which understate him in rural counties (he ran 14 points ahead of Harris statewide in 2024).
A28: • Alaska reports by state House district, not county, and most results come in after 1 AM ET.
A29: • Mississippi's 2022 column is the US House races (no statewide race that year), so its 2022 margins are rough.

Sheet Key Counties
A1: Key counties: why they matter and how they're doing, on margin and turnout
A2: Break-even = the margin the Democratic side needs in that county for a statewide tie if every county swings equally from 2024 and turnout follows 2022's pattern. Turnout index = the county's votes vs its par (2022 pattern x the state's pace): 100 = in line with the state. Weak turnout in a Democratic county raises the margin it needs; strong turnout in a Republican county means Democrats must hold it closer. 'Margin + turnout' combines both in margin points; turnout columns fill in once a county is fully counted. The last row in each state is all its small-town and rural counties together.
A4: State | B4: County | C4: Why it matters | D4: What to watch | E4: Type | F4: Margin 2024 | G4: Swing 20→24 | H4: Margin 2022 | I4: Share of state vote 2024 | J4: Expected share (2022 turnout) | K4: D break-even | L4: Live margin | M4: Est. % in | N4: Live vs break-even | O4: Margin status | P4: Turnout index (100 = state pace) | Q4: Break-even at actual turnout | R4: Turnout index needed at live margin | S4: Turnout effect (pts) | T4: Margin + turnout vs tie pace (pts) | U4: Net votes vs tie pace | V4: Overall read | W4: FIPS
A5: Georgia · 2024: R+2.2 (R+1.1 with 2022's turnout pattern) · Jon Ossoff vs Mike Collins
A6: GA | B6: Fulton | C6: Largest vote bank for Democrats (Atlanta). | D6: Raw D vote margin matters more than the percentage. If turnout lags 2022, Democrats need bigger margins elsewhere. | E6: Big metro core | F6: =Counties!O101 | G6: =Counties!Q101 | H6: =Counties!R101 | I6: =Counties!S101 | J6: =Counties!AQ101/SUMIFS(Counties!$AQ:$AQ,Counties!$A:$A,"GA") | K6: =Counties!T101 | L6: =Counties!AH101 | M6: =Counties!AO101 | N6: =Counties!AN101 | O6: =IF(L6="","not in yet",IF(N6>=0.05,"Great for Ossoff",IF(N6>=0.01,"Ossoff on track",IF(N6>-0.01,"Toss-up",IF(N6>-0.05,"Collins on track","Great for Collins"))))&IF(Counties!AG101=1,""," (partial)")) | P6: =Counties!AU101 | Q6: =Counties!AV101 | R6: =Counties!AW101 | S6: =Counties!AX101 | T6: =Counties!AY101 | U6: =IF(T6="","",T6*Counties!AF101) | V6: =IF(T6="",IF(L6="","not in yet","waiting for the full count"),IF(T6>=0.05,"Great for Ossoff",IF(T6>=0.01,"Ossoff on track",IF(T6>-0.01,"Toss-up",IF(T6>-0.05,"Collins on track","Great for Collins"))))) | W6: 13121
A7: GA | B7: Gwinnett | C7: Most diverse big county in the state; swung slightly R from 2020 to 2024 as Hispanic and Asian voters moved. | D7: Whether the 2024 drift toward R continues or snaps back. Best single read on nonwhite swing voters. | E7: Big metro core | F7: =Counties!O108 | G7: =Counties!Q108 | H7: =Counties!R108 | I7: =Counties!S108 | J7: =Counties!AQ108/SUMIFS(Counties!$AQ:$AQ,Counties!$A:$A,"GA") | K7: =Counties!T108 | L7: =Counties!AH108 | M7: =Counties!AO108 | N7: =Counties!AN108 | O7: =IF(L7="","not in yet",IF(N7>=0.05,"Great for Ossoff",IF(N7>=0.01,"Ossoff on track",IF(N7>-0.01,"Toss-up",IF(N7>-0.05,"Collins on track","Great for Collins"))))&IF(Counties!AG108=1,""," (partial)")) | P7: =Counties!AU108 | Q7: =Counties!AV108 | R7: =Counties!AW108 | S7: =Counties!AX108 | T7: =Counties!AY108 | U7: =IF(T7="","",T7*Counties!AF108) | V7: =IF(T7="",IF(L7="","not in yet","waiting for the full count"),IF(T7>=0.05,"Great for Ossoff",IF(T7>=0.01,"Ossoff on track",IF(T7>-0.01,"Toss-up",IF(T7>-0.05,"Collins on track","Great for Collins"))))) | W7: 13135
A8: GA | B8: Cobb | C8: College-educated suburbs that flipped D in 2016 and kept moving left. | D8: A margin above 2024 means the suburban realignment is still paying Democrats. | E8: Big metro core | F8: =Counties!O74 | G8: =Counties!Q74 | H8: =Counties!R74 | I8: =Counties!S74 | J8: =Counties!AQ74/SUMIFS(Counties!$AQ:$AQ,Counties!$A:$A,"GA") | K8: =Counties!T74 | L8: =Counties!AH74 | M8: =Counties!AO74 | N8: =Counties!AN74 | O8: =IF(L8="","not in yet",IF(N8>=0.05,"Great for Ossoff",IF(N8>=0.01,"Ossoff on track",IF(N8>-0.01,"Toss-up",IF(N8>-0.05,"Collins on track","Great for Collins"))))&IF(Counties!AG74=1,""," (partial)")) | P8: =Counties!AU74 | Q8: =Counties!AV74 | R8: =Counties!AW74 | S8: =Counties!AX74 | T8: =Counties!AY74 | U8: =IF(T8="","",T8*Counties!AF74) | V8: =IF(T8="",IF(L8="","not in yet","waiting for the full count"),IF(T8>=0.05,"Great for Ossoff",IF(T8>=0.01,"Ossoff on track",IF(T8>-0.01,"Toss-up",IF(T8>-0.05,"Collins on track","Great for Collins"))))) | W8: 13067
A9: GA | B9: DeKalb | C9: Heavily Black, highly educated D base. | D9: Turnout versus 2022. Its margin barely moves, so the vote count is the signal. | E9: Big metro core | F9: =Counties!O84 | G9: =Counties!Q84 | H9: =Counties!R84 | I9: =Counties!S84 | J9: =Counties!AQ84/SUMIFS(Counties!$AQ:$AQ,Counties!$A:$A,"GA") | K9: =Counties!T84 | L9: =Counties!AH84 | M9: =Counties!AO84 | N9: =Counties!AN84 | O9: =IF(L9="","not in yet",IF(N9>=0.05,"Great for Ossoff",IF(N9>=0.01,"Ossoff on track",IF(N9>-0.01,"Toss-up",IF(N9>-0.05,"Collins on track","Great for Collins"))))&IF(Counties!AG84=1,""," (partial)")) | P9: =Counties!AU84 | Q9: =Counties!AV84 | R9: =Counties!AW84 | S9: =Counties!AX84 | T9: =Counties!AY84 | U9: =IF(T9="","",T9*Counties!AF84) | V9: =IF(T9="",IF(L9="","not in yet","waiting for the full count"),IF(T9>=0.05,"Great for Ossoff",IF(T9>=0.01,"Ossoff on track",IF(T9>-0.01,"Toss-up",IF(T9>-0.05,"Collins on track","Great for Collins"))))) | W9: 13089
A10: GA | B10: Cherokee | C10: Georgia's biggest Republican vote bank: a fast-growing exurb north of Atlanta that gave Trump about 63,000 net votes in 2024. | D10: Republican turnout. Its margin barely moves (R+40 in 2020, 2022 and 2024), so a turnout index under 100 here is the clearest sign of a Republican enthusiasm gap. | E10: Mid-size/working metro | F10: =Counties!O69 | G10: =Counties!Q69 | H10: =Counties!R69 | I10: =Counties!S69 | J10: =Counties!AQ69/SUMIFS(Counties!$AQ:$AQ,Counties!$A:$A,"GA") | K10: =Counties!T69 | L10: =Counties!AH69 | M10: =Counties!AO69 | N10: =Counties!AN69 | O10: =IF(L10="","not in yet",IF(N10>=0.05,"Great for Ossoff",IF(N10>=0.01,"Ossoff on track",IF(N10>-0.01,"Toss-up",IF(N10>-0.05,"Collins on track","Great for Collins"))))&IF(Counties!AG69=1,""," (partial)")) | P10: =Counties!AU69 | Q10: =Counties!AV69 | R10: =Counties!AW69 | S10: =Counties!AX69 | T10: =Counties!AY69 | U10: =IF(T10="","",T10*Counties!AF69) | V10: =IF(T10="",IF(L10="","not in yet","waiting for the full count"),IF(T10>=0.05,"Great for Ossoff",IF(T10>=0.01,"Ossoff on track",IF(T10>-0.01,"Toss-up",IF(T10>-0.05,"Collins on track","Great for Collins"))))) | W10: 13057
A11: GA | B11: Chatham | C11: Savannah. A mid-size D county with a large Black population. | D11: A non-Atlanta check on Black turnout and margin. | E11: Mid-size/working metro | F11: =Counties!O66 | G11: =Counties!Q66 | H11: =Counties!R66 | I11: =Counties!S66 | J11: =Counties!AQ66/SUMIFS(Counties!$AQ:$AQ,Counties!$A:$A,"GA") | K11: =Counties!T66 | L11: =Counties!AH66 | M11: =Counties!AO66 | N11: =Counties!AN66 | O11: =IF(L11="","not in yet",IF(N11>=0.05,"Great for Ossoff",IF(N11>=0.01,"Ossoff on track",IF(N11>-0.01,"Toss-up",IF(N11>-0.05,"Collins on track","Great for Collins"))))&IF(Counties!AG66=1,""," (partial)")) | P11: =Counties!AU66 | Q11: =Counties!AV66 | R11: =Counties!AW66 | S11: =Counties!AX66 | T11: =Counties!AY66 | U11: =IF(T11="","",T11*Counties!AF66) | V11: =IF(T11="",IF(L11="","not in yet","waiting for the full count"),IF(T11>=0.05,"Great for Ossoff",IF(T11>=0.01,"Ossoff on track",IF(T11>-0.01,"Toss-up",IF(T11>-0.05,"Collins on track","Great for Collins"))))) | W11: 13051
A12: GA | B12: Forsyth | C12: Wealthy, college-educated exurb that's still strongly R. | D12: Any shrinking of the R margin here signals college-educated Republicans defecting. | E12: College suburb/metro | F12: =Counties!O99 | G12: =Counties!Q99 | H12: =Counties!R99 | I12: =Counties!S99 | J12: =Counties!AQ99/SUMIFS(Counties!$AQ:$AQ,Counties!$A:$A,"GA") | K12: =Counties!T99 | L12: =Counties!AH99 | M12: =Counties!AO99 | N12: =Counties!AN99 | O12: =IF(L12="","not in yet",IF(N12>=0.05,"Great for Ossoff",IF(N12>=0.01,"Ossoff on track",IF(N12>-0.01,"Toss-up",IF(N12>-0.05,"Collins on track","Great for Collins"))))&IF(Counties!AG99=1,""," (partial)")) | P12: =Counties!AU99 | Q12: =Counties!AV99 | R12: =Counties!AW99 | S12: =Counties!AX99 | T12: =Counties!AY99 | U12: =IF(T12="","",T12*Counties!AF99) | V12: =IF(T12="",IF(L12="","not in yet","waiting for the full count"),IF(T12>=0.05,"Great for Ossoff",IF(T12>=0.01,"Ossoff on track",IF(T12>-0.01,"Toss-up",IF(T12>-0.05,"Collins on track","Great for Collins"))))) | W12: 13117
A13: GA | B13: Henry | C13: Fast-growing Black suburb south of Atlanta, and the biggest D gain of any large Georgia county from 2020 to 2024 (about 9 points). | D13: Whether that gain holds in a midterm with lower Black turnout. | E13: Black Belt | F13: =Counties!O116 | G13: =Counties!Q116 | H13: =Counties!R116 | I13: =Counties!S116 | J13: =Counties!AQ116/SUMIFS(Counties!$AQ:$AQ,Counties!$A:$A,"GA") | K13: =Counties!T116 | L13: =Counties!AH116 | M13: =Counties!AO116 | N13: =Counties!AN116 | O13: =IF(L13="","not in yet",IF(N13>=0.05,"Great for Ossoff",IF(N13>=0.01,"Ossoff on track",IF(N13>-0.01,"Toss-up",IF(N13>-0.05,"Collins on track","Great for Collins"))))&IF(Counties!AG116=1,""," (partial)")) | P13: =Counties!AU116 | Q13: =Counties!AV116 | R13: =Counties!AW116 | S13: =Counties!AX116 | T13: =Counties!AY116 | U13: =IF(T13="","",T13*Counties!AF116) | V13: =IF(T13="",IF(L13="","not in yet","waiting for the full count"),IF(T13>=0.05,"Great for Ossoff",IF(T13>=0.01,"Ossoff on track",IF(T13>-0.01,"Toss-up",IF(T13>-0.05,"Collins on track","Great for Collins"))))) | W13: 13151
A14: GA | B14: Clayton | C14: Most Democratic county in Georgia, majority Black. | D14: Turnout. Its margin barely moves, so the raw vote count is what matters. | E14: Black Belt | F14: =Counties!O72 | G14: =Counties!Q72 | H14: =Counties!R72 | I14: =Counties!S72 | J14: =Counties!AQ72/SUMIFS(Counties!$AQ:$AQ,Counties!$A:$A,"GA") | K14: =Counties!T72 | L14: =Counties!AH72 | M14: =Counties!AO72 | N14: =Counties!AN72 | O14: =IF(L14="","not in yet",IF(N14>=0.05,"Great for Ossoff",IF(N14>=0.01,"Ossoff on track",IF(N14>-0.01,"Toss-up",IF(N14>-0.05,"Collins on track","Great for Collins"))))&IF(Counties!AG72=1,""," (partial)")) | P14: =Counties!AU72 | Q14: =Counties!AV72 | R14: =Counties!AW72 | S14: =Counties!AX72 | T14: =Counties!AY72 | U14: =IF(T14="","",T14*Counties!AF72) | V14: =IF(T14="",IF(L14="","not in yet","waiting for the full count"),IF(T14>=0.05,"Great for Ossoff",IF(T14>=0.01,"Ossoff on track",IF(T14>-0.01,"Toss-up",IF(T14>-0.05,"Collins on track","Great for Collins"))))) | W14: 13063
A15: GA | B15: Hall | C15: Gainesville. The third-biggest R net-vote county, and nearly 30% Hispanic. | D15: Margin and turnout both. An R margin well under R+44 points to Hispanic voters moving back toward Democrats; turnout under the state pace means the exurban base isn't showing up. | E15: Mid-size/working metro | F15: =Counties!O110 | G15: =Counties!Q110 | H15: =Counties!R110 | I15: =Counties!S110 | J15: =Counties!AQ110/SUMIFS(Counties!$AQ:$AQ,Counties!$A:$A,"GA") | K15: =Counties!T110 | L15: =Counties!AH110 | M15: =Counties!AO110 | N15: =Counties!AN110 | O15: =IF(L15="","not in yet",IF(N15>=0.05,"Great for Ossoff",IF(N15>=0.01,"Ossoff on track",IF(N15>-0.01,"Toss-up",IF(N15>-0.05,"Collins on track","Great for Collins"))))&IF(Counties!AG110=1,""," (partial)")) | P15: =Counties!AU110 | Q15: =Counties!AV110 | R15: =Counties!AW110 | S15: =Counties!AX110 | T15: =Counties!AY110 | U15: =IF(T15="","",T15*Counties!AF110) | V15: =IF(T15="",IF(L15="","not in yet","waiting for the full count"),IF(T15>=0.05,"Great for Ossoff",IF(T15>=0.01,"Ossoff on track",IF(T15>-0.01,"Toss-up",IF(T15>-0.05,"Collins on track","Great for Collins"))))) | W15: 13139
A16: GA | B16: Bartow | C16: Northwest Georgia exurb along I-75 at R+51, a stand-in for the small-town Republican base. | D16: Turnout. The margin is locked in (R+51 in 2020, 2022 and 2024), so the vote count is the signal. | E16: Mid-size/working metro | F16: =Counties!O49 | G16: =Counties!Q49 | H16: =Counties!R49 | I16: =Counties!S49 | J16: =Counties!AQ49/SUMIFS(Counties!$AQ:$AQ,Counties!$A:$A,"GA") | K16: =Counties!T49 | L16: =Counties!AH49 | M16: =Counties!AO49 | N16: =Counties!AN49 | O16: =IF(L16="","not in yet",IF(N16>=0.05,"Great for Ossoff",IF(N16>=0.01,"Ossoff on track",IF(N16>-0.01,"Toss-up",IF(N16>-0.05,"Collins on track","Great for Collins"))))&IF(Counties!AG49=1,""," (partial)")) | P16: =Counties!AU49 | Q16: =Counties!AV49 | R16: =Counties!AW49 | S16: =Counties!AX49 | T16: =Counties!AY49 | U16: =IF(T16="","",T16*Counties!AF49) | V16: =IF(T16="",IF(L16="","not in yet","waiting for the full count"),IF(T16>=0.05,"Great for Ossoff",IF(T16>=0.01,"Ossoff on track",IF(T16>-0.01,"Toss-up",IF(T16>-0.05,"Collins on track","Great for Collins"))))) | W16: 13015
A17: GA | B17: All rural (103) | C17: Every small-town and rural county together: the Republican base's turnout test. | D17: Turnout index from its finished counties. Above 100 means the rural base is a bigger share of the vote than a tie assumes; the margin rarely moves much. | E17: Small town & rural | F17: =Types!M9 | J17: =Types!L9 | K17: =Types!P9 | L17: =Types!S9 | M17: =IFERROR(Types!E9/Types!D9,"") | N17: =IF(L17="","",L17-K17) | O17: =IF(Types!F9=0,"not in yet",IF(N17>=0.05,"Great for Ossoff",IF(N17>=0.01,"Ossoff on track",IF(N17>-0.01,"Toss-up",IF(N17>-0.05,"Collins on track","Great for Collins"))))&" (projected)") | P17: =Types!V9 | Q17: =Types!W9 | S17: =IF(Q17="","",K17-Q17) | T17: =Types!X9 | U17: =Types!Y9 | V17: =IF(T17="","not in yet",IF(T17>=0.05,"Great for Ossoff",IF(T17>=0.01,"Ossoff on track",IF(T17>-0.01,"Toss-up",IF(T17>-0.05,"Collins on track","Great for Collins"))))&" (finished counties)")
A18: Iowa · 2024: R+13.4 (R+13.2 with 2022's turnout pattern) · Josh Turek vs Ashley Hinson
A19: IA | B19: Polk | C19: Des Moines. The D vote bank, about 15% of the state's vote. | D19: Margin and turnout. Democrats need it well above 2024's +11. | E19: Mid-size/working metro | F19: =Counties!O277 | G19: =Counties!Q277 | H19: =Counties!R277 | I19: =Counties!S277 | J19: =Counties!AQ277/SUMIFS(Counties!$AQ:$AQ,Counties!$A:$A,"IA") | K19: =Counties!T277 | L19: =Counties!AH277 | M19: =Counties!AO277 | N19: =Counties!AN277 | O19: =IF(L19="","not in yet",IF(N19>=0.05,"Great for Turek",IF(N19>=0.01,"Turek on track",IF(N19>-0.01,"Toss-up",IF(N19>-0.05,"Hinson on track","Great for Hinson"))))&IF(Counties!AG277=1,""," (partial)")) | P19: =Counties!AU277 | Q19: =Counties!AV277 | R19: =Counties!AW277 | S19: =Counties!AX277 | T19: =Counties!AY277 | U19: =IF(T19="","",T19*Counties!AF277) | V19: =IF(T19="",IF(L19="","not in yet","waiting for the full count"),IF(T19>=0.05,"Great for Turek",IF(T19>=0.01,"Turek on track",IF(T19>-0.01,"Toss-up",IF(T19>-0.05,"Hinson on track","Great for Hinson"))))) | W19: 19153
A20: IA | B20: Linn | C20: Cedar Rapids. A union county that's been sliding toward R. | D20: A D margin near +15 is a good sign. | E20: Mid-size/working metro | F20: =Counties!O257 | G20: =Counties!Q257 | H20: =Counties!R257 | I20: =Counties!S257 | J20: =Counties!AQ257/SUMIFS(Counties!$AQ:$AQ,Counties!$A:$A,"IA") | K20: =Counties!T257 | L20: =Counties!AH257 | M20: =Counties!AO257 | N20: =Counties!AN257 | O20: =IF(L20="","not in yet",IF(N20>=0.05,"Great for Turek",IF(N20>=0.01,"Turek on track",IF(N20>-0.01,"Toss-up",IF(N20>-0.05,"Hinson on track","Great for Hinson"))))&IF(Counties!AG257=1,""," (partial)")) | P20: =Counties!AU257 | Q20: =Counties!AV257 | R20: =Counties!AW257 | S20: =Counties!AX257 | T20: =Counties!AY257 | U20: =IF(T20="","",T20*Counties!AF257) | V20: =IF(T20="",IF(L20="","not in yet","waiting for the full count"),IF(T20>=0.05,"Great for Turek",IF(T20>=0.01,"Turek on track",IF(T20>-0.01,"Toss-up",IF(T20>-0.05,"Hinson on track","Great for Hinson"))))) | W20: 19113
A21: IA | B21: Scott | C21: Davenport. Former D county that went R in 2024. | D21: Classic Mississippi River swing county. | E21: Mid-size/working metro | F21: =Counties!O282 | G21: =Counties!Q282 | H21: =Counties!R282 | I21: =Counties!S282 | J21: =Counties!AQ282/SUMIFS(Counties!$AQ:$AQ,Counties!$A:$A,"IA") | K21: =Counties!T282 | L21: =Counties!AH282 | M21: =Counties!AO282 | N21: =Counties!AN282 | O21: =IF(L21="","not in yet",IF(N21>=0.05,"Great for Turek",IF(N21>=0.01,"Turek on track",IF(N21>-0.01,"Toss-up",IF(N21>-0.05,"Hinson on track","Great for Hinson"))))&IF(Counties!AG282=1,""," (partial)")) | P21: =Counties!AU282 | Q21: =Counties!AV282 | R21: =Counties!AW282 | S21: =Counties!AX282 | T21: =Counties!AY282 | U21: =IF(T21="","",T21*Counties!AF282) | V21: =IF(T21="",IF(L21="","not in yet","waiting for the full count"),IF(T21>=0.05,"Great for Turek",IF(T21>=0.01,"Turek on track",IF(T21>-0.01,"Toss-up",IF(T21>-0.05,"Hinson on track","Great for Hinson"))))) | W21: 19163
A22: IA | B22: Johnson | C22: Iowa City. University of Iowa, very D. | D22: Student turnout. | E22: College suburb/metro | F22: =Counties!O252 | G22: =Counties!Q252 | H22: =Counties!R252 | I22: =Counties!S252 | J22: =Counties!AQ252/SUMIFS(Counties!$AQ:$AQ,Counties!$A:$A,"IA") | K22: =Counties!T252 | L22: =Counties!AH252 | M22: =Counties!AO252 | N22: =Counties!AN252 | O22: =IF(L22="","not in yet",IF(N22>=0.05,"Great for Turek",IF(N22>=0.01,"Turek on track",IF(N22>-0.01,"Toss-up",IF(N22>-0.05,"Hinson on track","Great for Hinson"))))&IF(Counties!AG252=1,""," (partial)")) | P22: =Counties!AU252 | Q22: =Counties!AV252 | R22: =Counties!AW252 | S22: =Counties!AX252 | T22: =Counties!AY252 | U22: =IF(T22="","",T22*Counties!AF252) | V22: =IF(T22="",IF(L22="","not in yet","waiting for the full count"),IF(T22>=0.05,"Great for Turek",IF(T22>=0.01,"Turek on track",IF(T22>-0.01,"Toss-up",IF(T22>-0.05,"Hinson on track","Great for Hinson"))))) | W22: 19103
A23: IA | B23: Black Hawk | C23: Waterloo. Union and Black voters, almost tied in 2024. | D23: Working-class D strength. | E23: Mid-size/working metro | F23: =Counties!O207 | G23: =Counties!Q207 | H23: =Counties!R207 | I23: =Counties!S207 | J23: =Counties!AQ207/SUMIFS(Counties!$AQ:$AQ,Counties!$A:$A,"IA") | K23: =Counties!T207 | L23: =Counties!AH207 | M23: =Counties!AO207 | N23: =Counties!AN207 | O23: =IF(L23="","not in yet",IF(N23>=0.05,"Great for Turek",IF(N23>=0.01,"Turek on track",IF(N23>-0.01,"Toss-up",IF(N23>-0.05,"Hinson on track","Great for Hinson"))))&IF(Counties!AG207=1,""," (partial)")) | P23: =Counties!AU207 | Q23: =Counties!AV207 | R23: =Counties!AW207 | S23: =Counties!AX207 | T23: =Counties!AY207 | U23: =IF(T23="","",T23*Counties!AF207) | V23: =IF(T23="",IF(L23="","not in yet","waiting for the full count"),IF(T23>=0.05,"Great for Turek",IF(T23>=0.01,"Turek on track",IF(T23>-0.01,"Toss-up",IF(T23>-0.05,"Hinson on track","Great for Hinson"))))) | W23: 19013
A24: IA | B24: Dallas | C24: Fast-growing, college-educated Des Moines suburb, still R. | D24: Suburban defections. Flipping it would be a big D night. | E24: College suburb/metro | F24: =Counties!O225 | G24: =Counties!Q225 | H24: =Counties!R225 | I24: =Counties!S225 | J24: =Counties!AQ225/SUMIFS(Counties!$AQ:$AQ,Counties!$A:$A,"IA") | K24: =Counties!T225 | L24: =Counties!AH225 | M24: =Counties!AO225 | N24: =Counties!AN225 | O24: =IF(L24="","not in yet",IF(N24>=0.05,"Great for Turek",IF(N24>=0.01,"Turek on track",IF(N24>-0.01,"Toss-up",IF(N24>-0.05,"Hinson on track","Great for Hinson"))))&IF(Counties!AG225=1,""," (partial)")) | P24: =Counties!AU225 | Q24: =Counties!AV225 | R24: =Counties!AW225 | S24: =Counties!AX225 | T24: =Counties!AY225 | U24: =IF(T24="","",T24*Counties!AF225) | V24: =IF(T24="",IF(L24="","not in yet","waiting for the full count"),IF(T24>=0.05,"Great for Turek",IF(T24>=0.01,"Turek on track",IF(T24>-0.01,"Toss-up",IF(T24>-0.05,"Hinson on track","Great for Hinson"))))) | W24: 19049
A25: IA | B25: Dubuque | C25: Catholic working-class river county that went from D to R. | D25: Ancestral Democrats returning or not. | E25: Small town & rural | F25: =Counties!O231 | G25: =Counties!Q231 | H25: =Counties!R231 | I25: =Counties!S231 | J25: =Counties!AQ231/SUMIFS(Counties!$AQ:$AQ,Counties!$A:$A,"IA") | K25: =Counties!T231 | L25: =Counties!AH231 | M25: =Counties!AO231 | N25: =Counties!AN231 | O25: =IF(L25="","not in yet",IF(N25>=0.05,"Great for Turek",IF(N25>=0.01,"Turek on track",IF(N25>-0.01,"Toss-up",IF(N25>-0.05,"Hinson on track","Great for Hinson"))))&IF(Counties!AG231=1,""," (partial)")) | P25: =Counties!AU231 | Q25: =Counties!AV231 | R25: =Counties!AW231 | S25: =Counties!AX231 | T25: =Counties!AY231 | U25: =IF(T25="","",T25*Counties!AF231) | V25: =IF(T25="",IF(L25="","not in yet","waiting for the full count"),IF(T25>=0.05,"Great for Turek",IF(T25>=0.01,"Turek on track",IF(T25>-0.01,"Toss-up",IF(T25>-0.05,"Hinson on track","Great for Hinson"))))) | W25: 19061
A26: IA | B26: Pottawattamie | C26: Council Bluffs, Iowa's side of metro Omaha: working-class and R+20. | D26: Working-class swing: R+17 in 2020, R+20 in 2024. Its turnout also tests whether the Republican base outside the big metros is showing up. | E26: Small town & rural | F26: =Counties!O278 | G26: =Counties!Q278 | H26: =Counties!R278 | I26: =Counties!S278 | J26: =Counties!AQ278/SUMIFS(Counties!$AQ:$AQ,Counties!$A:$A,"IA") | K26: =Counties!T278 | L26: =Counties!AH278 | M26: =Counties!AO278 | N26: =Counties!AN278 | O26: =IF(L26="","not in yet",IF(N26>=0.05,"Great for Turek",IF(N26>=0.01,"Turek on track",IF(N26>-0.01,"Toss-up",IF(N26>-0.05,"Hinson on track","Great for Hinson"))))&IF(Counties!AG278=1,""," (partial)")) | P26: =Counties!AU278 | Q26: =Counties!AV278 | R26: =Counties!AW278 | S26: =Counties!AX278 | T26: =Counties!AY278 | U26: =IF(T26="","",T26*Counties!AF278) | V26: =IF(T26="",IF(L26="","not in yet","waiting for the full count"),IF(T26>=0.05,"Great for Turek",IF(T26>=0.01,"Turek on track",IF(T26>-0.01,"Toss-up",IF(T26>-0.05,"Hinson on track","Great for Hinson"))))) | W26: 19155
A27: IA | B27: Woodbury | C27: Sioux City, 20% Hispanic; moved 7.5 pts toward R from 2020 to 2024. | D27: Hispanic and working-class voters. A margin back toward 2020 (R+16) is good for Democrats. | E27: Mid-size/working metro | F27: =Counties!O297 | G27: =Counties!Q297 | H27: =Counties!R297 | I27: =Counties!S297 | J27: =Counties!AQ297/SUMIFS(Counties!$AQ:$AQ,Counties!$A:$A,"IA") | K27: =Counties!T297 | L27: =Counties!AH297 | M27: =Counties!AO297 | N27: =Counties!AN297 | O27: =IF(L27="","not in yet",IF(N27>=0.05,"Great for Turek",IF(N27>=0.01,"Turek on track",IF(N27>-0.01,"Toss-up",IF(N27>-0.05,"Hinson on track","Great for Hinson"))))&IF(Counties!AG297=1,""," (partial)")) | P27: =Counties!AU297 | Q27: =Counties!AV297 | R27: =Counties!AW297 | S27: =Counties!AX297 | T27: =Counties!AY297 | U27: =IF(T27="","",T27*Counties!AF297) | V27: =IF(T27="",IF(L27="","not in yet","waiting for the full count"),IF(T27>=0.05,"Great for Turek",IF(T27>=0.01,"Turek on track",IF(T27>-0.01,"Toss-up",IF(T27>-0.05,"Hinson on track","Great for Hinson"))))) | W27: 19193
A28: IA | B28: Sioux | C28: Iowa's most Republican county (R+72), the core of northwest Iowa's Republican base. | D28: Turnout. The margin is maxed out, so the R vote count is the signal. | E28: Small town & rural | F28: =Counties!O284 | G28: =Counties!Q284 | H28: =Counties!R284 | I28: =Counties!S284 | J28: =Counties!AQ284/SUMIFS(Counties!$AQ:$AQ,Counties!$A:$A,"IA") | K28: =Counties!T284 | L28: =Counties!AH284 | M28: =Counties!AO284 | N28: =Counties!AN284 | O28: =IF(L28="","not in yet",IF(N28>=0.05,"Great for Turek",IF(N28>=0.01,"Turek on track",IF(N28>-0.01,"Toss-up",IF(N28>-0.05,"Hinson on track","Great for Hinson"))))&IF(Counties!AG284=1,""," (partial)")) | P28: =Counties!AU284 | Q28: =Counties!AV284 | R28: =Counties!AW284 | S28: =Counties!AX284 | T28: =Counties!AY284 | U28: =IF(T28="","",T28*Counties!AF284) | V28: =IF(T28="",IF(L28="","not in yet","waiting for the full count"),IF(T28>=0.05,"Great for Turek",IF(T28>=0.01,"Turek on track",IF(T28>-0.01,"Toss-up",IF(T28>-0.05,"Hinson on track","Great for Hinson"))))) | W28: 19167
A29: IA | B29: All rural (92) | C29: Every small-town and rural county together: the Republican base's turnout test. | D29: Turnout index from its finished counties. Above 100 means the rural base is a bigger share of the vote than a tie assumes; the margin rarely moves much. | E29: Small town & rural | F29: =Types!M12 | J29: =Types!L12 | K29: =Types!P12 | L29: =Types!S12 | M29: =IFERROR(Types!E12/Types!D12,"") | N29: =IF(L29="","",L29-K29) | O29: =IF(Types!F12=0,"not in yet",IF(N29>=0.05,"Great for Turek",IF(N29>=0.01,"Turek on track",IF(N29>-0.01,"Toss-up",IF(N29>-0.05,"Hinson on track","Great for Hinson"))))&" (projected)") | P29: =Types!V12 | Q29: =Types!W12 | S29: =IF(Q29="","",K29-Q29) | T29: =Types!X12 | U29: =Types!Y12 | V29: =IF(T29="","not in yet",IF(T29>=0.05,"Great for Turek",IF(T29>=0.01,"Turek on track",IF(T29>-0.01,"Toss-up",IF(T29>-0.05,"Hinson on track","Great for Hinson"))))&" (finished counties)")
A30: Kansas · 2024: R+16.4 (R+16.5 with 2022's turnout pattern) · Adam Hamilton vs Roger Marshall
A31: KS | B31: Johnson | C31: Kansas City suburbs. A quarter of the state's vote, college-educated, trending D. | D31: A big D margin here is required for any upset. | E31: College suburb/metro | F31: =Counties!O345 | G31: =Counties!Q345 | H31: =Counties!R345 | I31: =Counties!S345 | J31: =Counties!AQ345/SUMIFS(Counties!$AQ:$AQ,Counties!$A:$A,"KS") | K31: =Counties!T345 | L31: =Counties!AH345 | M31: =Counties!AO345 | N31: =Counties!AN345 | O31: =IF(L31="","not in yet",IF(N31>=0.05,"Great for Hamilton",IF(N31>=0.01,"Hamilton on track",IF(N31>-0.01,"Toss-up",IF(N31>-0.05,"Marshall on track","Great for Marshall"))))&IF(Counties!AG345=1,""," (partial)")) | P31: =Counties!AU345 | Q31: =Counties!AV345 | R31: =Counties!AW345 | S31: =Counties!AX345 | T31: =Counties!AY345 | U31: =IF(T31="","",T31*Counties!AF345) | V31: =IF(T31="",IF(L31="","not in yet","waiting for the full count"),IF(T31>=0.05,"Great for Hamilton",IF(T31>=0.01,"Hamilton on track",IF(T31>-0.01,"Toss-up",IF(T31>-0.05,"Marshall on track","Great for Marshall"))))) | W31: 20091
A32: KS | B32: Sedgwick | C32: Wichita. R-leaning swing county. | D32: If Democrats get within single digits, they're competitive statewide. | E32: Mid-size/working metro | F32: =Counties!O386 | G32: =Counties!Q386 | H32: =Counties!R386 | I32: =Counties!S386 | J32: =Counties!AQ386/SUMIFS(Counties!$AQ:$AQ,Counties!$A:$A,"KS") | K32: =Counties!T386 | L32: =Counties!AH386 | M32: =Counties!AO386 | N32: =Counties!AN386 | O32: =IF(L32="","not in yet",IF(N32>=0.05,"Great for Hamilton",IF(N32>=0.01,"Hamilton on track",IF(N32>-0.01,"Toss-up",IF(N32>-0.05,"Marshall on track","Great for Marshall"))))&IF(Counties!AG386=1,""," (partial)")) | P32: =Counties!AU386 | Q32: =Counties!AV386 | R32: =Counties!AW386 | S32: =Counties!AX386 | T32: =Counties!AY386 | U32: =IF(T32="","",T32*Counties!AF386) | V32: =IF(T32="",IF(L32="","not in yet","waiting for the full count"),IF(T32>=0.05,"Great for Hamilton",IF(T32>=0.01,"Hamilton on track",IF(T32>-0.01,"Toss-up",IF(T32>-0.05,"Marshall on track","Great for Marshall"))))) | W32: 20173
A33: KS | B33: Shawnee | C33: Topeka. Roughly even in 2024. | D33: Democrats need to win it clearly for an upset. | E33: Mid-size/working metro | F33: =Counties!O388 | G33: =Counties!Q388 | H33: =Counties!R388 | I33: =Counties!S388 | J33: =Counties!AQ388/SUMIFS(Counties!$AQ:$AQ,Counties!$A:$A,"KS") | K33: =Counties!T388 | L33: =Counties!AH388 | M33: =Counties!AO388 | N33: =Counties!AN388 | O33: =IF(L33="","not in yet",IF(N33>=0.05,"Great for Hamilton",IF(N33>=0.01,"Hamilton on track",IF(N33>-0.01,"Toss-up",IF(N33>-0.05,"Marshall on track","Great for Marshall"))))&IF(Counties!AG388=1,""," (partial)")) | P33: =Counties!AU388 | Q33: =Counties!AV388 | R33: =Counties!AW388 | S33: =Counties!AX388 | T33: =Counties!AY388 | U33: =IF(T33="","",T33*Counties!AF388) | V33: =IF(T33="",IF(L33="","not in yet","waiting for the full count"),IF(T33>=0.05,"Great for Hamilton",IF(T33>=0.01,"Hamilton on track",IF(T33>-0.01,"Toss-up",IF(T33>-0.05,"Marshall on track","Great for Marshall"))))) | W33: 20177
A34: KS | B34: Douglas | C34: Lawrence (KU). Very D. | D34: Student turnout. | E34: College suburb/metro | F34: =Counties!O322 | G34: =Counties!Q322 | H34: =Counties!R322 | I34: =Counties!S322 | J34: =Counties!AQ322/SUMIFS(Counties!$AQ:$AQ,Counties!$A:$A,"KS") | K34: =Counties!T322 | L34: =Counties!AH322 | M34: =Counties!AO322 | N34: =Counties!AN322 | O34: =IF(L34="","not in yet",IF(N34>=0.05,"Great for Hamilton",IF(N34>=0.01,"Hamilton on track",IF(N34>-0.01,"Toss-up",IF(N34>-0.05,"Marshall on track","Great for Marshall"))))&IF(Counties!AG322=1,""," (partial)")) | P34: =Counties!AU322 | Q34: =Counties!AV322 | R34: =Counties!AW322 | S34: =Counties!AX322 | T34: =Counties!AY322 | U34: =IF(T34="","",T34*Counties!AF322) | V34: =IF(T34="",IF(L34="","not in yet","waiting for the full count"),IF(T34>=0.05,"Great for Hamilton",IF(T34>=0.01,"Hamilton on track",IF(T34>-0.01,"Toss-up",IF(T34>-0.05,"Marshall on track","Great for Marshall"))))) | W34: 20045
A35: KS | B35: Wyandotte | C35: Kansas City, Kansas. Black and Hispanic D base that swung R in 2024. | D35: Turnout and Hispanic swing. | E35: Mid-size/working metro | F35: =Counties!O404 | G35: =Counties!Q404 | H35: =Counties!R404 | I35: =Counties!S404 | J35: =Counties!AQ404/SUMIFS(Counties!$AQ:$AQ,Counties!$A:$A,"KS") | K35: =Counties!T404 | L35: =Counties!AH404 | M35: =Counties!AO404 | N35: =Counties!AN404 | O35: =IF(L35="","not in yet",IF(N35>=0.05,"Great for Hamilton",IF(N35>=0.01,"Hamilton on track",IF(N35>-0.01,"Toss-up",IF(N35>-0.05,"Marshall on track","Great for Marshall"))))&IF(Counties!AG404=1,""," (partial)")) | P35: =Counties!AU404 | Q35: =Counties!AV404 | R35: =Counties!AW404 | S35: =Counties!AX404 | T35: =Counties!AY404 | U35: =IF(T35="","",T35*Counties!AF404) | V35: =IF(T35="",IF(L35="","not in yet","waiting for the full count"),IF(T35>=0.05,"Great for Hamilton",IF(T35>=0.01,"Hamilton on track",IF(T35>-0.01,"Toss-up",IF(T35>-0.05,"Marshall on track","Great for Marshall"))))) | W35: 20209
A36: KS | B36: Butler | C36: Wichita's eastern exurb and the biggest R net-vote county after Sedgwick. | D36: Turnout plus a margin near R+42. A softer margin means suburban Wichita Republicans are drifting. | E36: Small town & rural | F36: =Counties!O307 | G36: =Counties!Q307 | H36: =Counties!R307 | I36: =Counties!S307 | J36: =Counties!AQ307/SUMIFS(Counties!$AQ:$AQ,Counties!$A:$A,"KS") | K36: =Counties!T307 | L36: =Counties!AH307 | M36: =Counties!AO307 | N36: =Counties!AN307 | O36: =IF(L36="","not in yet",IF(N36>=0.05,"Great for Hamilton",IF(N36>=0.01,"Hamilton on track",IF(N36>-0.01,"Toss-up",IF(N36>-0.05,"Marshall on track","Great for Marshall"))))&IF(Counties!AG307=1,""," (partial)")) | P36: =Counties!AU307 | Q36: =Counties!AV307 | R36: =Counties!AW307 | S36: =Counties!AX307 | T36: =Counties!AY307 | U36: =IF(T36="","",T36*Counties!AF307) | V36: =IF(T36="",IF(L36="","not in yet","waiting for the full count"),IF(T36>=0.05,"Great for Hamilton",IF(T36>=0.01,"Hamilton on track",IF(T36>-0.01,"Toss-up",IF(T36>-0.05,"Marshall on track","Great for Marshall"))))) | W36: 20015
A37: KS | B37: Reno | C37: Hutchinson. A small-city county that stands in for central Kansas. | D37: Midterm turnout leans R here: R+45 in the 2022 Senate race vs R+35 in 2024. Republicans want it closer to 2022. | E37: Small town & rural | F37: =Counties!O377 | G37: =Counties!Q377 | H37: =Counties!R377 | I37: =Counties!S377 | J37: =Counties!AQ377/SUMIFS(Counties!$AQ:$AQ,Counties!$A:$A,"KS") | K37: =Counties!T377 | L37: =Counties!AH377 | M37: =Counties!AO377 | N37: =Counties!AN377 | O37: =IF(L37="","not in yet",IF(N37>=0.05,"Great for Hamilton",IF(N37>=0.01,"Hamilton on track",IF(N37>-0.01,"Toss-up",IF(N37>-0.05,"Marshall on track","Great for Marshall"))))&IF(Counties!AG377=1,""," (partial)")) | P37: =Counties!AU377 | Q37: =Counties!AV377 | R37: =Counties!AW377 | S37: =Counties!AX377 | T37: =Counties!AY377 | U37: =IF(T37="","",T37*Counties!AF377) | V37: =IF(T37="",IF(L37="","not in yet","waiting for the full count"),IF(T37>=0.05,"Great for Hamilton",IF(T37>=0.01,"Hamilton on track",IF(T37>-0.01,"Toss-up",IF(T37>-0.05,"Marshall on track","Great for Marshall"))))) | W37: 20155
A38: KS | B38: Riley | C38: Manhattan (K-State, Fort Riley). Swingy college town. | D38: Youth turnout. | E38: Small town & rural | F38: =Counties!O380 | G38: =Counties!Q380 | H38: =Counties!R380 | I38: =Counties!S380 | J38: =Counties!AQ380/SUMIFS(Counties!$AQ:$AQ,Counties!$A:$A,"KS") | K38: =Counties!T380 | L38: =Counties!AH380 | M38: =Counties!AO380 | N38: =Counties!AN380 | O38: =IF(L38="","not in yet",IF(N38>=0.05,"Great for Hamilton",IF(N38>=0.01,"Hamilton on track",IF(N38>-0.01,"Toss-up",IF(N38>-0.05,"Marshall on track","Great for Marshall"))))&IF(Counties!AG380=1,""," (partial)")) | P38: =Counties!AU380 | Q38: =Counties!AV380 | R38: =Counties!AW380 | S38: =Counties!AX380 | T38: =Counties!AY380 | U38: =IF(T38="","",T38*Counties!AF380) | V38: =IF(T38="",IF(L38="","not in yet","waiting for the full count"),IF(T38>=0.05,"Great for Hamilton",IF(T38>=0.01,"Hamilton on track",IF(T38>-0.01,"Toss-up",IF(T38>-0.05,"Marshall on track","Great for Marshall"))))) | W38: 20161
A39: KS | B39: All rural (94) | C39: Every small-town and rural county together: the Republican base's turnout test. | D39: Turnout index from its finished counties. Above 100 means the rural base is a bigger share of the vote than a tie assumes; the margin rarely moves much. | E39: Small town & rural | F39: =Types!M16 | J39: =Types!L16 | K39: =Types!P16 | L39: =Types!S16 | M39: =IFERROR(Types!E16/Types!D16,"") | N39: =IF(L39="","",L39-K39) | O39: =IF(Types!F16=0,"not in yet",IF(N39>=0.05,"Great for Hamilton",IF(N39>=0.01,"Hamilton on track",IF(N39>-0.01,"Toss-up",IF(N39>-0.05,"Marshall on track","Great for Marshall"))))&" (projected)") | P39: =Types!V16 | Q39: =Types!W16 | S39: =IF(Q39="","",K39-Q39) | T39: =Types!X16 | U39: =Types!Y16 | V39: =IF(T39="","not in yet",IF(T39>=0.05,"Great for Hamilton",IF(T39>=0.01,"Hamilton on track",IF(T39>-0.01,"Toss-up",IF(T39>-0.05,"Marshall on track","Great for Marshall"))))&" (finished counties)")
A40: Maine · 2024: D+7.1 (D+7.2 with 2022's turnout pattern) · Troy Jackson vs Susan Collins
A41: ME | B41: Cumberland | C41: Portland. A quarter of the state's vote and very D. | D41: Margin and turnout. Collins has historically cut into it. | E41: College suburb/metro | F41: =Counties!O407 | G41: =Counties!Q407 | H41: =Counties!R407 | I41: =Counties!S407 | J41: =Counties!AQ407/SUMIFS(Counties!$AQ:$AQ,Counties!$A:$A,"ME") | K41: =Counties!T407 | L41: =Counties!AH407 | M41: =Counties!AO407 | N41: =Counties!AN407 | O41: =IF(L41="","not in yet",IF(N41>=0.05,"Great for Jackson",IF(N41>=0.01,"Jackson on track",IF(N41>-0.01,"Toss-up",IF(N41>-0.05,"Collins on track","Great for Collins"))))&IF(Counties!AG407=1,""," (partial)")) | P41: =Counties!AU407 | Q41: =Counties!AV407 | R41: =Counties!AW407 | S41: =Counties!AX407 | T41: =Counties!AY407 | U41: =IF(T41="","",T41*Counties!AF407) | V41: =IF(T41="",IF(L41="","not in yet","waiting for the full count"),IF(T41>=0.05,"Great for Jackson",IF(T41>=0.01,"Jackson on track",IF(T41>-0.01,"Toss-up",IF(T41>-0.05,"Collins on track","Great for Collins"))))) | W41: 23005
A42: ME | B42: York | C42: Southern Maine. Bigger and more swingy than Cumberland. | D42: Collins's crossover strength. Democrats want about +15. | E42: Mid-size/working metro | F42: =Counties!O420 | G42: =Counties!Q420 | H42: =Counties!R420 | I42: =Counties!S420 | J42: =Counties!AQ420/SUMIFS(Counties!$AQ:$AQ,Counties!$A:$A,"ME") | K42: =Counties!T420 | L42: =Counties!AH420 | M42: =Counties!AO420 | N42: =Counties!AN420 | O42: =IF(L42="","not in yet",IF(N42>=0.05,"Great for Jackson",IF(N42>=0.01,"Jackson on track",IF(N42>-0.01,"Toss-up",IF(N42>-0.05,"Collins on track","Great for Collins"))))&IF(Counties!AG420=1,""," (partial)")) | P42: =Counties!AU420 | Q42: =Counties!AV420 | R42: =Counties!AW420 | S42: =Counties!AX420 | T42: =Counties!AY420 | U42: =IF(T42="","",T42*Counties!AF420) | V42: =IF(T42="",IF(L42="","not in yet","waiting for the full count"),IF(T42>=0.05,"Great for Jackson",IF(T42>=0.01,"Jackson on track",IF(T42>-0.01,"Toss-up",IF(T42>-0.05,"Collins on track","Great for Collins"))))) | W42: 23031
A43: ME | B43: Penobscot | C43: Bangor. The 2nd District's population center, leans R. | D43: Jackson is from northern Maine. Watch whether he cuts into the R margin here. | E43: Mid-size/working metro | F43: =Counties!O414 | G43: =Counties!Q414 | H43: =Counties!R414 | I43: =Counties!S414 | J43: =Counties!AQ414/SUMIFS(Counties!$AQ:$AQ,Counties!$A:$A,"ME") | K43: =Counties!T414 | L43: =Counties!AH414 | M43: =Counties!AO414 | N43: =Counties!AN414 | O43: =IF(L43="","not in yet",IF(N43>=0.05,"Great for Jackson",IF(N43>=0.01,"Jackson on track",IF(N43>-0.01,"Toss-up",IF(N43>-0.05,"Collins on track","Great for Collins"))))&IF(Counties!AG414=1,""," (partial)")) | P43: =Counties!AU414 | Q43: =Counties!AV414 | R43: =Counties!AW414 | S43: =Counties!AX414 | T43: =Counties!AY414 | U43: =IF(T43="","",T43*Counties!AF414) | V43: =IF(T43="",IF(L43="","not in yet","waiting for the full count"),IF(T43>=0.05,"Great for Jackson",IF(T43>=0.01,"Jackson on track",IF(T43>-0.01,"Toss-up",IF(T43>-0.05,"Collins on track","Great for Collins"))))) | W43: 23019
A44: ME | B44: Kennebec | C44: Augusta. Roughly even, about 10 points right of the state in 2024. | D44: A Jackson win here would point to a comfortable statewide win. | E44: Mid-size/working metro | F44: =Counties!O410 | G44: =Counties!Q410 | H44: =Counties!R410 | I44: =Counties!S410 | J44: =Counties!AQ410/SUMIFS(Counties!$AQ:$AQ,Counties!$A:$A,"ME") | K44: =Counties!T410 | L44: =Counties!AH410 | M44: =Counties!AO410 | N44: =Counties!AN410 | O44: =IF(L44="","not in yet",IF(N44>=0.05,"Great for Jackson",IF(N44>=0.01,"Jackson on track",IF(N44>-0.01,"Toss-up",IF(N44>-0.05,"Collins on track","Great for Collins"))))&IF(Counties!AG410=1,""," (partial)")) | P44: =Counties!AU410 | Q44: =Counties!AV410 | R44: =Counties!AW410 | S44: =Counties!AX410 | T44: =Counties!AY410 | U44: =IF(T44="","",T44*Counties!AF410) | V44: =IF(T44="",IF(L44="","not in yet","waiting for the full count"),IF(T44>=0.05,"Great for Jackson",IF(T44>=0.01,"Jackson on track",IF(T44>-0.01,"Toss-up",IF(T44>-0.05,"Collins on track","Great for Collins"))))) | W44: 23011
A45: ME | B45: Androscoggin | C45: Lewiston-Auburn. A blue-collar former D county that now leans R. | D45: Working-class swing. | E45: Mid-size/working metro | F45: =Counties!O405 | G45: =Counties!Q405 | H45: =Counties!R405 | I45: =Counties!S405 | J45: =Counties!AQ405/SUMIFS(Counties!$AQ:$AQ,Counties!$A:$A,"ME") | K45: =Counties!T405 | L45: =Counties!AH405 | M45: =Counties!AO405 | N45: =Counties!AN405 | O45: =IF(L45="","not in yet",IF(N45>=0.05,"Great for Jackson",IF(N45>=0.01,"Jackson on track",IF(N45>-0.01,"Toss-up",IF(N45>-0.05,"Collins on track","Great for Collins"))))&IF(Counties!AG405=1,""," (partial)")) | P45: =Counties!AU405 | Q45: =Counties!AV405 | R45: =Counties!AW405 | S45: =Counties!AX405 | T45: =Counties!AY405 | U45: =IF(T45="","",T45*Counties!AF405) | V45: =IF(T45="",IF(L45="","not in yet","waiting for the full count"),IF(T45>=0.05,"Great for Jackson",IF(T45>=0.01,"Jackson on track",IF(T45>-0.01,"Toss-up",IF(T45>-0.05,"Collins on track","Great for Collins"))))) | W45: 23001
A46: ME | B46: Aroostook | C46: The County. Rural far north, where Jackson is from. | D46: A home-region bounce for Jackson would show up here first. | E46: Small town & rural | F46: =Counties!O406 | G46: =Counties!Q406 | H46: =Counties!R406 | I46: =Counties!S406 | J46: =Counties!AQ406/SUMIFS(Counties!$AQ:$AQ,Counties!$A:$A,"ME") | K46: =Counties!T406 | L46: =Counties!AH406 | M46: =Counties!AO406 | N46: =Counties!AN406 | O46: =IF(L46="","not in yet",IF(N46>=0.05,"Great for Jackson",IF(N46>=0.01,"Jackson on track",IF(N46>-0.01,"Toss-up",IF(N46>-0.05,"Collins on track","Great for Collins"))))&IF(Counties!AG406=1,""," (partial)")) | P46: =Counties!AU406 | Q46: =Counties!AV406 | R46: =Counties!AW406 | S46: =Counties!AX406 | T46: =Counties!AY406 | U46: =IF(T46="","",T46*Counties!AF406) | V46: =IF(T46="",IF(L46="","not in yet","waiting for the full count"),IF(T46>=0.05,"Great for Jackson",IF(T46>=0.01,"Jackson on track",IF(T46>-0.01,"Toss-up",IF(T46>-0.05,"Collins on track","Great for Collins"))))) | W46: 23003
A47: ME | B47: Somerset | C47: Rural central Maine (Skowhegan), R+28 and among the three biggest R net-vote counties. | D47: Rural Republican turnout in the 2nd District. It moved 3.5 pts toward R from 2020 to 2024 but was only R+19 in the 2022 governor race. | E47: Small town & rural | F47: =Counties!O417 | G47: =Counties!Q417 | H47: =Counties!R417 | I47: =Counties!S417 | J47: =Counties!AQ417/SUMIFS(Counties!$AQ:$AQ,Counties!$A:$A,"ME") | K47: =Counties!T417 | L47: =Counties!AH417 | M47: =Counties!AO417 | N47: =Counties!AN417 | O47: =IF(L47="","not in yet",IF(N47>=0.05,"Great for Jackson",IF(N47>=0.01,"Jackson on track",IF(N47>-0.01,"Toss-up",IF(N47>-0.05,"Collins on track","Great for Collins"))))&IF(Counties!AG417=1,""," (partial)")) | P47: =Counties!AU417 | Q47: =Counties!AV417 | R47: =Counties!AW417 | S47: =Counties!AX417 | T47: =Counties!AY417 | U47: =IF(T47="","",T47*Counties!AF417) | V47: =IF(T47="",IF(L47="","not in yet","waiting for the full count"),IF(T47>=0.05,"Great for Jackson",IF(T47>=0.01,"Jackson on track",IF(T47>-0.01,"Toss-up",IF(T47>-0.05,"Collins on track","Great for Collins"))))) | W47: 23025
A48: ME | B48: All rural (11) | C48: Every small-town and rural county together: the Republican base's turnout test. | D48: Turnout index from its finished counties. Above 100 means the rural base is a bigger share of the vote than a tie assumes; the margin rarely moves much. | E48: Small town & rural | F48: =Types!M19 | J48: =Types!L19 | K48: =Types!P19 | L48: =Types!S19 | M48: =IFERROR(Types!E19/Types!D19,"") | N48: =IF(L48="","",L48-K48) | O48: =IF(Types!F19=0,"not in yet",IF(N48>=0.05,"Great for Jackson",IF(N48>=0.01,"Jackson on track",IF(N48>-0.01,"Toss-up",IF(N48>-0.05,"Collins on track","Great for Collins"))))&" (projected)") | P48: =Types!V19 | Q48: =Types!W19 | S48: =IF(Q48="","",K48-Q48) | T48: =Types!X19 | U48: =Types!Y19 | V48: =IF(T48="","not in yet",IF(T48>=0.05,"Great for Jackson",IF(T48>=0.01,"Jackson on track",IF(T48>-0.01,"Toss-up",IF(T48>-0.05,"Collins on track","Great for Collins"))))&" (finished counties)")
A49: Michigan · 2024: R+1.4 (R+1.8 with 2022's turnout pattern) · Abdul El-Sayed vs Mike Rogers
A50: MI | B50: Wayne | C50: Detroit and its inner suburbs. The biggest D vote bank, which collapsed 8.6 points toward R in 2024 (including Dearborn's Arab American vote). | D50: Detroit turnout and Dearborn-area margins. A rebound toward 2022's +44 is the clearest D path. | E50: Big metro core | F50: =Counties!O502 | G50: =Counties!Q502 | H50: =Counties!R502 | I50: =Counties!S502 | J50: =Counties!AQ502/SUMIFS(Counties!$AQ:$AQ,Counties!$A:$A,"MI") | K50: =Counties!T502 | L50: =Counties!AH502 | M50: =Counties!AO502 | N50: =Counties!AN502 | O50: =IF(L50="","not in yet",IF(N50>=0.05,"Great for El-Sayed",IF(N50>=0.01,"El-Sayed on track",IF(N50>-0.01,"Toss-up",IF(N50>-0.05,"Rogers on track","Great for Rogers"))))&IF(Counties!AG502=1,""," (partial)")) | P50: =Counties!AU502 | Q50: =Counties!AV502 | R50: =Counties!AW502 | S50: =Counties!AX502 | T50: =Counties!AY502 | U50: =IF(T50="","",T50*Counties!AF502) | V50: =IF(T50="",IF(L50="","not in yet","waiting for the full count"),IF(T50>=0.05,"Great for El-Sayed",IF(T50>=0.01,"El-Sayed on track",IF(T50>-0.01,"Toss-up",IF(T50>-0.05,"Rogers on track","Great for Rogers"))))) | W50: 26163
A51: MI | B51: Oakland | C51: Large, educated suburban county that anchors D statewide wins. | D51: Margin. It was D+23 in 2022 (Whitmer) but only D+11 for Harris. | E51: Big metro core | F51: =Counties!O483 | G51: =Counties!Q483 | H51: =Counties!R483 | I51: =Counties!S483 | J51: =Counties!AQ483/SUMIFS(Counties!$AQ:$AQ,Counties!$A:$A,"MI") | K51: =Counties!T483 | L51: =Counties!AH483 | M51: =Counties!AO483 | N51: =Counties!AN483 | O51: =IF(L51="","not in yet",IF(N51>=0.05,"Great for El-Sayed",IF(N51>=0.01,"El-Sayed on track",IF(N51>-0.01,"Toss-up",IF(N51>-0.05,"Rogers on track","Great for Rogers"))))&IF(Counties!AG483=1,""," (partial)")) | P51: =Counties!AU483 | Q51: =Counties!AV483 | R51: =Counties!AW483 | S51: =Counties!AX483 | T51: =Counties!AY483 | U51: =IF(T51="","",T51*Counties!AF483) | V51: =IF(T51="",IF(L51="","not in yet","waiting for the full count"),IF(T51>=0.05,"Great for El-Sayed",IF(T51>=0.01,"El-Sayed on track",IF(T51>-0.01,"Toss-up",IF(T51>-0.05,"Rogers on track","Great for Rogers"))))) | W51: 26125
A52: MI | B52: Macomb | C52: Classic blue-collar bellwether that went R+14 in 2024. | D52: Whether Democrats get it back toward even, as Whitmer did in 2022 (D+5). | E52: Big metro core | F52: =Counties!O470 | G52: =Counties!Q470 | H52: =Counties!R470 | I52: =Counties!S470 | J52: =Counties!AQ470/SUMIFS(Counties!$AQ:$AQ,Counties!$A:$A,"MI") | K52: =Counties!T470 | L52: =Counties!AH470 | M52: =Counties!AO470 | N52: =Counties!AN470 | O52: =IF(L52="","not in yet",IF(N52>=0.05,"Great for El-Sayed",IF(N52>=0.01,"El-Sayed on track",IF(N52>-0.01,"Toss-up",IF(N52>-0.05,"Rogers on track","Great for Rogers"))))&IF(Counties!AG470=1,""," (partial)")) | P52: =Counties!AU470 | Q52: =Counties!AV470 | R52: =Counties!AW470 | S52: =Counties!AX470 | T52: =Counties!AY470 | U52: =IF(T52="","",T52*Counties!AF470) | V52: =IF(T52="",IF(L52="","not in yet","waiting for the full count"),IF(T52>=0.05,"Great for El-Sayed",IF(T52>=0.01,"El-Sayed on track",IF(T52>-0.01,"Toss-up",IF(T52>-0.05,"Rogers on track","Great for Rogers"))))) | W52: 26099
A53: MI | B53: Kent | C53: Grand Rapids. West Michigan swing county, D since 2020. | D53: College-educated and religious voters. A margin above +10 is very good for D. | E53: Mid-size/working metro | F53: =Counties!O461 | G53: =Counties!Q461 | H53: =Counties!R461 | I53: =Counties!S461 | J53: =Counties!AQ461/SUMIFS(Counties!$AQ:$AQ,Counties!$A:$A,"MI") | K53: =Counties!T461 | L53: =Counties!AH461 | M53: =Counties!AO461 | N53: =Counties!AN461 | O53: =IF(L53="","not in yet",IF(N53>=0.05,"Great for El-Sayed",IF(N53>=0.01,"El-Sayed on track",IF(N53>-0.01,"Toss-up",IF(N53>-0.05,"Rogers on track","Great for Rogers"))))&IF(Counties!AG461=1,""," (partial)")) | P53: =Counties!AU461 | Q53: =Counties!AV461 | R53: =Counties!AW461 | S53: =Counties!AX461 | T53: =Counties!AY461 | U53: =IF(T53="","",T53*Counties!AF461) | V53: =IF(T53="",IF(L53="","not in yet","waiting for the full count"),IF(T53>=0.05,"Great for El-Sayed",IF(T53>=0.01,"El-Sayed on track",IF(T53>-0.01,"Toss-up",IF(T53>-0.05,"Rogers on track","Great for Rogers"))))) | W53: 26081
A54: MI | B54: Genesee | C54: Flint. A union-heavy county where the D margin has been eroding. | D54: Working-class Black and white voters. A margin near 2022's +19 is a strong D sign. | E54: Mid-size/working metro | F54: =Counties!O445 | G54: =Counties!Q445 | H54: =Counties!R445 | I54: =Counties!S445 | J54: =Counties!AQ445/SUMIFS(Counties!$AQ:$AQ,Counties!$A:$A,"MI") | K54: =Counties!T445 | L54: =Counties!AH445 | M54: =Counties!AO445 | N54: =Counties!AN445 | O54: =IF(L54="","not in yet",IF(N54>=0.05,"Great for El-Sayed",IF(N54>=0.01,"El-Sayed on track",IF(N54>-0.01,"Toss-up",IF(N54>-0.05,"Rogers on track","Great for Rogers"))))&IF(Counties!AG445=1,""," (partial)")) | P54: =Counties!AU445 | Q54: =Counties!AV445 | R54: =Counties!AW445 | S54: =Counties!AX445 | T54: =Counties!AY445 | U54: =IF(T54="","",T54*Counties!AF445) | V54: =IF(T54="",IF(L54="","not in yet","waiting for the full count"),IF(T54>=0.05,"Great for El-Sayed",IF(T54>=0.01,"El-Sayed on track",IF(T54>-0.01,"Toss-up",IF(T54>-0.05,"Rogers on track","Great for Rogers"))))) | W54: 26049
A55: MI | B55: Washtenaw | C55: Ann Arbor. Students and university staff. | D55: Turnout, especially campus precincts. Midterm youth turnout drops are the risk. | E55: College suburb/metro | F55: =Counties!O501 | G55: =Counties!Q501 | H55: =Counties!R501 | I55: =Counties!S501 | J55: =Counties!AQ501/SUMIFS(Counties!$AQ:$AQ,Counties!$A:$A,"MI") | K55: =Counties!T501 | L55: =Counties!AH501 | M55: =Counties!AO501 | N55: =Counties!AN501 | O55: =IF(L55="","not in yet",IF(N55>=0.05,"Great for El-Sayed",IF(N55>=0.01,"El-Sayed on track",IF(N55>-0.01,"Toss-up",IF(N55>-0.05,"Rogers on track","Great for Rogers"))))&IF(Counties!AG501=1,""," (partial)")) | P55: =Counties!AU501 | Q55: =Counties!AV501 | R55: =Counties!AW501 | S55: =Counties!AX501 | T55: =Counties!AY501 | U55: =IF(T55="","",T55*Counties!AF501) | V55: =IF(T55="",IF(L55="","not in yet","waiting for the full count"),IF(T55>=0.05,"Great for El-Sayed",IF(T55>=0.01,"El-Sayed on track",IF(T55>-0.01,"Toss-up",IF(T55>-0.05,"Rogers on track","Great for Rogers"))))) | W55: 26161
A56: MI | B56: Ottawa | C56: Deep-red, religious, increasingly college-educated West Michigan suburb. | D56: The R margin shrinking below 20 means GOP erosion with educated conservatives. | E56: Mid-size/working metro | F56: =Counties!O490 | G56: =Counties!Q490 | H56: =Counties!R490 | I56: =Counties!S490 | J56: =Counties!AQ490/SUMIFS(Counties!$AQ:$AQ,Counties!$A:$A,"MI") | K56: =Counties!T490 | L56: =Counties!AH490 | M56: =Counties!AO490 | N56: =Counties!AN490 | O56: =IF(L56="","not in yet",IF(N56>=0.05,"Great for El-Sayed",IF(N56>=0.01,"El-Sayed on track",IF(N56>-0.01,"Toss-up",IF(N56>-0.05,"Rogers on track","Great for Rogers"))))&IF(Counties!AG490=1,""," (partial)")) | P56: =Counties!AU490 | Q56: =Counties!AV490 | R56: =Counties!AW490 | S56: =Counties!AX490 | T56: =Counties!AY490 | U56: =IF(T56="","",T56*Counties!AF490) | V56: =IF(T56="",IF(L56="","not in yet","waiting for the full count"),IF(T56>=0.05,"Great for El-Sayed",IF(T56>=0.01,"El-Sayed on track",IF(T56>-0.01,"Toss-up",IF(T56>-0.05,"Rogers on track","Great for Rogers"))))) | W56: 26139
A57: MI | B57: Livingston | C57: Affluent, college-educated exurb between Detroit and Lansing: R+24 in 2024 but only R+13 in the 2022 governor race. | D57: Whether Republicans hold their presidential margin in a midterm. Closer to 2022's R+13 than 2024's R+24 means suburban Republicans are defecting or staying home. | E57: Mid-size/working metro | F57: =Counties!O467 | G57: =Counties!Q467 | H57: =Counties!R467 | I57: =Counties!S467 | J57: =Counties!AQ467/SUMIFS(Counties!$AQ:$AQ,Counties!$A:$A,"MI") | K57: =Counties!T467 | L57: =Counties!AH467 | M57: =Counties!AO467 | N57: =Counties!AN467 | O57: =IF(L57="","not in yet",IF(N57>=0.05,"Great for El-Sayed",IF(N57>=0.01,"El-Sayed on track",IF(N57>-0.01,"Toss-up",IF(N57>-0.05,"Rogers on track","Great for Rogers"))))&IF(Counties!AG467=1,""," (partial)")) | P57: =Counties!AU467 | Q57: =Counties!AV467 | R57: =Counties!AW467 | S57: =Counties!AX467 | T57: =Counties!AY467 | U57: =IF(T57="","",T57*Counties!AF467) | V57: =IF(T57="",IF(L57="","not in yet","waiting for the full count"),IF(T57>=0.05,"Great for El-Sayed",IF(T57>=0.01,"El-Sayed on track",IF(T57>-0.01,"Toss-up",IF(T57>-0.05,"Rogers on track","Great for Rogers"))))) | W57: 26093
A58: MI | B58: Saginaw | C58: Long-running bellwether that has gone with the statewide winner in most recent races. | D58: Whoever wins it likely wins the state. | E58: Mid-size/working metro | F58: =Counties!O493 | G58: =Counties!Q493 | H58: =Counties!R493 | I58: =Counties!S493 | J58: =Counties!AQ493/SUMIFS(Counties!$AQ:$AQ,Counties!$A:$A,"MI") | K58: =Counties!T493 | L58: =Counties!AH493 | M58: =Counties!AO493 | N58: =Counties!AN493 | O58: =IF(L58="","not in yet",IF(N58>=0.05,"Great for El-Sayed",IF(N58>=0.01,"El-Sayed on track",IF(N58>-0.01,"Toss-up",IF(N58>-0.05,"Rogers on track","Great for Rogers"))))&IF(Counties!AG493=1,""," (partial)")) | P58: =Counties!AU493 | Q58: =Counties!AV493 | R58: =Counties!AW493 | S58: =Counties!AX493 | T58: =Counties!AY493 | U58: =IF(T58="","",T58*Counties!AF493) | V58: =IF(T58="",IF(L58="","not in yet","waiting for the full count"),IF(T58>=0.05,"Great for El-Sayed",IF(T58>=0.01,"El-Sayed on track",IF(T58>-0.01,"Toss-up",IF(T58>-0.05,"Rogers on track","Great for Rogers"))))) | W58: 26145
A59: MI | B59: St. Clair | C59: Blue-collar Thumb county (Port Huron) that moved 4.4 pts toward R from 2020 to 2024. | D59: Working-class Republican turnout. Its 2022 margin (R+17) was half its 2024 margin, so a midterm drop-off among these voters shows up here first. | E59: Mid-size/working metro | F59: =Counties!O497 | G59: =Counties!Q497 | H59: =Counties!R497 | I59: =Counties!S497 | J59: =Counties!AQ497/SUMIFS(Counties!$AQ:$AQ,Counties!$A:$A,"MI") | K59: =Counties!T497 | L59: =Counties!AH497 | M59: =Counties!AO497 | N59: =Counties!AN497 | O59: =IF(L59="","not in yet",IF(N59>=0.05,"Great for El-Sayed",IF(N59>=0.01,"El-Sayed on track",IF(N59>-0.01,"Toss-up",IF(N59>-0.05,"Rogers on track","Great for Rogers"))))&IF(Counties!AG497=1,""," (partial)")) | P59: =Counties!AU497 | Q59: =Counties!AV497 | R59: =Counties!AW497 | S59: =Counties!AX497 | T59: =Counties!AY497 | U59: =IF(T59="","",T59*Counties!AF497) | V59: =IF(T59="",IF(L59="","not in yet","waiting for the full count"),IF(T59>=0.05,"Great for El-Sayed",IF(T59>=0.01,"El-Sayed on track",IF(T59>-0.01,"Toss-up",IF(T59>-0.05,"Rogers on track","Great for Rogers"))))) | W59: 26147
A60: MI | B60: All rural (63) | C60: Every small-town and rural county together: the Republican base's turnout test. | D60: Turnout index from its finished counties. Above 100 means the rural base is a bigger share of the vote than a tie assumes; the margin rarely moves much. | E60: Small town & rural | F60: =Types!M23 | J60: =Types!L23 | K60: =Types!P23 | L60: =Types!S23 | M60: =IFERROR(Types!E23/Types!D23,"") | N60: =IF(L60="","",L60-K60) | O60: =IF(Types!F23=0,"not in yet",IF(N60>=0.05,"Great for El-Sayed",IF(N60>=0.01,"El-Sayed on track",IF(N60>-0.01,"Toss-up",IF(N60>-0.05,"Rogers on track","Great for Rogers"))))&" (projected)") | P60: =Types!V23 | Q60: =Types!W23 | S60: =IF(Q60="","",K60-Q60) | T60: =Types!X23 | U60: =Types!Y23 | V60: =IF(T60="","not in yet",IF(T60>=0.05,"Great for El-Sayed",IF(T60>=0.01,"El-Sayed on track",IF(T60>-0.01,"Toss-up",IF(T60>-0.05,"Rogers on track","Great for Rogers"))))&" (finished counties)")
A61: Minnesota · 2024: D+4.3 (D+4.9 with 2022's turnout pattern) · Peggy Flanagan vs Michele Tafoya
A62: MN | B62: Hennepin | C62: Minneapolis. The giant D vote bank, about 22% of the state. | D62: Turnout. Its margin is near the ceiling. | E62: Big metro core | F62: =Counties!O530 | G62: =Counties!Q530 | H62: =Counties!R530 | I62: =Counties!S530 | J62: =Counties!AQ530/SUMIFS(Counties!$AQ:$AQ,Counties!$A:$A,"MN") | K62: =Counties!T530 | L62: =Counties!AH530 | M62: =Counties!AO530 | N62: =Counties!AN530 | O62: =IF(L62="","not in yet",IF(N62>=0.05,"Great for Flanagan",IF(N62>=0.01,"Flanagan on track",IF(N62>-0.01,"Toss-up",IF(N62>-0.05,"Tafoya on track","Great for Tafoya"))))&IF(Counties!AG530=1,""," (partial)")) | P62: =Counties!AU530 | Q62: =Counties!AV530 | R62: =Counties!AW530 | S62: =Counties!AX530 | T62: =Counties!AY530 | U62: =IF(T62="","",T62*Counties!AF530) | V62: =IF(T62="",IF(L62="","not in yet","waiting for the full count"),IF(T62>=0.05,"Great for Flanagan",IF(T62>=0.01,"Flanagan on track",IF(T62>-0.01,"Toss-up",IF(T62>-0.05,"Tafoya on track","Great for Tafoya"))))) | W62: 27053
A63: MN | B63: Ramsey | C63: St. Paul. Very D. | D63: Turnout. | E63: College suburb/metro | F63: =Counties!O565 | G63: =Counties!Q565 | H63: =Counties!R565 | I63: =Counties!S565 | J63: =Counties!AQ565/SUMIFS(Counties!$AQ:$AQ,Counties!$A:$A,"MN") | K63: =Counties!T565 | L63: =Counties!AH565 | M63: =Counties!AO565 | N63: =Counties!AN565 | O63: =IF(L63="","not in yet",IF(N63>=0.05,"Great for Flanagan",IF(N63>=0.01,"Flanagan on track",IF(N63>-0.01,"Toss-up",IF(N63>-0.05,"Tafoya on track","Great for Tafoya"))))&IF(Counties!AG565=1,""," (partial)")) | P63: =Counties!AU565 | Q63: =Counties!AV565 | R63: =Counties!AW565 | S63: =Counties!AX565 | T63: =Counties!AY565 | U63: =IF(T63="","",T63*Counties!AF565) | V63: =IF(T63="",IF(L63="","not in yet","waiting for the full count"),IF(T63>=0.05,"Great for Flanagan",IF(T63>=0.01,"Flanagan on track",IF(T63>-0.01,"Toss-up",IF(T63>-0.05,"Tafoya on track","Great for Tafoya"))))) | W63: 27123
A64: MN | B64: Dakota | C64: Southern Twin Cities suburbs, D-leaning swing. | D64: Margin above +13 (2024) is good for Flanagan. | E64: College suburb/metro | F64: =Counties!O522 | G64: =Counties!Q522 | H64: =Counties!R522 | I64: =Counties!S522 | J64: =Counties!AQ522/SUMIFS(Counties!$AQ:$AQ,Counties!$A:$A,"MN") | K64: =Counties!T522 | L64: =Counties!AH522 | M64: =Counties!AO522 | N64: =Counties!AN522 | O64: =IF(L64="","not in yet",IF(N64>=0.05,"Great for Flanagan",IF(N64>=0.01,"Flanagan on track",IF(N64>-0.01,"Toss-up",IF(N64>-0.05,"Tafoya on track","Great for Tafoya"))))&IF(Counties!AG522=1,""," (partial)")) | P64: =Counties!AU522 | Q64: =Counties!AV522 | R64: =Counties!AW522 | S64: =Counties!AX522 | T64: =Counties!AY522 | U64: =IF(T64="","",T64*Counties!AF522) | V64: =IF(T64="",IF(L64="","not in yet","waiting for the full count"),IF(T64>=0.05,"Great for Flanagan",IF(T64>=0.01,"Flanagan on track",IF(T64>-0.01,"Toss-up",IF(T64>-0.05,"Tafoya on track","Great for Tafoya"))))) | W64: 27037
A65: MN | B65: Anoka | C65: Northern suburbs, R-leaning blue-collar swing. | D65: Tafoya needs a clear win here. | E65: Mid-size/working metro | F65: =Counties!O505 | G65: =Counties!Q505 | H65: =Counties!R505 | I65: =Counties!S505 | J65: =Counties!AQ505/SUMIFS(Counties!$AQ:$AQ,Counties!$A:$A,"MN") | K65: =Counties!T505 | L65: =Counties!AH505 | M65: =Counties!AO505 | N65: =Counties!AN505 | O65: =IF(L65="","not in yet",IF(N65>=0.05,"Great for Flanagan",IF(N65>=0.01,"Flanagan on track",IF(N65>-0.01,"Toss-up",IF(N65>-0.05,"Tafoya on track","Great for Tafoya"))))&IF(Counties!AG505=1,""," (partial)")) | P65: =Counties!AU505 | Q65: =Counties!AV505 | R65: =Counties!AW505 | S65: =Counties!AX505 | T65: =Counties!AY505 | U65: =IF(T65="","",T65*Counties!AF505) | V65: =IF(T65="",IF(L65="","not in yet","waiting for the full count"),IF(T65>=0.05,"Great for Flanagan",IF(T65>=0.01,"Flanagan on track",IF(T65>-0.01,"Toss-up",IF(T65>-0.05,"Tafoya on track","Great for Tafoya"))))) | W65: 27003
A66: MN | B66: Washington | C66: Eastern suburbs, college-educated, D-leaning. | D66: Suburban margin. | E66: College suburb/metro | F66: =Counties!O585 | G66: =Counties!Q585 | H66: =Counties!R585 | I66: =Counties!S585 | J66: =Counties!AQ585/SUMIFS(Counties!$AQ:$AQ,Counties!$A:$A,"MN") | K66: =Counties!T585 | L66: =Counties!AH585 | M66: =Counties!AO585 | N66: =Counties!AN585 | O66: =IF(L66="","not in yet",IF(N66>=0.05,"Great for Flanagan",IF(N66>=0.01,"Flanagan on track",IF(N66>-0.01,"Toss-up",IF(N66>-0.05,"Tafoya on track","Great for Tafoya"))))&IF(Counties!AG585=1,""," (partial)")) | P66: =Counties!AU585 | Q66: =Counties!AV585 | R66: =Counties!AW585 | S66: =Counties!AX585 | T66: =Counties!AY585 | U66: =IF(T66="","",T66*Counties!AF585) | V66: =IF(T66="",IF(L66="","not in yet","waiting for the full count"),IF(T66>=0.05,"Great for Flanagan",IF(T66>=0.01,"Flanagan on track",IF(T66>-0.01,"Toss-up",IF(T66>-0.05,"Tafoya on track","Great for Tafoya"))))) | W66: 27163
A67: MN | B67: St. Louis | C67: Duluth and the Iron Range. Historic DFL labor country, eroding. | D67: Range towns moving R would be bad news for Flanagan. | E67: Mid-size/working metro | F67: =Counties!O575 | G67: =Counties!Q575 | H67: =Counties!R575 | I67: =Counties!S575 | J67: =Counties!AQ575/SUMIFS(Counties!$AQ:$AQ,Counties!$A:$A,"MN") | K67: =Counties!T575 | L67: =Counties!AH575 | M67: =Counties!AO575 | N67: =Counties!AN575 | O67: =IF(L67="","not in yet",IF(N67>=0.05,"Great for Flanagan",IF(N67>=0.01,"Flanagan on track",IF(N67>-0.01,"Toss-up",IF(N67>-0.05,"Tafoya on track","Great for Tafoya"))))&IF(Counties!AG575=1,""," (partial)")) | P67: =Counties!AU575 | Q67: =Counties!AV575 | R67: =Counties!AW575 | S67: =Counties!AX575 | T67: =Counties!AY575 | U67: =IF(T67="","",T67*Counties!AF575) | V67: =IF(T67="",IF(L67="","not in yet","waiting for the full count"),IF(T67>=0.05,"Great for Flanagan",IF(T67>=0.01,"Flanagan on track",IF(T67>-0.01,"Toss-up",IF(T67>-0.05,"Tafoya on track","Great for Tafoya"))))) | W67: 27137
A68: MN | B68: Olmsted | C68: Rochester (Mayo Clinic). Educated, D-leaning, a few points left of the state. | D68: Margin compared with 2024's +11. | E68: College suburb/metro | F68: =Counties!O558 | G68: =Counties!Q558 | H68: =Counties!R558 | I68: =Counties!S558 | J68: =Counties!AQ558/SUMIFS(Counties!$AQ:$AQ,Counties!$A:$A,"MN") | K68: =Counties!T558 | L68: =Counties!AH558 | M68: =Counties!AO558 | N68: =Counties!AN558 | O68: =IF(L68="","not in yet",IF(N68>=0.05,"Great for Flanagan",IF(N68>=0.01,"Flanagan on track",IF(N68>-0.01,"Toss-up",IF(N68>-0.05,"Tafoya on track","Great for Tafoya"))))&IF(Counties!AG558=1,""," (partial)")) | P68: =Counties!AU558 | Q68: =Counties!AV558 | R68: =Counties!AW558 | S68: =Counties!AX558 | T68: =Counties!AY558 | U68: =IF(T68="","",T68*Counties!AF558) | V68: =IF(T68="",IF(L68="","not in yet","waiting for the full count"),IF(T68>=0.05,"Great for Flanagan",IF(T68>=0.01,"Flanagan on track",IF(T68>-0.01,"Toss-up",IF(T68>-0.05,"Tafoya on track","Great for Tafoya"))))) | W68: 27109
A69: MN | B69: Wright | C69: Fast-growing exurb northwest of the Twin Cities and Minnesota's biggest R net-vote county (about 26,000 in 2024). | D69: Exurban Republican turnout. An index under 100 here plus strong Hennepin turnout is a bad night for Republicans. | E69: Mid-size/working metro | F69: =Counties!O589 | G69: =Counties!Q589 | H69: =Counties!R589 | I69: =Counties!S589 | J69: =Counties!AQ589/SUMIFS(Counties!$AQ:$AQ,Counties!$A:$A,"MN") | K69: =Counties!T589 | L69: =Counties!AH589 | M69: =Counties!AO589 | N69: =Counties!AN589 | O69: =IF(L69="","not in yet",IF(N69>=0.05,"Great for Flanagan",IF(N69>=0.01,"Flanagan on track",IF(N69>-0.01,"Toss-up",IF(N69>-0.05,"Tafoya on track","Great for Tafoya"))))&IF(Counties!AG589=1,""," (partial)")) | P69: =Counties!AU589 | Q69: =Counties!AV589 | R69: =Counties!AW589 | S69: =Counties!AX589 | T69: =Counties!AY589 | U69: =IF(T69="","",T69*Counties!AF589) | V69: =IF(T69="",IF(L69="","not in yet","waiting for the full count"),IF(T69>=0.05,"Great for Flanagan",IF(T69>=0.01,"Flanagan on track",IF(T69>-0.01,"Toss-up",IF(T69>-0.05,"Tafoya on track","Great for Tafoya"))))) | W69: 27171
A70: MN | B70: Stearns | C70: St. Cloud. Strongly R central Minnesota. | D70: R turnout and margin. | E70: Mid-size/working metro | F70: =Counties!O576 | G70: =Counties!Q576 | H70: =Counties!R576 | I70: =Counties!S576 | J70: =Counties!AQ576/SUMIFS(Counties!$AQ:$AQ,Counties!$A:$A,"MN") | K70: =Counties!T576 | L70: =Counties!AH576 | M70: =Counties!AO576 | N70: =Counties!AN576 | O70: =IF(L70="","not in yet",IF(N70>=0.05,"Great for Flanagan",IF(N70>=0.01,"Flanagan on track",IF(N70>-0.01,"Toss-up",IF(N70>-0.05,"Tafoya on track","Great for Tafoya"))))&IF(Counties!AG576=1,""," (partial)")) | P70: =Counties!AU576 | Q70: =Counties!AV576 | R70: =Counties!AW576 | S70: =Counties!AX576 | T70: =Counties!AY576 | U70: =IF(T70="","",T70*Counties!AF576) | V70: =IF(T70="",IF(L70="","not in yet","waiting for the full count"),IF(T70>=0.05,"Great for Flanagan",IF(T70>=0.01,"Flanagan on track",IF(T70>-0.01,"Toss-up",IF(T70>-0.05,"Tafoya on track","Great for Tafoya"))))) | W70: 27145
A71: MN | B71: Sherburne | C71: Exurban corridor northwest of the Twin Cities, R+35. | D71: Margin and turnout. It moved 2 pts toward R from 2020 to 2024; a reversal is an early D sign. | E71: Mid-size/working metro | F71: =Counties!O573 | G71: =Counties!Q573 | H71: =Counties!R573 | I71: =Counties!S573 | J71: =Counties!AQ573/SUMIFS(Counties!$AQ:$AQ,Counties!$A:$A,"MN") | K71: =Counties!T573 | L71: =Counties!AH573 | M71: =Counties!AO573 | N71: =Counties!AN573 | O71: =IF(L71="","not in yet",IF(N71>=0.05,"Great for Flanagan",IF(N71>=0.01,"Flanagan on track",IF(N71>-0.01,"Toss-up",IF(N71>-0.05,"Tafoya on track","Great for Tafoya"))))&IF(Counties!AG573=1,""," (partial)")) | P71: =Counties!AU573 | Q71: =Counties!AV573 | R71: =Counties!AW573 | S71: =Counties!AX573 | T71: =Counties!AY573 | U71: =IF(T71="","",T71*Counties!AF573) | V71: =IF(T71="",IF(L71="","not in yet","waiting for the full count"),IF(T71>=0.05,"Great for Flanagan",IF(T71>=0.01,"Flanagan on track",IF(T71>-0.01,"Toss-up",IF(T71>-0.05,"Tafoya on track","Great for Tafoya"))))) | W71: 27141
A72: MN | B72: All rural (74) | C72: Every small-town and rural county together: the Republican base's turnout test. | D72: Turnout index from its finished counties. Above 100 means the rural base is a bigger share of the vote than a tie assumes; the margin rarely moves much. | E72: Small town & rural | F72: =Types!M28 | J72: =Types!L28 | K72: =Types!P28 | L72: =Types!S28 | M72: =IFERROR(Types!E28/Types!D28,"") | N72: =IF(L72="","",L72-K72) | O72: =IF(Types!F28=0,"not in yet",IF(N72>=0.05,"Great for Flanagan",IF(N72>=0.01,"Flanagan on track",IF(N72>-0.01,"Toss-up",IF(N72>-0.05,"Tafoya on track","Great for Tafoya"))))&" (projected)") | P72: =Types!V28 | Q72: =Types!W28 | S72: =IF(Q72="","",K72-Q72) | T72: =Types!X28 | U72: =Types!Y28 | V72: =IF(T72="","not in yet",IF(T72>=0.05,"Great for Flanagan",IF(T72>=0.01,"Flanagan on track",IF(T72>-0.01,"Toss-up",IF(T72>-0.05,"Tafoya on track","Great for Tafoya"))))&" (finished counties)")
A73: Mississippi · 2024: R+23.1 (R+21.8 with 2022's turnout pattern) · Scott Colom vs Cindy Hyde-Smith
A74: MS | B74: Hinds | C74: Jackson. Majority Black, the D base. | D74: Black turnout. Democrats need it high everywhere in the Delta too. | E74: Black Belt | F74: =Counties!O615 | G74: =Counties!Q615 | H74: =Counties!R615 | I74: =Counties!S615 | J74: =Counties!AQ615/SUMIFS(Counties!$AQ:$AQ,Counties!$A:$A,"MS") | K74: =Counties!T615 | L74: =Counties!AH615 | M74: =Counties!AO615 | N74: =Counties!AN615 | O74: =IF(L74="","not in yet",IF(N74>=0.05,"Great for Colom",IF(N74>=0.01,"Colom on track",IF(N74>-0.01,"Toss-up",IF(N74>-0.05,"Hyde-Smith on track","Great for Hyde-Smith"))))&IF(Counties!AG615=1,""," (partial)")) | P74: =Counties!AU615 | Q74: =Counties!AV615 | R74: =Counties!AW615 | S74: =Counties!AX615 | T74: =Counties!AY615 | U74: =IF(T74="","",T74*Counties!AF615) | V74: =IF(T74="",IF(L74="","not in yet","waiting for the full count"),IF(T74>=0.05,"Great for Colom",IF(T74>=0.01,"Colom on track",IF(T74>-0.01,"Toss-up",IF(T74>-0.05,"Hyde-Smith on track","Great for Hyde-Smith"))))) | W74: 28049
A75: MS | B75: DeSoto | C75: Memphis suburbs, fast-growing, increasingly Black. | D75: The R margin shrinking is a long-term D trend. | E75: Mid-size/working metro | F75: =Counties!O607 | G75: =Counties!Q607 | H75: =Counties!R607 | I75: =Counties!S607 | J75: =Counties!AQ607/SUMIFS(Counties!$AQ:$AQ,Counties!$A:$A,"MS") | K75: =Counties!T607 | L75: =Counties!AH607 | M75: =Counties!AO607 | N75: =Counties!AN607 | O75: =IF(L75="","not in yet",IF(N75>=0.05,"Great for Colom",IF(N75>=0.01,"Colom on track",IF(N75>-0.01,"Toss-up",IF(N75>-0.05,"Hyde-Smith on track","Great for Hyde-Smith"))))&IF(Counties!AG607=1,""," (partial)")) | P75: =Counties!AU607 | Q75: =Counties!AV607 | R75: =Counties!AW607 | S75: =Counties!AX607 | T75: =Counties!AY607 | U75: =IF(T75="","",T75*Counties!AF607) | V75: =IF(T75="",IF(L75="","not in yet","waiting for the full count"),IF(T75>=0.05,"Great for Colom",IF(T75>=0.01,"Colom on track",IF(T75>-0.01,"Toss-up",IF(T75>-0.05,"Hyde-Smith on track","Great for Hyde-Smith"))))) | W75: 28033
A76: MS | B76: Harrison | C76: Gulfport and Biloxi. The Gulf Coast. | D76: R margin. | E76: Mid-size/working metro | F76: =Counties!O614 | G76: =Counties!Q614 | H76: =Counties!R614 | I76: =Counties!S614 | J76: =Counties!AQ614/SUMIFS(Counties!$AQ:$AQ,Counties!$A:$A,"MS") | K76: =Counties!T614 | L76: =Counties!AH614 | M76: =Counties!AO614 | N76: =Counties!AN614 | O76: =IF(L76="","not in yet",IF(N76>=0.05,"Great for Colom",IF(N76>=0.01,"Colom on track",IF(N76>-0.01,"Toss-up",IF(N76>-0.05,"Hyde-Smith on track","Great for Hyde-Smith"))))&IF(Counties!AG614=1,""," (partial)")) | P76: =Counties!AU614 | Q76: =Counties!AV614 | R76: =Counties!AW614 | S76: =Counties!AX614 | T76: =Counties!AY614 | U76: =IF(T76="","",T76*Counties!AF614) | V76: =IF(T76="",IF(L76="","not in yet","waiting for the full count"),IF(T76>=0.05,"Great for Colom",IF(T76>=0.01,"Colom on track",IF(T76>-0.01,"Toss-up",IF(T76>-0.05,"Hyde-Smith on track","Great for Hyde-Smith"))))) | W76: 28047
A77: MS | B77: Rankin | C77: White suburban Jackson, very R. | D77: R turnout. | E77: Mid-size/working metro | F77: =Counties!O651 | G77: =Counties!Q651 | H77: =Counties!R651 | I77: =Counties!S651 | J77: =Counties!AQ651/SUMIFS(Counties!$AQ:$AQ,Counties!$A:$A,"MS") | K77: =Counties!T651 | L77: =Counties!AH651 | M77: =Counties!AO651 | N77: =Counties!AN651 | O77: =IF(L77="","not in yet",IF(N77>=0.05,"Great for Colom",IF(N77>=0.01,"Colom on track",IF(N77>-0.01,"Toss-up",IF(N77>-0.05,"Hyde-Smith on track","Great for Hyde-Smith"))))&IF(Counties!AG651=1,""," (partial)")) | P77: =Counties!AU651 | Q77: =Counties!AV651 | R77: =Counties!AW651 | S77: =Counties!AX651 | T77: =Counties!AY651 | U77: =IF(T77="","",T77*Counties!AF651) | V77: =IF(T77="",IF(L77="","not in yet","waiting for the full count"),IF(T77>=0.05,"Great for Colom",IF(T77>=0.01,"Colom on track",IF(T77>-0.01,"Toss-up",IF(T77>-0.05,"Hyde-Smith on track","Great for Hyde-Smith"))))) | W77: 28121
A78: MS | B78: Madison | C78: Affluent Jackson suburb, educated. | D78: Suburban defections. | E78: College suburb/metro | F78: =Counties!O635 | G78: =Counties!Q635 | H78: =Counties!R635 | I78: =Counties!S635 | J78: =Counties!AQ635/SUMIFS(Counties!$AQ:$AQ,Counties!$A:$A,"MS") | K78: =Counties!T635 | L78: =Counties!AH635 | M78: =Counties!AO635 | N78: =Counties!AN635 | O78: =IF(L78="","not in yet",IF(N78>=0.05,"Great for Colom",IF(N78>=0.01,"Colom on track",IF(N78>-0.01,"Toss-up",IF(N78>-0.05,"Hyde-Smith on track","Great for Hyde-Smith"))))&IF(Counties!AG635=1,""," (partial)")) | P78: =Counties!AU635 | Q78: =Counties!AV635 | R78: =Counties!AW635 | S78: =Counties!AX635 | T78: =Counties!AY635 | U78: =IF(T78="","",T78*Counties!AF635) | V78: =IF(T78="",IF(L78="","not in yet","waiting for the full count"),IF(T78>=0.05,"Great for Colom",IF(T78>=0.01,"Colom on track",IF(T78>-0.01,"Toss-up",IF(T78>-0.05,"Hyde-Smith on track","Great for Hyde-Smith"))))) | W78: 28089
A79: MS | B79: Lee | C79: Tupelo. Northeast Mississippi. | D79: R margin. | E79: Small town & rural | F79: =Counties!O631 | G79: =Counties!Q631 | H79: =Counties!R631 | I79: =Counties!S631 | J79: =Counties!AQ631/SUMIFS(Counties!$AQ:$AQ,Counties!$A:$A,"MS") | K79: =Counties!T631 | L79: =Counties!AH631 | M79: =Counties!AO631 | N79: =Counties!AN631 | O79: =IF(L79="","not in yet",IF(N79>=0.05,"Great for Colom",IF(N79>=0.01,"Colom on track",IF(N79>-0.01,"Toss-up",IF(N79>-0.05,"Hyde-Smith on track","Great for Hyde-Smith"))))&IF(Counties!AG631=1,""," (partial)")) | P79: =Counties!AU631 | Q79: =Counties!AV631 | R79: =Counties!AW631 | S79: =Counties!AX631 | T79: =Counties!AY631 | U79: =IF(T79="","",T79*Counties!AF631) | V79: =IF(T79="",IF(L79="","not in yet","waiting for the full count"),IF(T79>=0.05,"Great for Colom",IF(T79>=0.01,"Colom on track",IF(T79>-0.01,"Toss-up",IF(T79>-0.05,"Hyde-Smith on track","Great for Hyde-Smith"))))) | W79: 28081
A80: MS | B80: All rural (40) | C80: Every small-town and rural county together: the Republican base's turnout test. | D80: Turnout index from its finished counties. Above 100 means the rural base is a bigger share of the vote than a tie assumes; the margin rarely moves much. | E80: Small town & rural | F80: =Types!M32 | J80: =Types!L32 | K80: =Types!P32 | L80: =Types!S32 | M80: =IFERROR(Types!E32/Types!D32,"") | N80: =IF(L80="","",L80-K80) | O80: =IF(Types!F32=0,"not in yet",IF(N80>=0.05,"Great for Colom",IF(N80>=0.01,"Colom on track",IF(N80>-0.01,"Toss-up",IF(N80>-0.05,"Hyde-Smith on track","Great for Hyde-Smith"))))&" (projected)") | P80: =Types!V32 | Q80: =Types!W32 | S80: =IF(Q80="","",K80-Q80) | T80: =Types!X32 | U80: =Types!Y32 | V80: =IF(T80="","not in yet",IF(T80>=0.05,"Great for Colom",IF(T80>=0.01,"Colom on track",IF(T80>-0.01,"Toss-up",IF(T80>-0.05,"Hyde-Smith on track","Great for Hyde-Smith"))))&" (finished counties)")
A81: North Carolina · 2024: R+3.3 (R+2.8 with 2022's turnout pattern) · Roy Cooper vs Michael Whatley
A82: NC | B82: Wake | C82: Largest county (Raleigh), with fast-growing college-educated suburbs. | D82: Turnout growth plus margin. Wake has been adding thousands of net D votes every cycle. | E82: Big metro core | F82: =Counties!O764 | G82: =Counties!Q764 | H82: =Counties!R764 | I82: =Counties!S764 | J82: =Counties!AQ764/SUMIFS(Counties!$AQ:$AQ,Counties!$A:$A,"NC") | K82: =Counties!T764 | L82: =Counties!AH764 | M82: =Counties!AO764 | N82: =Counties!AN764 | O82: =IF(L82="","not in yet",IF(N82>=0.05,"Great for Cooper",IF(N82>=0.01,"Cooper on track",IF(N82>-0.01,"Toss-up",IF(N82>-0.05,"Whatley on track","Great for Whatley"))))&IF(Counties!AG764=1,""," (partial)")) | P82: =Counties!AU764 | Q82: =Counties!AV764 | R82: =Counties!AW764 | S82: =Counties!AX764 | T82: =Counties!AY764 | U82: =IF(T82="","",T82*Counties!AF764) | V82: =IF(T82="",IF(L82="","not in yet","waiting for the full count"),IF(T82>=0.05,"Great for Cooper",IF(T82>=0.01,"Cooper on track",IF(T82>-0.01,"Toss-up",IF(T82>-0.05,"Whatley on track","Great for Whatley"))))) | W82: 37183
A83: NC | B83: Mecklenburg | C83: Charlotte. Second-biggest D vote bank, with a large Black population. | D83: Its margin slipped 2.2 points toward R in 2024. A rebound is a good D sign. | E83: Big metro core | F83: =Counties!O732 | G83: =Counties!Q732 | H83: =Counties!R732 | I83: =Counties!S732 | J83: =Counties!AQ732/SUMIFS(Counties!$AQ:$AQ,Counties!$A:$A,"NC") | K83: =Counties!T732 | L83: =Counties!AH732 | M83: =Counties!AO732 | N83: =Counties!AN732 | O83: =IF(L83="","not in yet",IF(N83>=0.05,"Great for Cooper",IF(N83>=0.01,"Cooper on track",IF(N83>-0.01,"Toss-up",IF(N83>-0.05,"Whatley on track","Great for Whatley"))))&IF(Counties!AG732=1,""," (partial)")) | P83: =Counties!AU732 | Q83: =Counties!AV732 | R83: =Counties!AW732 | S83: =Counties!AX732 | T83: =Counties!AY732 | U83: =IF(T83="","",T83*Counties!AF732) | V83: =IF(T83="",IF(L83="","not in yet","waiting for the full count"),IF(T83>=0.05,"Great for Cooper",IF(T83>=0.01,"Cooper on track",IF(T83>-0.01,"Toss-up",IF(T83>-0.05,"Whatley on track","Great for Whatley"))))) | W83: 37119
A84: NC | B84: Guilford | C84: Greensboro. A big, racially mixed county that tracks the statewide trend. | D84: Margin compared with its 2022 and 2024 baselines. | E84: Mid-size/working metro | F84: =Counties!O713 | G84: =Counties!Q713 | H84: =Counties!R713 | I84: =Counties!S713 | J84: =Counties!AQ713/SUMIFS(Counties!$AQ:$AQ,Counties!$A:$A,"NC") | K84: =Counties!T713 | L84: =Counties!AH713 | M84: =Counties!AO713 | N84: =Counties!AN713 | O84: =IF(L84="","not in yet",IF(N84>=0.05,"Great for Cooper",IF(N84>=0.01,"Cooper on track",IF(N84>-0.01,"Toss-up",IF(N84>-0.05,"Whatley on track","Great for Whatley"))))&IF(Counties!AG713=1,""," (partial)")) | P84: =Counties!AU713 | Q84: =Counties!AV713 | R84: =Counties!AW713 | S84: =Counties!AX713 | T84: =Counties!AY713 | U84: =IF(T84="","",T84*Counties!AF713) | V84: =IF(T84="",IF(L84="","not in yet","waiting for the full count"),IF(T84>=0.05,"Great for Cooper",IF(T84>=0.01,"Cooper on track",IF(T84>-0.01,"Toss-up",IF(T84>-0.05,"Whatley on track","Great for Whatley"))))) | W84: 37081
A85: NC | B85: Durham | C85: Deep-blue Research Triangle county. | D85: Turnout. The margin is near its ceiling. | E85: College suburb/metro | F85: =Counties!O704 | G85: =Counties!Q704 | H85: =Counties!R704 | I85: =Counties!S704 | J85: =Counties!AQ704/SUMIFS(Counties!$AQ:$AQ,Counties!$A:$A,"NC") | K85: =Counties!T704 | L85: =Counties!AH704 | M85: =Counties!AO704 | N85: =Counties!AN704 | O85: =IF(L85="","not in yet",IF(N85>=0.05,"Great for Cooper",IF(N85>=0.01,"Cooper on track",IF(N85>-0.01,"Toss-up",IF(N85>-0.05,"Whatley on track","Great for Whatley"))))&IF(Counties!AG704=1,""," (partial)")) | P85: =Counties!AU704 | Q85: =Counties!AV704 | R85: =Counties!AW704 | S85: =Counties!AX704 | T85: =Counties!AY704 | U85: =IF(T85="","",T85*Counties!AF704) | V85: =IF(T85="",IF(L85="","not in yet","waiting for the full count"),IF(T85>=0.05,"Great for Cooper",IF(T85>=0.01,"Cooper on track",IF(T85>-0.01,"Toss-up",IF(T85>-0.05,"Whatley on track","Great for Whatley"))))) | W85: 37063
A86: NC | B86: Buncombe | C86: Asheville. Hurricane Helene hit it in 2024, and it still swung D. | D86: Turnout recovery after Helene, and whether the 2024 D gain holds. | E86: College suburb/metro | F86: =Counties!O683 | G86: =Counties!Q683 | H86: =Counties!R683 | I86: =Counties!S683 | J86: =Counties!AQ683/SUMIFS(Counties!$AQ:$AQ,Counties!$A:$A,"NC") | K86: =Counties!T683 | L86: =Counties!AH683 | M86: =Counties!AO683 | N86: =Counties!AN683 | O86: =IF(L86="","not in yet",IF(N86>=0.05,"Great for Cooper",IF(N86>=0.01,"Cooper on track",IF(N86>-0.01,"Toss-up",IF(N86>-0.05,"Whatley on track","Great for Whatley"))))&IF(Counties!AG683=1,""," (partial)")) | P86: =Counties!AU683 | Q86: =Counties!AV683 | R86: =Counties!AW683 | S86: =Counties!AX683 | T86: =Counties!AY683 | U86: =IF(T86="","",T86*Counties!AF683) | V86: =IF(T86="",IF(L86="","not in yet","waiting for the full count"),IF(T86>=0.05,"Great for Cooper",IF(T86>=0.01,"Cooper on track",IF(T86>-0.01,"Toss-up",IF(T86>-0.05,"Whatley on track","Great for Whatley"))))) | W86: 37021
A87: NC | B87: Union | C87: Charlotte's fast-growing southeastern exurb, about 35,000 net R votes in 2024. | D87: Suburban Republicans. College-educated growth has kept it flat (R+24.5 in 2020, R+25.5 in 2024). Well under that, with turnout on pace, means suburban Republicans are slipping. | E87: Mid-size/working metro | F87: =Counties!O762 | G87: =Counties!Q762 | H87: =Counties!R762 | I87: =Counties!S762 | J87: =Counties!AQ762/SUMIFS(Counties!$AQ:$AQ,Counties!$A:$A,"NC") | K87: =Counties!T762 | L87: =Counties!AH762 | M87: =Counties!AO762 | N87: =Counties!AN762 | O87: =IF(L87="","not in yet",IF(N87>=0.05,"Great for Cooper",IF(N87>=0.01,"Cooper on track",IF(N87>-0.01,"Toss-up",IF(N87>-0.05,"Whatley on track","Great for Whatley"))))&IF(Counties!AG762=1,""," (partial)")) | P87: =Counties!AU762 | Q87: =Counties!AV762 | R87: =Counties!AW762 | S87: =Counties!AX762 | T87: =Counties!AY762 | U87: =IF(T87="","",T87*Counties!AF762) | V87: =IF(T87="",IF(L87="","not in yet","waiting for the full count"),IF(T87>=0.05,"Great for Cooper",IF(T87>=0.01,"Cooper on track",IF(T87>-0.01,"Toss-up",IF(T87>-0.05,"Whatley on track","Great for Whatley"))))) | W87: 37179
A88: NC | B88: New Hanover | C88: Wilmington. A true swing county, almost exactly tied in 2024. | D88: Whichever side wins it by a few points is usually having a good night statewide. | E88: College suburb/metro | F88: =Counties!O737 | G88: =Counties!Q737 | H88: =Counties!R737 | I88: =Counties!S737 | J88: =Counties!AQ737/SUMIFS(Counties!$AQ:$AQ,Counties!$A:$A,"NC") | K88: =Counties!T737 | L88: =Counties!AH737 | M88: =Counties!AO737 | N88: =Counties!AN737 | O88: =IF(L88="","not in yet",IF(N88>=0.05,"Great for Cooper",IF(N88>=0.01,"Cooper on track",IF(N88>-0.01,"Toss-up",IF(N88>-0.05,"Whatley on track","Great for Whatley"))))&IF(Counties!AG737=1,""," (partial)")) | P88: =Counties!AU737 | Q88: =Counties!AV737 | R88: =Counties!AW737 | S88: =Counties!AX737 | T88: =Counties!AY737 | U88: =IF(T88="","",T88*Counties!AF737) | V88: =IF(T88="",IF(L88="","not in yet","waiting for the full count"),IF(T88>=0.05,"Great for Cooper",IF(T88>=0.01,"Cooper on track",IF(T88>-0.01,"Toss-up",IF(T88>-0.05,"Whatley on track","Great for Whatley"))))) | W88: 37129
A89: NC | B89: Johnston | C89: Booming exurb southeast of Raleigh, still strongly R but trending D. | D89: R margin under about 20 means Democrats are making suburban growth work for them. | E89: Mid-size/working metro | F89: =Counties!O723 | G89: =Counties!Q723 | H89: =Counties!R723 | I89: =Counties!S723 | J89: =Counties!AQ723/SUMIFS(Counties!$AQ:$AQ,Counties!$A:$A,"NC") | K89: =Counties!T723 | L89: =Counties!AH723 | M89: =Counties!AO723 | N89: =Counties!AN723 | O89: =IF(L89="","not in yet",IF(N89>=0.05,"Great for Cooper",IF(N89>=0.01,"Cooper on track",IF(N89>-0.01,"Toss-up",IF(N89>-0.05,"Whatley on track","Great for Whatley"))))&IF(Counties!AG723=1,""," (partial)")) | P89: =Counties!AU723 | Q89: =Counties!AV723 | R89: =Counties!AW723 | S89: =Counties!AX723 | T89: =Counties!AY723 | U89: =IF(T89="","",T89*Counties!AF723) | V89: =IF(T89="",IF(L89="","not in yet","waiting for the full count"),IF(T89>=0.05,"Great for Cooper",IF(T89>=0.01,"Cooper on track",IF(T89>-0.01,"Toss-up",IF(T89>-0.05,"Whatley on track","Great for Whatley"))))) | W89: 37101
A90: NC | B90: Davidson | C90: The state's biggest R net-vote county (about 44,000 in 2024), working-class Piedmont. | D90: Turnout and margin together: R+48 at a turnout index of 100 or better means the Republican base is fully there. | E90: Mid-size/working metro | F90: =Counties!O701 | G90: =Counties!Q701 | H90: =Counties!R701 | I90: =Counties!S701 | J90: =Counties!AQ701/SUMIFS(Counties!$AQ:$AQ,Counties!$A:$A,"NC") | K90: =Counties!T701 | L90: =Counties!AH701 | M90: =Counties!AO701 | N90: =Counties!AN701 | O90: =IF(L90="","not in yet",IF(N90>=0.05,"Great for Cooper",IF(N90>=0.01,"Cooper on track",IF(N90>-0.01,"Toss-up",IF(N90>-0.05,"Whatley on track","Great for Whatley"))))&IF(Counties!AG701=1,""," (partial)")) | P90: =Counties!AU701 | Q90: =Counties!AV701 | R90: =Counties!AW701 | S90: =Counties!AX701 | T90: =Counties!AY701 | U90: =IF(T90="","",T90*Counties!AF701) | V90: =IF(T90="",IF(L90="","not in yet","waiting for the full count"),IF(T90>=0.05,"Great for Cooper",IF(T90>=0.01,"Cooper on track",IF(T90>-0.01,"Toss-up",IF(T90>-0.05,"Whatley on track","Great for Whatley"))))) | W90: 37057
A91: NC | B91: Randolph | C91: The most Republican county in North Carolina with 100,000+ people (R+58), in the Piedmont between Greensboro and Charlotte. | D91: Turnout. The margin is near its ceiling, so whether small-town Republicans turn out in a midterm is the question. | E91: Mid-size/working metro | F91: =Counties!O748 | G91: =Counties!Q748 | H91: =Counties!R748 | I91: =Counties!S748 | J91: =Counties!AQ748/SUMIFS(Counties!$AQ:$AQ,Counties!$A:$A,"NC") | K91: =Counties!T748 | L91: =Counties!AH748 | M91: =Counties!AO748 | N91: =Counties!AN748 | O91: =IF(L91="","not in yet",IF(N91>=0.05,"Great for Cooper",IF(N91>=0.01,"Cooper on track",IF(N91>-0.01,"Toss-up",IF(N91>-0.05,"Whatley on track","Great for Whatley"))))&IF(Counties!AG748=1,""," (partial)")) | P91: =Counties!AU748 | Q91: =Counties!AV748 | R91: =Counties!AW748 | S91: =Counties!AX748 | T91: =Counties!AY748 | U91: =IF(T91="","",T91*Counties!AF748) | V91: =IF(T91="",IF(L91="","not in yet","waiting for the full count"),IF(T91>=0.05,"Great for Cooper",IF(T91>=0.01,"Cooper on track",IF(T91>-0.01,"Toss-up",IF(T91>-0.05,"Whatley on track","Great for Whatley"))))) | W91: 37151
A92: NC | B92: Robeson | C92: Lumbee Native American, Black and white rural county that swung hard R (about 9 points in 2024). | D92: Bellwether for rural working-class nonwhite voters. A Cooper bounce-back here is a strong D signal. | E92: Native American | F92: =Counties!O750 | G92: =Counties!Q750 | H92: =Counties!R750 | I92: =Counties!S750 | J92: =Counties!AQ750/SUMIFS(Counties!$AQ:$AQ,Counties!$A:$A,"NC") | K92: =Counties!T750 | L92: =Counties!AH750 | M92: =Counties!AO750 | N92: =Counties!AN750 | O92: =IF(L92="","not in yet",IF(N92>=0.05,"Great for Cooper",IF(N92>=0.01,"Cooper on track",IF(N92>-0.01,"Toss-up",IF(N92>-0.05,"Whatley on track","Great for Whatley"))))&IF(Counties!AG750=1,""," (partial)")) | P92: =Counties!AU750 | Q92: =Counties!AV750 | R92: =Counties!AW750 | S92: =Counties!AX750 | T92: =Counties!AY750 | U92: =IF(T92="","",T92*Counties!AF750) | V92: =IF(T92="",IF(L92="","not in yet","waiting for the full count"),IF(T92>=0.05,"Great for Cooper",IF(T92>=0.01,"Cooper on track",IF(T92>-0.01,"Toss-up",IF(T92>-0.05,"Whatley on track","Great for Whatley"))))) | W92: 37155
A93: NC | B93: All rural (59) | C93: Every small-town and rural county together: the Republican base's turnout test. | D93: Turnout index from its finished counties. Above 100 means the rural base is a bigger share of the vote than a tie assumes; the margin rarely moves much. | E93: Small town & rural | F93: =Types!M38 | J93: =Types!L38 | K93: =Types!P38 | L93: =Types!S38 | M93: =IFERROR(Types!E38/Types!D38,"") | N93: =IF(L93="","",L93-K93) | O93: =IF(Types!F38=0,"not in yet",IF(N93>=0.05,"Great for Cooper",IF(N93>=0.01,"Cooper on track",IF(N93>-0.01,"Toss-up",IF(N93>-0.05,"Whatley on track","Great for Whatley"))))&" (projected)") | P93: =Types!V38 | Q93: =Types!W38 | S93: =IF(Q93="","",K93-Q93) | T93: =Types!X38 | U93: =Types!Y38 | V93: =IF(T93="","not in yet",IF(T93>=0.05,"Great for Cooper",IF(T93>=0.01,"Cooper on track",IF(T93>-0.01,"Toss-up",IF(T93>-0.05,"Whatley on track","Great for Whatley"))))&" (finished counties)")
A94: Nebraska · 2024: R+20.8 (R+21.3 with 2022's turnout pattern) · Dan Osborn vs Pete Ricketts
A95: NE | B95: Douglas | C95: Omaha. The largest county. | D95: Osborn needs a big win in Omaha on top of rural crossover. | E95: College suburb/metro | F95: =Counties!O800 | G95: =Counties!Q800 | H95: =Counties!R800 | I95: =Counties!S800 | J95: =Counties!AQ800/SUMIFS(Counties!$AQ:$AQ,Counties!$A:$A,"NE") | K95: =Counties!T800 | L95: =Counties!AH800 | M95: =Counties!AO800 | N95: =Counties!AN800 | O95: =IF(L95="","not in yet",IF(N95>=0.05,"Great for Osborn",IF(N95>=0.01,"Osborn on track",IF(N95>-0.01,"Toss-up",IF(N95>-0.05,"Ricketts on track","Great for Ricketts"))))&IF(Counties!AG800=1,""," (partial)")) | P95: =Counties!AU800 | Q95: =Counties!AV800 | R95: =Counties!AW800 | S95: =Counties!AX800 | T95: =Counties!AY800 | U95: =IF(T95="","",T95*Counties!AF800) | V95: =IF(T95="",IF(L95="","not in yet","waiting for the full count"),IF(T95>=0.05,"Great for Osborn",IF(T95>=0.01,"Osborn on track",IF(T95>-0.01,"Toss-up",IF(T95>-0.05,"Ricketts on track","Great for Ricketts"))))) | W95: 31055
A96: NE | B96: Lancaster | C96: Lincoln. University and state government. | D96: Margin. Osborn needs it comfortably. | E96: College suburb/metro | F96: =Counties!O827 | G96: =Counties!Q827 | H96: =Counties!R827 | I96: =Counties!S827 | J96: =Counties!AQ827/SUMIFS(Counties!$AQ:$AQ,Counties!$A:$A,"NE") | K96: =Counties!T827 | L96: =Counties!AH827 | M96: =Counties!AO827 | N96: =Counties!AN827 | O96: =IF(L96="","not in yet",IF(N96>=0.05,"Great for Osborn",IF(N96>=0.01,"Osborn on track",IF(N96>-0.01,"Toss-up",IF(N96>-0.05,"Ricketts on track","Great for Ricketts"))))&IF(Counties!AG827=1,""," (partial)")) | P96: =Counties!AU827 | Q96: =Counties!AV827 | R96: =Counties!AW827 | S96: =Counties!AX827 | T96: =Counties!AY827 | U96: =IF(T96="","",T96*Counties!AF827) | V96: =IF(T96="",IF(L96="","not in yet","waiting for the full count"),IF(T96>=0.05,"Great for Osborn",IF(T96>=0.01,"Osborn on track",IF(T96>-0.01,"Toss-up",IF(T96>-0.05,"Ricketts on track","Great for Ricketts"))))) | W96: 31109
A97: NE | B97: Sarpy | C97: Omaha suburbs, R-leaning. | D97: Close to even here would be a great Osborn sign. | E97: College suburb/metro | F97: =Counties!O849 | G97: =Counties!Q849 | H97: =Counties!R849 | I97: =Counties!S849 | J97: =Counties!AQ849/SUMIFS(Counties!$AQ:$AQ,Counties!$A:$A,"NE") | K97: =Counties!T849 | L97: =Counties!AH849 | M97: =Counties!AO849 | N97: =Counties!AN849 | O97: =IF(L97="","not in yet",IF(N97>=0.05,"Great for Osborn",IF(N97>=0.01,"Osborn on track",IF(N97>-0.01,"Toss-up",IF(N97>-0.05,"Ricketts on track","Great for Ricketts"))))&IF(Counties!AG849=1,""," (partial)")) | P97: =Counties!AU849 | Q97: =Counties!AV849 | R97: =Counties!AW849 | S97: =Counties!AX849 | T97: =Counties!AY849 | U97: =IF(T97="","",T97*Counties!AF849) | V97: =IF(T97="",IF(L97="","not in yet","waiting for the full count"),IF(T97>=0.05,"Great for Osborn",IF(T97>=0.01,"Osborn on track",IF(T97>-0.01,"Toss-up",IF(T97>-0.05,"Ricketts on track","Great for Ricketts"))))) | W97: 31153
A98: NE | B98: Buffalo | C98: Kearney. Rural central Nebraska. | D98: Osborn's 2024 strategy was cutting rural R margins. Watch whether he does it again. | E98: Small town & rural | F98: =Counties!O782 | G98: =Counties!Q782 | H98: =Counties!R782 | I98: =Counties!S782 | J98: =Counties!AQ782/SUMIFS(Counties!$AQ:$AQ,Counties!$A:$A,"NE") | K98: =Counties!T782 | L98: =Counties!AH782 | M98: =Counties!AO782 | N98: =Counties!AN782 | O98: =IF(L98="","not in yet",IF(N98>=0.05,"Great for Osborn",IF(N98>=0.01,"Osborn on track",IF(N98>-0.01,"Toss-up",IF(N98>-0.05,"Ricketts on track","Great for Ricketts"))))&IF(Counties!AG782=1,""," (partial)")) | P98: =Counties!AU782 | Q98: =Counties!AV782 | R98: =Counties!AW782 | S98: =Counties!AX782 | T98: =Counties!AY782 | U98: =IF(T98="","",T98*Counties!AF782) | V98: =IF(T98="",IF(L98="","not in yet","waiting for the full count"),IF(T98>=0.05,"Great for Osborn",IF(T98>=0.01,"Osborn on track",IF(T98>-0.01,"Toss-up",IF(T98>-0.05,"Ricketts on track","Great for Ricketts"))))) | W98: 31019
A99: NE | B99: Hall | C99: Grand Island. A third Hispanic, meatpacking. | D99: Osborn's working-class pitch and Hispanic voters. | E99: Small town & rural | F99: =Counties!O812 | G99: =Counties!Q812 | H99: =Counties!R812 | I99: =Counties!S812 | J99: =Counties!AQ812/SUMIFS(Counties!$AQ:$AQ,Counties!$A:$A,"NE") | K99: =Counties!T812 | L99: =Counties!AH812 | M99: =Counties!AO812 | N99: =Counties!AN812 | O99: =IF(L99="","not in yet",IF(N99>=0.05,"Great for Osborn",IF(N99>=0.01,"Osborn on track",IF(N99>-0.01,"Toss-up",IF(N99>-0.05,"Ricketts on track","Great for Ricketts"))))&IF(Counties!AG812=1,""," (partial)")) | P99: =Counties!AU812 | Q99: =Counties!AV812 | R99: =Counties!AW812 | S99: =Counties!AX812 | T99: =Counties!AY812 | U99: =IF(T99="","",T99*Counties!AF812) | V99: =IF(T99="",IF(L99="","not in yet","waiting for the full count"),IF(T99>=0.05,"Great for Osborn",IF(T99>=0.01,"Osborn on track",IF(T99>-0.01,"Toss-up",IF(T99>-0.05,"Ricketts on track","Great for Ricketts"))))) | W99: 31079
A100: NE | B100: Lincoln | C100: North Platte. Rural western Nebraska, railroad and union history. | D100: Same test, further west. | E100: Small town & rural | F100: =Counties!O828 | G100: =Counties!Q828 | H100: =Counties!R828 | I100: =Counties!S828 | J100: =Counties!AQ828/SUMIFS(Counties!$AQ:$AQ,Counties!$A:$A,"NE") | K100: =Counties!T828 | L100: =Counties!AH828 | M100: =Counties!AO828 | N100: =Counties!AN828 | O100: =IF(L100="","not in yet",IF(N100>=0.05,"Great for Osborn",IF(N100>=0.01,"Osborn on track",IF(N100>-0.01,"Toss-up",IF(N100>-0.05,"Ricketts on track","Great for Ricketts"))))&IF(Counties!AG828=1,""," (partial)")) | P100: =Counties!AU828 | Q100: =Counties!AV828 | R100: =Counties!AW828 | S100: =Counties!AX828 | T100: =Counties!AY828 | U100: =IF(T100="","",T100*Counties!AF828) | V100: =IF(T100="",IF(L100="","not in yet","waiting for the full count"),IF(T100>=0.05,"Great for Osborn",IF(T100>=0.01,"Osborn on track",IF(T100>-0.01,"Toss-up",IF(T100>-0.05,"Ricketts on track","Great for Ricketts"))))) | W100: 31111
A101: NE | B101: All rural (87) | C101: Every small-town and rural county together: the Republican base's turnout test. | D101: Turnout index from its finished counties. Above 100 means the rural base is a bigger share of the vote than a tie assumes; the margin rarely moves much. | E101: Small town & rural | F101: =Types!M42 | J101: =Types!L42 | K101: =Types!P42 | L101: =Types!S42 | M101: =IFERROR(Types!E42/Types!D42,"") | N101: =IF(L101="","",L101-K101) | O101: =IF(Types!F42=0,"not in yet",IF(N101>=0.05,"Great for Osborn",IF(N101>=0.01,"Osborn on track",IF(N101>-0.01,"Toss-up",IF(N101>-0.05,"Ricketts on track","Great for Ricketts"))))&" (projected)") | P101: =Types!V42 | Q101: =Types!W42 | S101: =IF(Q101="","",K101-Q101) | T101: =Types!X42 | U101: =Types!Y42 | V101: =IF(T101="","not in yet",IF(T101>=0.05,"Great for Osborn",IF(T101>=0.01,"Osborn on track",IF(T101>-0.01,"Toss-up",IF(T101>-0.05,"Ricketts on track","Great for Ricketts"))))&" (finished counties)")
...

Sheet County Benchmarks
A1: County benchmarks: what each key county needs to show when it finishes counting
A2: Each column is the county margin that matches a statewide result, if every county moves the same amount from 2024 and turnout follows 2022's pattern. Net votes = that margin x the county's par vote (its 2022-pattern two-party vote x the state's projected turnout pace, so it rescales on the night). Read a county's FINAL number against these; partial counts are skewed by vote method (see First Counties). Once a county is fully counted, its turnout index adjusts the break-even and the reading uses margin and turnout together.
A4: State | B4: County | C4: Type | D4: Par 2-party votes (tie pace) | E4: Margin 2024 | F4: Margin 2022 | G4: Margin if state ends R+5 | H4: Margin if state ends R+1 | I4: Margin if state ends tie | J4: Margin if state ends D+1 | K4: Margin if state ends D+5 | L4: Net votes if state ends R+5 | M4: Net votes if state ends R+1 | N4: Net votes if state ends tie | O4: Net votes if state ends D+1 | P4: Net votes if state ends D+5 | Q4: D votes needed for a tie | R4: Live margin | S4: Live net votes | T4: Est. % in | U4: Turnout index (100 = state pace) | V4: Break-even at actual turnout | W4: Margin + turnout vs tie pace (pts) | X4: Reading | Y4: What to look for
A5: Georgia: Jon Ossoff vs Mike Collins · 2024 statewide R+2.2 (R+1.1 with 2022's turnout pattern)
A6: GA | B6: Fulton | C6: Big metro core | D6: =Counties!AT101 | E6: =Counties!O101 | F6: =Counties!R101 | G6: =MAX(-1,MIN(1,Counties!O101+-0.05+Dashboard!$F$7)) | H6: =MAX(-1,MIN(1,Counties!O101+-0.01+Dashboard!$F$7)) | I6: =MAX(-1,MIN(1,Counties!O101+0.0+Dashboard!$F$7)) | J6: =MAX(-1,MIN(1,Counties!O101+0.01+Dashboard!$F$7)) | K6: =MAX(-1,MIN(1,Counties!O101+0.05+Dashboard!$F$7)) | L6: =G6*D6 | M6: =H6*D6 | N6: =I6*D6 | O6: =J6*D6 | P6: =K6*D6 | Q6: =D6*(1+I6)/2 | R6: =Counties!AH101 | S6: =IF(Counties!AH101="","",Counties!AH101*Counties!AF101) | T6: =Counties!AO101 | U6: =Counties!AU101 | V6: =Counties!AV101 | W6: =Counties!AY101 | X6: =IF(R6="","not in yet",IF(W6<>"",IF(W6>=0.05,"Great for Ossoff",IF(W6>=0.01,"Ossoff on track",IF(W6>-0.01,"Toss-up",IF(W6>-0.05,"Collins on track","Great for Collins"))))&" (margin + turnout)",IF((R6-I6)>=0.05,"Great for Ossoff",IF((R6-I6)>=0.01,"Ossoff on track",IF((R6-I6)>-0.01,"Toss-up",IF((R6-I6)>-0.05,"Collins on track","Great for Collins"))))&IF(Counties!AG101=1,""," (partial count)"))) | Y6: ="Break-even "&IF(I6>=0,"D+","R+")&TEXT(ABS(I6)*100,"0.0")&" ("&IF(N6>=0,"D +","R +")&TEXT(ABS(N6),"#,##0")&" net, about "&TEXT(Q6,"#,##0")&" Ossoff votes). Ossoff at "&IF(K6>=0,"D+","R+")&TEXT(ABS(K6)*100,"0.0")&" or better = great night; "&IF(J6>=0,"D+","R+")&TEXT(ABS(J6)*100,"0.0")&" = on track to win. Collins holding it to "&IF(H6>=0,"D+","R+")&TEXT(ABS(H6)*100,"0.0")&" = Collins on track; "&IF(G6>=0,"D+","R+")&TEXT(ABS(G6)*100,"0.0")&" or worse for Ossoff = great for Collins. Turnout: par is about "&TEXT(D6,"#,##0")&" two-party votes ("&TEXT(Counties!AQ101/SUMIFS(Counties!$AQ:$AQ,Counties!$A:$A,"GA"),"0.0%")&" of the state). At 95% of par the break-even moves to "&IF((I6/0.95)>=0,"D+","R+")&TEXT(ABS((I6/0.95))*100,"0.0")&"; at 105%, to "&IF((I6/1.05)>=0,"D+","R+")&TEXT(ABS((I6/1.05))*100,"0.0")&"."
A7: GA | B7: Gwinnett | C7: Big metro core | D7: =Counties!AT108 | E7: =Counties!O108 | F7: =Counties!R108 | G7: =MAX(-1,MIN(1,Counties!O108+-0.05+Dashboard!$F$7)) | H7: =MAX(-1,MIN(1,Counties!O108+-0.01+Dashboard!$F$7)) | I7: =MAX(-1,MIN(1,Counties!O108+0.0+Dashboard!$F$7)) | J7: =MAX(-1,MIN(1,Counties!O108+0.01+Dashboard!$F$7)) | K7: =MAX(-1,MIN(1,Counties!O108+0.05+Dashboard!$F$7)) | L7: =G7*D7 | M7: =H7*D7 | N7: =I7*D7 | O7: =J7*D7 | P7: =K7*D7 | Q7: =D7*(1+I7)/2 | R7: =Counties!AH108 | S7: =IF(Counties!AH108="","",Counties!AH108*Counties!AF108) | T7: =Counties!AO108 | U7: =Counties!AU108 | V7: =Counties!AV108 | W7: =Counties!AY108 | X7: =IF(R7="","not in yet",IF(W7<>"",IF(W7>=0.05,"Great for Ossoff",IF(W7>=0.01,"Ossoff on track",IF(W7>-0.01,"Toss-up",IF(W7>-0.05,"Collins on track","Great for Collins"))))&" (margin + turnout)",IF((R7-I7)>=0.05,"Great for Ossoff",IF((R7-I7)>=0.01,"Ossoff on track",IF((R7-I7)>-0.01,"Toss-up",IF((R7-I7)>-0.05,"Collins on track","Great for Collins"))))&IF(Counties!AG108=1,""," (partial count)"))) | Y7: ="Break-even "&IF(I7>=0,"D+","R+")&TEXT(ABS(I7)*100,"0.0")&" ("&IF(N7>=0,"D +","R +")&TEXT(ABS(N7),"#,##0")&" net, about "&TEXT(Q7,"#,##0")&" Ossoff votes). Ossoff at "&IF(K7>=0,"D+","R+")&TEXT(ABS(K7)*100,"0.0")&" or better = great night; "&IF(J7>=0,"D+","R+")&TEXT(ABS(J7)*100,"0.0")&" = on track to win. Collins holding it to "&IF(H7>=0,"D+","R+")&TEXT(ABS(H7)*100,"0.0")&" = Collins on track; "&IF(G7>=0,"D+","R+")&TEXT(ABS(G7)*100,"0.0")&" or worse for Ossoff = great for Collins. Turnout: par is about "&TEXT(D7,"#,##0")&" two-party votes ("&TEXT(Counties!AQ108/SUMIFS(Counties!$AQ:$AQ,Counties!$A:$A,"GA"),"0.0%")&" of the state). At 95% of par the break-even moves to "&IF((I7/0.95)>=0,"D+","R+")&TEXT(ABS((I7/0.95))*100,"0.0")&"; at 105%, to "&IF((I7/1.05)>=0,"D+","R+")&TEXT(ABS((I7/1.05))*100,"0.0")&"."
A8: GA | B8: Cobb | C8: Big metro core | D8: =Counties!AT74 | E8: =Counties!O74 | F8: =Counties!R74 | G8: =MAX(-1,MIN(1,Counties!O74+-0.05+Dashboard!$F$7)) | H8: =MAX(-1,MIN(1,Counties!O74+-0.01+Dashboard!$F$7)) | I8: =MAX(-1,MIN(1,Counties!O74+0.0+Dashboard!$F$7)) | J8: =MAX(-1,MIN(1,Counties!O74+0.01+Dashboard!$F$7)) | K8: =MAX(-1,MIN(1,Counties!O74+0.05+Dashboard!$F$7)) | L8: =G8*D8 | M8: =H8*D8 | N8: =I8*D8 | O8: =J8*D8 | P8: =K8*D8 | Q8: =D8*(1+I8)/2 | R8: =Counties!AH74 | S8: =IF(Counties!AH74="","",Counties!AH74*Counties!AF74) | T8: =Counties!AO74 | U8: =Counties!AU74 | V8: =Counties!AV74 | W8: =Counties!AY74 | X8: =IF(R8="","not in yet",IF(W8<>"",IF(W8>=0.05,"Great for Ossoff",IF(W8>=0.01,"Ossoff on track",IF(W8>-0.01,"Toss-up",IF(W8>-0.05,"Collins on track","Great for Collins"))))&" (margin + turnout)",IF((R8-I8)>=0.05,"Great for Ossoff",IF((R8-I8)>=0.01,"Ossoff on track",IF((R8-I8)>-0.01,"Toss-up",IF((R8-I8)>-0.05,"Collins on track","Great for Collins"))))&IF(Counties!AG74=1,""," (partial count)"))) | Y8: ="Break-even "&IF(I8>=0,"D+","R+")&TEXT(ABS(I8)*100,"0.0")&" ("&IF(N8>=0,"D +","R +")&TEXT(ABS(N8),"#,##0")&" net, about "&TEXT(Q8,"#,##0")&" Ossoff votes). Ossoff at "&IF(K8>=0,"D+","R+")&TEXT(ABS(K8)*100,"0.0")&" or better = great night; "&IF(J8>=0,"D+","R+")&TEXT(ABS(J8)*100,"0.0")&" = on track to win. Collins holding it to "&IF(H8>=0,"D+","R+")&TEXT(ABS(H8)*100,"0.0")&" = Collins on track; "&IF(G8>=0,"D+","R+")&TEXT(ABS(G8)*100,"0.0")&" or worse for Ossoff = great for Collins. Turnout: par is about "&TEXT(D8,"#,##0")&" two-party votes ("&TEXT(Counties!AQ74/SUMIFS(Counties!$AQ:$AQ,Counties!$A:$A,"GA"),"0.0%")&" of the state). At 95% of par the break-even moves to "&IF((I8/0.95)>=0,"D+","R+")&TEXT(ABS((I8/0.95))*100,"0.0")&"; at 105%, to "&IF((I8/1.05)>=0,"D+","R+")&TEXT(ABS((I8/1.05))*100,"0.0")&"."
A9: GA | B9: DeKalb | C9: Big metro core | D9: =Counties!AT84 | E9: =Counties!O84 | F9: =Counties!R84 | G9: =MAX(-1,MIN(1,Counties!O84+-0.05+Dashboard!$F$7)) | H9: =MAX(-1,MIN(1,Counties!O84+-0.01+Dashboard!$F$7)) | I9: =MAX(-1,MIN(1,Counties!O84+0.0+Dashboard!$F$7)) | J9: =MAX(-1,MIN(1,Counties!O84+0.01+Dashboard!$F$7)) | K9: =MAX(-1,MIN(1,Counties!O84+0.05+Dashboard!$F$7)) | L9: =G9*D9 | M9: =H9*D9 | N9: =I9*D9 | O9: =J9*D9 | P9: =K9*D9 | Q9: =D9*(1+I9)/2 | R9: =Counties!AH84 | S9: =IF(Counties!AH84="","",Counties!AH84*Counties!AF84) | T9: =Counties!AO84 | U9: =Counties!AU84 | V9: =Counties!AV84 | W9: =Counties!AY84 | X9: =IF(R9="","not in yet",IF(W9<>"",IF(W9>=0.05,"Great for Ossoff",IF(W9>=0.01,"Ossoff on track",IF(W9>-0.01,"Toss-up",IF(W9>-0.05,"Collins on track","Great for Collins"))))&" (margin + turnout)",IF((R9-I9)>=0.05,"Great for Ossoff",IF((R9-I9)>=0.01,"Ossoff on track",IF((R9-I9)>-0.01,"Toss-up",IF((R9-I9)>-0.05,"Collins on track","Great for Collins"))))&IF(Counties!AG84=1,""," (partial count)"))) | Y9: ="Break-even "&IF(I9>=0,"D+","R+")&TEXT(ABS(I9)*100,"0.0")&" ("&IF(N9>=0,"D +","R +")&TEXT(ABS(N9),"#,##0")&" net, about "&TEXT(Q9,"#,##0")&" Ossoff votes). Ossoff at "&IF(K9>=0,"D+","R+")&TEXT(ABS(K9)*100,"0.0")&" or better = great night; "&IF(J9>=0,"D+","R+")&TEXT(ABS(J9)*100,"0.0")&" = on track to win. Collins holding it to "&IF(H9>=0,"D+","R+")&TEXT(ABS(H9)*100,"0.0")&" = Collins on track; "&IF(G9>=0,"D+","R+")&TEXT(ABS(G9)*100,"0.0")&" or worse for Ossoff = great for Collins. Turnout: par is about "&TEXT(D9,"#,##0")&" two-party votes ("&TEXT(Counties!AQ84/SUMIFS(Counties!$AQ:$AQ,Counties!$A:$A,"GA"),"0.0%")&" of the state). At 95% of par the break-even moves to "&IF((I9/0.95)>=0,"D+","R+")&TEXT(ABS((I9/0.95))*100,"0.0")&"; at 105%, to "&IF((I9/1.05)>=0,"D+","R+")&TEXT(ABS((I9/1.05))*100,"0.0")&"."
A10: GA | B10: Cherokee | C10: Mid-size/working metro | D10: =Counties!AT69 | E10: =Counties!O69 | F10: =Counties!R69 | G10: =MAX(-1,MIN(1,Counties!O69+-0.05+Dashboard!$F$7)) | H10: =MAX(-1,MIN(1,Counties!O69+-0.01+Dashboard!$F$7)) | I10: =MAX(-1,MIN(1,Counties!O69+0.0+Dashboard!$F$7)) | J10: =MAX(-1,MIN(1,Counties!O69+0.01+Dashboard!$F$7)) | K10: =MAX(-1,MIN(1,Counties!O69+0.05+Dashboard!$F$7)) | L10: =G10*D10 | M10: =H10*D10 | N10: =I10*D10 | O10: =J10*D10 | P10: =K10*D10 | Q10: =D10*(1+I10)/2 | R10: =Counties!AH69 | S10: =IF(Counties!AH69="","",Counties!AH69*Counties!AF69) | T10: =Counties!AO69 | U10: =Counties!AU69 | V10: =Counties!AV69 | W10: =Counties!AY69 | X10: =IF(R10="","not in yet",IF(W10<>"",IF(W10>=0.05,"Great for Ossoff",IF(W10>=0.01,"Ossoff on track",IF(W10>-0.01,"Toss-up",IF(W10>-0.05,"Collins on track","Great for Collins"))))&" (margin + turnout)",IF((R10-I10)>=0.05,"Great for Ossoff",IF((R10-I10)>=0.01,"Ossoff on track",IF((R10-I10)>-0.01,"Toss-up",IF((R10-I10)>-0.05,"Collins on track","Great for Collins"))))&IF(Counties!AG69=1,""," (partial count)"))) | Y10: ="Break-even "&IF(I10>=0,"D+","R+")&TEXT(ABS(I10)*100,"0.0")&" ("&IF(N10>=0,"D +","R +")&TEXT(ABS(N10),"#,##0")&" net, about "&TEXT(Q10,"#,##0")&" Ossoff votes). Ossoff at "&IF(K10>=0,"D+","R+")&TEXT(ABS(K10)*100,"0.0")&" or better = great night; "&IF(J10>=0,"D+","R+")&TEXT(ABS(J10)*100,"0.0")&" = on track to win. Collins holding it to "&IF(H10>=0,"D+","R+")&TEXT(ABS(H10)*100,"0.0")&" = Collins on track; "&IF(G10>=0,"D+","R+")&TEXT(ABS(G10)*100,"0.0")&" or worse for Ossoff = great for Collins. Turnout: par is about "&TEXT(D10,"#,##0")&" two-party votes ("&TEXT(Counties!AQ69/SUMIFS(Counties!$AQ:$AQ,Counties!$A:$A,"GA"),"0.0%")&" of the state). At 95% of par the break-even moves to "&IF((I10/0.95)>=0,"D+","R+")&TEXT(ABS((I10/0.95))*100,"0.0")&"; at 105%, to "&IF((I10/1.05)>=0,"D+","R+")&TEXT(ABS((I10/1.05))*100,"0.0")&"."
A11: GA | B11: Chatham | C11: Mid-size/working metro | D11: =Counties!AT66 | E11: =Counties!O66 | F11: =Counties!R66 | G11: =MAX(-1,MIN(1,Counties!O66+-0.05+Dashboard!$F$7)) | H11: =MAX(-1,MIN(1,Counties!O66+-0.01+Dashboard!$F$7)) | I11: =MAX(-1,MIN(1,Counties!O66+0.0+Dashboard!$F$7)) | J11: =MAX(-1,MIN(1,Counties!O66+0.01+Dashboard!$F$7)) | K11: =MAX(-1,MIN(1,Counties!O66+0.05+Dashboard!$F$7)) | L11: =G11*D11 | M11: =H11*D11 | N11: =I11*D11 | O11: =J11*D11 | P11: =K11*D11 | Q11: =D11*(1+I11)/2 | R11: =Counties!AH66 | S11: =IF(Counties!AH66="","",Counties!AH66*Counties!AF66) | T11: =Counties!AO66 | U11: =Counties!AU66 | V11: =Counties!AV66 | W11: =Counties!AY66 | X11: =IF(R11="","not in yet",IF(W11<>"",IF(W11>=0.05,"Great for Ossoff",IF(W11>=0.01,"Ossoff on track",IF(W11>-0.01,"Toss-up",IF(W11>-0.05,"Collins on track","Great for Collins"))))&" (margin + turnout)",IF((R11-I11)>=0.05,"Great for Ossoff",IF((R11-I11)>=0.01,"Ossoff on track",IF((R11-I11)>-0.01,"Toss-up",IF((R11-I11)>-0.05,"Collins on track","Great for Collins"))))&IF(Counties!AG66=1,""," (partial count)"))) | Y11: ="Break-even "&IF(I11>=0,"D+","R+")&TEXT(ABS(I11)*100,"0.0")&" ("&IF(N11>=0,"D +","R +")&TEXT(ABS(N11),"#,##0")&" net, about "&TEXT(Q11,"#,##0")&" Ossoff votes). Ossoff at "&IF(K11>=0,"D+","R+")&TEXT(ABS(K11)*100,"0.0")&" or better = great night; "&IF(J11>=0,"D+","R+")&TEXT(ABS(J11)*100,"0.0")&" = on track to win. Collins holding it to "&IF(H11>=0,"D+","R+")&TEXT(ABS(H11)*100,"0.0")&" = Collins on track; "&IF(G11>=0,"D+","R+")&TEXT(ABS(G11)*100,"0.0")&" or worse for Ossoff = great for Collins. Turnout: par is about "&TEXT(D11,"#,##0")&" two-party votes ("&TEXT(Counties!AQ66/SUMIFS(Counties!$AQ:$AQ,Counties!$A:$A,"GA"),"0.0%")&" of the state). At 95% of par the break-even moves to "&IF((I11/0.95)>=0,"D+","R+")&TEXT(ABS((I11/0.95))*100,"0.0")&"; at 105%, to "&IF((I11/1.05)>=0,"D+","R+")&TEXT(ABS((I11/1.05))*100,"0.0")&"."
A12: GA | B12: Forsyth | C12: College suburb/metro | D12: =Counties!AT99 | E12: =Counties!O99 | F12: =Counties!R99 | G12: =MAX(-1,MIN(1,Counties!O99+-0.05+Dashboard!$F$7)) | H12: =MAX(-1,MIN(1,Counties!O99+-0.01+Dashboard!$F$7)) | I12: =MAX(-1,MIN(1,Counties!O99+0.0+Dashboard!$F$7)) | J12: =MAX(-1,MIN(1,Counties!O99+0.01+Dashboard!$F$7)) | K12: =MAX(-1,MIN(1,Counties!O99+0.05+Dashboard!$F$7)) | L12: =G12*D12 | M12: =H12*D12 | N12: =I12*D12 | O12: =J12*D12 | P12: =K12*D12 | Q12: =D12*(1+I12)/2 | R12: =Counties!AH99 | S12: =IF(Counties!AH99="","",Counties!AH99*Counties!AF99) | T12: =Counties!AO99 | U12: =Counties!AU99 | V12: =Counties!AV99 | W12: =Counties!AY99 | X12: =IF(R12="","not in yet",IF(W12<>"",IF(W12>=0.05,"Great for Ossoff",IF(W12>=0.01,"Ossoff on track",IF(W12>-0.01,"Toss-up",IF(W12>-0.05,"Collins on track","Great for Collins"))))&" (margin + turnout)",IF((R12-I12)>=0.05,"Great for Ossoff",IF((R12-I12)>=0.01,"Ossoff on track",IF((R12-I12)>-0.01,"Toss-up",IF((R12-I12)>-0.05,"Collins on track","Great for Collins"))))&IF(Counties!AG99=1,""," (partial count)"))) | Y12: ="Break-even "&IF(I12>=0,"D+","R+")&TEXT(ABS(I12)*100,"0.0")&" ("&IF(N12>=0,"D +","R +")&TEXT(ABS(N12),"#,##0")&" net, about "&TEXT(Q12,"#,##0")&" Ossoff votes). Ossoff at "&IF(K12>=0,"D+","R+")&TEXT(ABS(K12)*100,"0.0")&" or better = great night; "&IF(J12>=0,"D+","R+")&TEXT(ABS(J12)*100,"0.0")&" = on track to win. Collins holding it to "&IF(H12>=0,"D+","R+")&TEXT(ABS(H12)*100,"0.0")&" = Collins on track; "&IF(G12>=0,"D+","R+")&TEXT(ABS(G12)*100,"0.0")&" or worse for Ossoff = great for Collins. Turnout: par is about "&TEXT(D12,"#,##0")&" two-party votes ("&TEXT(Counties!AQ99/SUMIFS(Counties!$AQ:$AQ,Counties!$A:$A,"GA"),"0.0%")&" of the state). At 95% of par the break-even moves to "&IF((I12/0.95)>=0,"D+","R+")&TEXT(ABS((I12/0.95))*100,"0.0")&"; at 105%, to "&IF((I12/1.05)>=0,"D+","R+")&TEXT(ABS((I12/1.05))*100,"0.0")&"."
A13: GA | B13: Henry | C13: Black Belt | D13: =Counties!AT116 | E13: =Counties!O116 | F13: =Counties!R116 | G13: =MAX(-1,MIN(1,Counties!O116+-0.05+Dashboard!$F$7)) | H13: =MAX(-1,MIN(1,Counties!O116+-0.01+Dashboard!$F$7)) | I13: =MAX(-1,MIN(1,Counties!O116+0.0+Dashboard!$F$7)) | J13: =MAX(-1,MIN(1,Counties!O116+0.01+Dashboard!$F$7)) | K13: =MAX(-1,MIN(1,Counties!O116+0.05+Dashboard!$F$7)) | L13: =G13*D13 | M13: =H13*D13 | N13: =I13*D13 | O13: =J13*D13 | P13: =K13*D13 | Q13: =D13*(1+I13)/2 | R13: =Counties!AH116 | S13: =IF(Counties!AH116="","",Counties!AH116*Counties!AF116) | T13: =Counties!AO116 | U13: =Counties!AU116 | V13: =Counties!AV116 | W13: =Counties!AY116 | X13: =IF(R13="","not in yet",IF(W13<>"",IF(W13>=0.05,"Great for Ossoff",IF(W13>=0.01,"Ossoff on track",IF(W13>-0.01,"Toss-up",IF(W13>-0.05,"Collins on track","Great for Collins"))))&" (margin + turnout)",IF((R13-I13)>=0.05,"Great for Ossoff",IF((R13-I13)>=0.01,"Ossoff on track",IF((R13-I13)>-0.01,"Toss-up",IF((R13-I13)>-0.05,"Collins on track","Great for Collins"))))&IF(Counties!AG116=1,""," (partial count)"))) | Y13: ="Break-even "&IF(I13>=0,"D+","R+")&TEXT(ABS(I13)*100,"0.0")&" ("&IF(N13>=0,"D +","R +")&TEXT(ABS(N13),"#,##0")&" net, about "&TEXT(Q13,"#,##0")&" Ossoff votes). Ossoff at "&IF(K13>=0,"D+","R+")&TEXT(ABS(K13)*100,"0.0")&" or better = great night; "&IF(J13>=0,"D+","R+")&TEXT(ABS(J13)*100,"0.0")&" = on track to win. Collins holding it to "&IF(H13>=0,"D+","R+")&TEXT(ABS(H13)*100,"0.0")&" = Collins on track; "&IF(G13>=0,"D+","R+")&TEXT(ABS(G13)*100,"0.0")&" or worse for Ossoff = great for Collins. Turnout: par is about "&TEXT(D13,"#,##0")&" two-party votes ("&TEXT(Counties!AQ116/SUMIFS(Counties!$AQ:$AQ,Counties!$A:$A,"GA"),"0.0%")&" of the state). At 95% of par the break-even moves to "&IF((I13/0.95)>=0,"D+","R+")&TEXT(ABS((I13/0.95))*100,"0.0")&"; at 105%, to "&IF((I13/1.05)>=0,"D+","R+")&TEXT(ABS((I13/1.05))*100,"0.0")&"."
A14: GA | B14: Clayton | C14: Black Belt | D14: =Counties!AT72 | E14: =Counties!O72 | F14: =Counties!R72 | G14: =MAX(-1,MIN(1,Counties!O72+-0.05+Dashboard!$F$7)) | H14: =MAX(-1,MIN(1,Counties!O72+-0.01+Dashboard!$F$7)) | I14: =MAX(-1,MIN(1,Counties!O72+0.0+Dashboard!$F$7)) | J14: =MAX(-1,MIN(1,Counties!O72+0.01+Dashboard!$F$7)) | K14: =MAX(-1,MIN(1,Counties!O72+0.05+Dashboard!$F$7)) | L14: =G14*D14 | M14: =H14*D14 | N14: =I14*D14 | O14: =J14*D14 | P14: =K14*D14 | Q14: =D14*(1+I14)/2 | R14: =Counties!AH72 | S14: =IF(Counties!AH72="","",Counties!AH72*Counties!AF72) | T14: =Counties!AO72 | U14: =Counties!AU72 | V14: =Counties!AV72 | W14: =Counties!AY72 | X14: =IF(R14="","not in yet",IF(W14<>"",IF(W14>=0.05,"Great for Ossoff",IF(W14>=0.01,"Ossoff on track",IF(W14>-0.01,"Toss-up",IF(W14>-0.05,"Collins on track","Great for Collins"))))&" (margin + turnout)",IF((R14-I14)>=0.05,"Great for Ossoff",IF((R14-I14)>=0.01,"Ossoff on track",IF((R14-I14)>-0.01,"Toss-up",IF((R14-I14)>-0.05,"Collins on track","Great for Collins"))))&IF(Counties!AG72=1,""," (partial count)"))) | Y14: ="Break-even "&IF(I14>=0,"D+","R+")&TEXT(ABS(I14)*100,"0.0")&" ("&IF(N14>=0,"D +","R +")&TEXT(ABS(N14),"#,##0")&" net, about "&TEXT(Q14,"#,##0")&" Ossoff votes). Ossoff at "&IF(K14>=0,"D+","R+")&TEXT(ABS(K14)*100,"0.0")&" or better = great night; "&IF(J14>=0,"D+","R+")&TEXT(ABS(J14)*100,"0.0")&" = on track to win. Collins holding it to "&IF(H14>=0,"D+","R+")&TEXT(ABS(H14)*100,"0.0")&" = Collins on track; "&IF(G14>=0,"D+","R+")&TEXT(ABS(G14)*100,"0.0")&" or worse for Ossoff = great for Collins. Turnout: par is about "&TEXT(D14,"#,##0")&" two-party votes ("&TEXT(Counties!AQ72/SUMIFS(Counties!$AQ:$AQ,Counties!$A:$A,"GA"),"0.0%")&" of the state). At 95% of par the break-even moves to "&IF((I14/0.95)>=0,"D+","R+")&TEXT(ABS((I14/0.95))*100,"0.0")&"; at 105%, to "&IF((I14/1.05)>=0,"D+","R+")&TEXT(ABS((I14/1.05))*100,"0.0")&"."
A15: GA | B15: Hall | C15: Mid-size/working metro | D15: =Counties!AT110 | E15: =Counties!O110 | F15: =Counties!R110 | G15: =MAX(-1,MIN(1,Counties!O110+-0.05+Dashboard!$F$7)) | H15: =MAX(-1,MIN(1,Counties!O110+-0.01+Dashboard!$F$7)) | I15: =MAX(-1,MIN(1,Counties!O110+0.0+Dashboard!$F$7)) | J15: =MAX(-1,MIN(1,Counties!O110+0.01+Dashboard!$F$7)) | K15: =MAX(-1,MIN(1,Counties!O110+0.05+Dashboard!$F$7)) | L15: =G15*D15 | M15: =H15*D15 | N15: =I15*D15 | O15: =J15*D15 | P15: =K15*D15 | Q15: =D15*(1+I15)/2 | R15: =Counties!AH110 | S15: =IF(Counties!AH110="","",Counties!AH110*Counties!AF110) | T15: =Counties!AO110 | U15: =Counties!AU110 | V15: =Counties!AV110 | W15: =Counties!AY110 | X15: =IF(R15="","not in yet",IF(W15<>"",IF(W15>=0.05,"Great for Ossoff",IF(W15>=0.01,"Ossoff on track",IF(W15>-0.01,"Toss-up",IF(W15>-0.05,"Collins on track","Great for Collins"))))&" (margin + turnout)",IF((R15-I15)>=0.05,"Great for Ossoff",IF((R15-I15)>=0.01,"Ossoff on track",IF((R15-I15)>-0.01,"Toss-up",IF((R15-I15)>-0.05,"Collins on track","Great for Collins"))))&IF(Counties!AG110=1,""," (partial count)"))) | Y15: ="Break-even "&IF(I15>=0,"D+","R+")&TEXT(ABS(I15)*100,"0.0")&" ("&IF(N15>=0,"D +","R +")&TEXT(ABS(N15),"#,##0")&" net, about "&TEXT(Q15,"#,##0")&" Ossoff votes). Ossoff at "&IF(K15>=0,"D+","R+")&TEXT(ABS(K15)*100,"0.0")&" or better = great night; "&IF(J15>=0,"D+","R+")&TEXT(ABS(J15)*100,"0.0")&" = on track to win. Collins holding it to "&IF(H15>=0,"D+","R+")&TEXT(ABS(H15)*100,"0.0")&" = Collins on track; "&IF(G15>=0,"D+","R+")&TEXT(ABS(G15)*100,"0.0")&" or worse for Ossoff = great for Collins. Turnout: par is about "&TEXT(D15,"#,##0")&" two-party votes ("&TEXT(Counties!AQ110/SUMIFS(Counties!$AQ:$AQ,Counties!$A:$A,"GA"),"0.0%")&" of the state). At 95% of par the break-even moves to "&IF((I15/0.95)>=0,"D+","R+")&TEXT(ABS((I15/0.95))*100,"0.0")&"; at 105%, to "&IF((I15/1.05)>=0,"D+","R+")&TEXT(ABS((I15/1.05))*100,"0.0")&"."
A16: GA | B16: Bartow | C16: Mid-size/working metro | D16: =Counties!AT49 | E16: =Counties!O49 | F16: =Counties!R49 | G16: =MAX(-1,MIN(1,Counties!O49+-0.05+Dashboard!$F$7)) | H16: =MAX(-1,MIN(1,Counties!O49+-0.01+Dashboard!$F$7)) | I16: =MAX(-1,MIN(1,Counties!O49+0.0+Dashboard!$F$7)) | J16: =MAX(-1,MIN(1,Counties!O49+0.01+Dashboard!$F$7)) | K16: =MAX(-1,MIN(1,Counties!O49+0.05+Dashboard!$F$7)) | L16: =G16*D16 | M16: =H16*D16 | N16: =I16*D16 | O16: =J16*D16 | P16: =K16*D16 | Q16: =D16*(1+I16)/2 | R16: =Counties!AH49 | S16: =IF(Counties!AH49="","",Counties!AH49*Counties!AF49) | T16: =Counties!AO49 | U16: =Counties!AU49 | V16: =Counties!AV49 | W16: =Counties!AY49 | X16: =IF(R16="","not in yet",IF(W16<>"",IF(W16>=0.05,"Great for Ossoff",IF(W16>=0.01,"Ossoff on track",IF(W16>-0.01,"Toss-up",IF(W16>-0.05,"Collins on track","Great for Collins"))))&" (margin + turnout)",IF((R16-I16)>=0.05,"Great for Ossoff",IF((R16-I16)>=0.01,"Ossoff on track",IF((R16-I16)>-0.01,"Toss-up",IF((R16-I16)>-0.05,"Collins on track","Great for Collins"))))&IF(Counties!AG49=1,""," (partial count)"))) | Y16: ="Break-even "&IF(I16>=0,"D+","R+")&TEXT(ABS(I16)*100,"0.0")&" ("&IF(N16>=0,"D +","R +")&TEXT(ABS(N16),"#,##0")&" net, about "&TEXT(Q16,"#,##0")&" Ossoff votes). Ossoff at "&IF(K16>=0,"D+","R+")&TEXT(ABS(K16)*100,"0.0")&" or better = great night; "&IF(J16>=0,"D+","R+")&TEXT(ABS(J16)*100,"0.0")&" = on track to win. Collins holding it to "&IF(H16>=0,"D+","R+")&TEXT(ABS(H16)*100,"0.0")&" = Collins on track; "&IF(G16>=0,"D+","R+")&TEXT(ABS(G16)*100,"0.0")&" or worse for Ossoff = great for Collins. Turnout: par is about "&TEXT(D16,"#,##0")&" two-party votes ("&TEXT(Counties!AQ49/SUMIFS(Counties!$AQ:$AQ,Counties!$A:$A,"GA"),"0.0%")&" of the state). At 95% of par the break-even moves to "&IF((I16/0.95)>=0,"D+","R+")&TEXT(ABS((I16/0.95))*100,"0.0")&"; at 105%, to "&IF((I16/1.05)>=0,"D+","R+")&TEXT(ABS((I16/1.05))*100,"0.0")&"."
A17: Iowa: Josh Turek vs Ashley Hinson · 2024 statewide R+13.4 (R+13.2 with 2022's turnout pattern)
A18: IA | B18: Polk | C18: Mid-size/working metro | D18: =Counties!AT277 | E18: =Counties!O277 | F18: =Counties!R277 | G18: =MAX(-1,MIN(1,Counties!O277+-0.05+Dashboard!$F$8)) | H18: =MAX(-1,MIN(1,Counties!O277+-0.01+Dashboard!$F$8)) | I18: =MAX(-1,MIN(1,Counties!O277+0.0+Dashboard!$F$8)) | J18: =MAX(-1,MIN(1,Counties!O277+0.01+Dashboard!$F$8)) | K18: =MAX(-1,MIN(1,Counties!O277+0.05+Dashboard!$F$8)) | L18: =G18*D18 | M18: =H18*D18 | N18: =I18*D18 | O18: =J18*D18 | P18: =K18*D18 | Q18: =D18*(1+I18)/2 | R18: =Counties!AH277 | S18: =IF(Counties!AH277="","",Counties!AH277*Counties!AF277) | T18: =Counties!AO277 | U18: =Counties!AU277 | V18: =Counties!AV277 | W18: =Counties!AY277 | X18: =IF(R18="","not in yet",IF(W18<>"",IF(W18>=0.05,"Great for Turek",IF(W18>=0.01,"Turek on track",IF(W18>-0.01,"Toss-up",IF(W18>-0.05,"Hinson on track","Great for Hinson"))))&" (margin + turnout)",IF((R18-I18)>=0.05,"Great for Turek",IF((R18-I18)>=0.01,"Turek on track",IF((R18-I18)>-0.01,"Toss-up",IF((R18-I18)>-0.05,"Hinson on track","Great for Hinson"))))&IF(Counties!AG277=1,""," (partial count)"))) | Y18: ="Break-even "&IF(I18>=0,"D+","R+")&TEXT(ABS(I18)*100,"0.0")&" ("&IF(N18>=0,"D +","R +")&TEXT(ABS(N18),"#,##0")&" net, about "&TEXT(Q18,"#,##0")&" Turek votes). Turek at "&IF(K18>=0,"D+","R+")&TEXT(ABS(K18)*100,"0.0")&" or better = great night; "&IF(J18>=0,"D+","R+")&TEXT(ABS(J18)*100,"0.0")&" = on track to win. Hinson holding it to "&IF(H18>=0,"D+","R+")&TEXT(ABS(H18)*100,"0.0")&" = Hinson on track; "&IF(G18>=0,"D+","R+")&TEXT(ABS(G18)*100,"0.0")&" or worse for Turek = great for Hinson. Turnout: par is about "&TEXT(D18,"#,##0")&" two-party votes ("&TEXT(Counties!AQ277/SUMIFS(Counties!$AQ:$AQ,Counties!$A:$A,"IA"),"0.0%")&" of the state). At 95% of par the break-even moves to "&IF((I18/0.95)>=0,"D+","R+")&TEXT(ABS((I18/0.95))*100,"0.0")&"; at 105%, to "&IF((I18/1.05)>=0,"D+","R+")&TEXT(ABS((I18/1.05))*100,"0.0")&"."
A19: IA | B19: Linn | C19: Mid-size/working metro | D19: =Counties!AT257 | E19: =Counties!O257 | F19: =Counties!R257 | G19: =MAX(-1,MIN(1,Counties!O257+-0.05+Dashboard!$F$8)) | H19: =MAX(-1,MIN(1,Counties!O257+-0.01+Dashboard!$F$8)) | I19: =MAX(-1,MIN(1,Counties!O257+0.0+Dashboard!$F$8)) | J19: =MAX(-1,MIN(1,Counties!O257+0.01+Dashboard!$F$8)) | K19: =MAX(-1,MIN(1,Counties!O257+0.05+Dashboard!$F$8)) | L19: =G19*D19 | M19: =H19*D19 | N19: =I19*D19 | O19: =J19*D19 | P19: =K19*D19 | Q19: =D19*(1+I19)/2 | R19: =Counties!AH257 | S19: =IF(Counties!AH257="","",Counties!AH257*Counties!AF257) | T19: =Counties!AO257 | U19: =Counties!AU257 | V19: =Counties!AV257 | W19: =Counties!AY257 | X19: =IF(R19="","not in yet",IF(W19<>"",IF(W19>=0.05,"Great for Turek",IF(W19>=0.01,"Turek on track",IF(W19>-0.01,"Toss-up",IF(W19>-0.05,"Hinson on track","Great for Hinson"))))&" (margin + turnout)",IF((R19-I19)>=0.05,"Great for Turek",IF((R19-I19)>=0.01,"Turek on track",IF((R19-I19)>-0.01,"Toss-up",IF((R19-I19)>-0.05,"Hinson on track","Great for Hinson"))))&IF(Counties!AG257=1,""," (partial count)"))) | Y19: ="Break-even "&IF(I19>=0,"D+","R+")&TEXT(ABS(I19)*100,"0.0")&" ("&IF(N19>=0,"D +","R +")&TEXT(ABS(N19),"#,##0")&" net, about "&TEXT(Q19,"#,##0")&" Turek votes). Turek at "&IF(K19>=0,"D+","R+")&TEXT(ABS(K19)*100,"0.0")&" or better = great night; "&IF(J19>=0,"D+","R+")&TEXT(ABS(J19)*100,"0.0")&" = on track to win. Hinson holding it to "&IF(H19>=0,"D+","R+")&TEXT(ABS(H19)*100,"0.0")&" = Hinson on track; "&IF(G19>=0,"D+","R+")&TEXT(ABS(G19)*100,"0.0")&" or worse for Turek = great for Hinson. Turnout: par is about "&TEXT(D19,"#,##0")&" two-party votes ("&TEXT(Counties!AQ257/SUMIFS(Counties!$AQ:$AQ,Counties!$A:$A,"IA"),"0.0%")&" of the state). At 95% of par the break-even moves to "&IF((I19/0.95)>=0,"D+","R+")&TEXT(ABS((I19/0.95))*100,"0.0")&"; at 105%, to "&IF((I19/1.05)>=0,"D+","R+")&TEXT(ABS((I19/1.05))*100,"0.0")&"."
A20: IA | B20: Scott | C20: Mid-size/working metro | D20: =Counties!AT282 | E20: =Counties!O282 | F20: =Counties!R282 | G20: =MAX(-1,MIN(1,Counties!O282+-0.05+Dashboard!$F$8)) | H20: =MAX(-1,MIN(1,Counties!O282+-0.01+Dashboard!$F$8)) | I20: =MAX(-1,MIN(1,Counties!O282+0.0+Dashboard!$F$8)) | J20: =MAX(-1,MIN(1,Counties!O282+0.01+Dashboard!$F$8)) | K20: =MAX(-1,MIN(1,Counties!O282+0.05+Dashboard!$F$8)) | L20: =G20*D20 | M20: =H20*D20 | N20: =I20*D20 | O20: =J20*D20 | P20: =K20*D20 | Q20: =D20*(1+I20)/2 | R20: =Counties!AH282 | S20: =IF(Counties!AH282="","",Counties!AH282*Counties!AF282) | T20: =Counties!AO282 | U20: =Counties!AU282 | V20: =Counties!AV282 | W20: =Counties!AY282 | X20: =IF(R20="","not in yet",IF(W20<>"",IF(W20>=0.05,"Great for Turek",IF(W20>=0.01,"Turek on track",IF(W20>-0.01,"Toss-up",IF(W20>-0.05,"Hinson on track","Great for Hinson"))))&" (margin + turnout)",IF((R20-I20)>=0.05,"Great for Turek",IF((R20-I20)>=0.01,"Turek on track",IF((R20-I20)>-0.01,"Toss-up",IF((R20-I20)>-0.05,"Hinson on track","Great for Hinson"))))&IF(Counties!AG282=1,""," (partial count)"))) | Y20: ="Break-even "&IF(I20>=0,"D+","R+")&TEXT(ABS(I20)*100,"0.0")&" ("&IF(N20>=0,"D +","R +")&TEXT(ABS(N20),"#,##0")&" net, about "&TEXT(Q20,"#,##0")&" Turek votes). Turek at "&IF(K20>=0,"D+","R+")&TEXT(ABS(K20)*100,"0.0")&" or better = great night; "&IF(J20>=0,"D+","R+")&TEXT(ABS(J20)*100,"0.0")&" = on track to win. Hinson holding it to "&IF(H20>=0,"D+","R+")&TEXT(ABS(H20)*100,"0.0")&" = Hinson on track; "&IF(G20>=0,"D+","R+")&TEXT(ABS(G20)*100,"0.0")&" or worse for Turek = great for Hinson. Turnout: par is about "&TEXT(D20,"#,##0")&" two-party votes ("&TEXT(Counties!AQ282/SUMIFS(Counties!$AQ:$AQ,Counties!$A:$A,"IA"),"0.0%")&" of the state). At 95% of par the break-even moves to "&IF((I20/0.95)>=0,"D+","R+")&TEXT(ABS((I20/0.95))*100,"0.0")&"; at 105%, to "&IF((I20/1.05)>=0,"D+","R+")&TEXT(ABS((I20/1.05))*100,"0.0")&"."
A21: IA | B21: Johnson | C21: College suburb/metro | D21: =Counties!AT252 | E21: =Counties!O252 | F21: =Counties!R252 | G21: =MAX(-1,MIN(1,Counties!O252+-0.05+Dashboard!$F$8)) | H21: =MAX(-1,MIN(1,Counties!O252+-0.01+Dashboard!$F$8)) | I21: =MAX(-1,MIN(1,Counties!O252+0.0+Dashboard!$F$8)) | J21: =MAX(-1,MIN(1,Counties!O252+0.01+Dashboard!$F$8)) | K21: =MAX(-1,MIN(1,Counties!O252+0.05+Dashboard!$F$8)) | L21: =G21*D21 | M21: =H21*D21 | N21: =I21*D21 | O21: =J21*D21 | P21: =K21*D21 | Q21: =D21*(1+I21)/2 | R21: =Counties!AH252 | S21: =IF(Counties!AH252="","",Counties!AH252*Counties!AF252) | T21: =Counties!AO252 | U21: =Counties!AU252 | V21: =Counties!AV252 | W21: =Counties!AY252 | X21: =IF(R21="","not in yet",IF(W21<>"",IF(W21>=0.05,"Great for Turek",IF(W21>=0.01,"Turek on track",IF(W21>-0.01,"Toss-up",IF(W21>-0.05,"Hinson on track","Great for Hinson"))))&" (margin + turnout)",IF((R21-I21)>=0.05,"Great for Turek",IF((R21-I21)>=0.01,"Turek on track",IF((R21-I21)>-0.01,"Toss-up",IF((R21-I21)>-0.05,"Hinson on track","Great for Hinson"))))&IF(Counties!AG252=1,""," (partial count)"))) | Y21: ="Break-even "&IF(I21>=0,"D+","R+")&TEXT(ABS(I21)*100,"0.0")&" ("&IF(N21>=0,"D +","R +")&TEXT(ABS(N21),"#,##0")&" net, about "&TEXT(Q21,"#,##0")&" Turek votes). Turek at "&IF(K21>=0,"D+","R+")&TEXT(ABS(K21)*100,"0.0")&" or better = great night; "&IF(J21>=0,"D+","R+")&TEXT(ABS(J21)*100,"0.0")&" = on track to win. Hinson holding it to "&IF(H21>=0,"D+","R+")&TEXT(ABS(H21)*100,"0.0")&" = Hinson on track; "&IF(G21>=0,"D+","R+")&TEXT(ABS(G21)*100,"0.0")&" or worse for Turek = great for Hinson. Turnout: par is about "&TEXT(D21,"#,##0")&" two-party votes ("&TEXT(Counties!AQ252/SUMIFS(Counties!$AQ:$AQ,Counties!$A:$A,"IA"),"0.0%")&" of the state). At 95% of par the break-even moves to "&IF((I21/0.95)>=0,"D+","R+")&TEXT(ABS((I21/0.95))*100,"0.0")&"; at 105%, to "&IF((I21/1.05)>=0,"D+","R+")&TEXT(ABS((I21/1.05))*100,"0.0")&"."
A22: IA | B22: Black Hawk | C22: Mid-size/working metro | D22: =Counties!AT207 | E22: =Counties!O207 | F22: =Counties!R207 | G22: =MAX(-1,MIN(1,Counties!O207+-0.05+Dashboard!$F$8)) | H22: =MAX(-1,MIN(1,Counties!O207+-0.01+Dashboard!$F$8)) | I22: =MAX(-1,MIN(1,Counties!O207+0.0+Dashboard!$F$8)) | J22: =MAX(-1,MIN(1,Counties!O207+0.01+Dashboard!$F$8)) | K22: =MAX(-1,MIN(1,Counties!O207+0.05+Dashboard!$F$8)) | L22: =G22*D22 | M22: =H22*D22 | N22: =I22*D22 | O22: =J22*D22 | P22: =K22*D22 | Q22: =D22*(1+I22)/2 | R22: =Counties!AH207 | S22: =IF(Counties!AH207="","",Counties!AH207*Counties!AF207) | T22: =Counties!AO207 | U22: =Counties!AU207 | V22: =Counties!AV207 | W22: =Counties!AY207 | X22: =IF(R22="","not in yet",IF(W22<>"",IF(W22>=0.05,"Great for Turek",IF(W22>=0.01,"Turek on track",IF(W22>-0.01,"Toss-up",IF(W22>-0.05,"Hinson on track","Great for Hinson"))))&" (margin + turnout)",IF((R22-I22)>=0.05,"Great for Turek",IF((R22-I22)>=0.01,"Turek on track",IF((R22-I22)>-0.01,"Toss-up",IF((R22-I22)>-0.05,"Hinson on track","Great for Hinson"))))&IF(Counties!AG207=1,""," (partial count)"))) | Y22: ="Break-even "&IF(I22>=0,"D+","R+")&TEXT(ABS(I22)*100,"0.0")&" ("&IF(N22>=0,"D +","R +")&TEXT(ABS(N22),"#,##0")&" net, about "&TEXT(Q22,"#,##0")&" Turek votes). Turek at "&IF(K22>=0,"D+","R+")&TEXT(ABS(K22)*100,"0.0")&" or better = great night; "&IF(J22>=0,"D+","R+")&TEXT(ABS(J22)*100,"0.0")&" = on track to win. Hinson holding it to "&IF(H22>=0,"D+","R+")&TEXT(ABS(H22)*100,"0.0")&" = Hinson on track; "&IF(G22>=0,"D+","R+")&TEXT(ABS(G22)*100,"0.0")&" or worse for Turek = great for Hinson. Turnout: par is about "&TEXT(D22,"#,##0")&" two-party votes ("&TEXT(Counties!AQ207/SUMIFS(Counties!$AQ:$AQ,Counties!$A:$A,"IA"),"0.0%")&" of the state). At 95% of par the break-even moves to "&IF((I22/0.95)>=0,"D+","R+")&TEXT(ABS((I22/0.95))*100,"0.0")&"; at 105%, to "&IF((I22/1.05)>=0,"D+","R+")&TEXT(ABS((I22/1.05))*100,"0.0")&"."
A23: IA | B23: Dallas | C23: College suburb/metro | D23: =Counties!AT225 | E23: =Counties!O225 | F23: =Counties!R225 | G23: =MAX(-1,MIN(1,Counties!O225+-0.05+Dashboard!$F$8)) | H23: =MAX(-1,MIN(1,Counties!O225+-0.01+Dashboard!$F$8)) | I23: =MAX(-1,MIN(1,Counties!O225+0.0+Dashboard!$F$8)) | J23: =MAX(-1,MIN(1,Counties!O225+0.01+Dashboard!$F$8)) | K23: =MAX(-1,MIN(1,Counties!O225+0.05+Dashboard!$F$8)) | L23: =G23*D23 | M23: =H23*D23 | N23: =I23*D23 | O23: =J23*D23 | P23: =K23*D23 | Q23: =D23*(1+I23)/2 | R23: =Counties!AH225 | S23: =IF(Counties!AH225="","",Counties!AH225*Counties!AF225) | T23: =Counties!AO225 | U23: =Counties!AU225 | V23: =Counties!AV225 | W23: =Counties!AY225 | X23: =IF(R23="","not in yet",IF(W23<>"",IF(W23>=0.05,"Great for Turek",IF(W23>=0.01,"Turek on track",IF(W23>-0.01,"Toss-up",IF(W23>-0.05,"Hinson on track","Great for Hinson"))))&" (margin + turnout)",IF((R23-I23)>=0.05,"Great for Turek",IF((R23-I23)>=0.01,"Turek on track",IF((R23-I23)>-0.01,"Toss-up",IF((R23-I23)>-0.05,"Hinson on track","Great for Hinson"))))&IF(Counties!AG225=1,""," (partial count)"))) | Y23: ="Break-even "&IF(I23>=0,"D+","R+")&TEXT(ABS(I23)*100,"0.0")&" ("&IF(N23>=0,"D +","R +")&TEXT(ABS(N23),"#,##0")&" net, about "&TEXT(Q23,"#,##0")&" Turek votes). Turek at "&IF(K23>=0,"D+","R+")&TEXT(ABS(K23)*100,"0.0")&" or better = great night; "&IF(J23>=0,"D+","R+")&TEXT(ABS(J23)*100,"0.0")&" = on track to win. Hinson holding it to "&IF(H23>=0,"D+","R+")&TEXT(ABS(H23)*100,"0.0")&" = Hinson on track; "&IF(G23>=0,"D+","R+")&TEXT(ABS(G23)*100,"0.0")&" or worse for Turek = great for Hinson. Turnout: par is about "&TEXT(D23,"#,##0")&" two-party votes ("&TEXT(Counties!AQ225/SUMIFS(Counties!$AQ:$AQ,Counties!$A:$A,"IA"),"0.0%")&" of the state). At 95% of par the break-even moves to "&IF((I23/0.95)>=0,"D+","R+")&TEXT(ABS((I23/0.95))*100,"0.0")&"; at 105%, to "&IF((I23/1.05)>=0,"D+","R+")&TEXT(ABS((I23/1.05))*100,"0.0")&"."
A24: IA | B24: Dubuque | C24: Small town & rural | D24: =Counties!AT231 | E24: =Counties!O231 | F24: =Counties!R231 | G24: =MAX(-1,MIN(1,Counties!O231+-0.05+Dashboard!$F$8)) | H24: =MAX(-1,MIN(1,Counties!O231+-0.01+Dashboard!$F$8)) | I24: =MAX(-1,MIN(1,Counties!O231+0.0+Dashboard!$F$8)) | J24: =MAX(-1,MIN(1,Counties!O231+0.01+Dashboard!$F$8)) | K24: =MAX(-1,MIN(1,Counties!O231+0.05+Dashboard!$F$8)) | L24: =G24*D24 | M24: =H24*D24 | N24: =I24*D24 | O24: =J24*D24 | P24: =K24*D24 | Q24: =D24*(1+I24)/2 | R24: =Counties!AH231 | S24: =IF(Counties!AH231="","",Counties!AH231*Counties!AF231) | T24: =Counties!AO231 | U24: =Counties!AU231 | V24: =Counties!AV231 | W24: =Counties!AY231 | X24: =IF(R24="","not in yet",IF(W24<>"",IF(W24>=0.05,"Great for Turek",IF(W24>=0.01,"Turek on track",IF(W24>-0.01,"Toss-up",IF(W24>-0.05,"Hinson on track","Great for Hinson"))))&" (margin + turnout)",IF((R24-I24)>=0.05,"Great for Turek",IF((R24-I24)>=0.01,"Turek on track",IF((R24-I24)>-0.01,"Toss-up",IF((R24-I24)>-0.05,"Hinson on track","Great for Hinson"))))&IF(Counties!AG231=1,""," (partial count)"))) | Y24: ="Break-even "&IF(I24>=0,"D+","R+")&TEXT(ABS(I24)*100,"0.0")&" ("&IF(N24>=0,"D +","R +")&TEXT(ABS(N24),"#,##0")&" net, about "&TEXT(Q24,"#,##0")&" Turek votes). Turek at "&IF(K24>=0,"D+","R+")&TEXT(ABS(K24)*100,"0.0")&" or better = great night; "&IF(J24>=0,"D+","R+")&TEXT(ABS(J24)*100,"0.0")&" = on track to win. Hinson holding it to "&IF(H24>=0,"D+","R+")&TEXT(ABS(H24)*100,"0.0")&" = Hinson on track; "&IF(G24>=0,"D+","R+")&TEXT(ABS(G24)*100,"0.0")&" or worse for Turek = great for Hinson. Turnout: par is about "&TEXT(D24,"#,##0")&" two-party votes ("&TEXT(Counties!AQ231/SUMIFS(Counties!$AQ:$AQ,Counties!$A:$A,"IA"),"0.0%")&" of the state). At 95% of par the break-even moves to "&IF((I24/0.95)>=0,"D+","R+")&TEXT(ABS((I24/0.95))*100,"0.0")&"; at 105%, to "&IF((I24/1.05)>=0,"D+","R+")&TEXT(ABS((I24/1.05))*100,"0.0")&"."
A25: IA | B25: Pottawattamie | C25: Small town & rural | D25: =Counties!AT278 | E25: =Counties!O278 | F25: =Counties!R278 | G25: =MAX(-1,MIN(1,Counties!O278+-0.05+Dashboard!$F$8)) | H25: =MAX(-1,MIN(1,Counties!O278+-0.01+Dashboard!$F$8)) | I25: =MAX(-1,MIN(1,Counties!O278+0.0+Dashboard!$F$8)) | J25: =MAX(-1,MIN(1,Counties!O278+0.01+Dashboard!$F$8)) | K25: =MAX(-1,MIN(1,Counties!O278+0.05+Dashboard!$F$8)) | L25: =G25*D25 | M25: =H25*D25 | N25: =I25*D25 | O25: =J25*D25 | P25: =K25*D25 | Q25: =D25*(1+I25)/2 | R25: =Counties!AH278 | S25: =IF(Counties!AH278="","",Counties!AH278*Counties!AF278) | T25: =Counties!AO278 | U25: =Counties!AU278 | V25: =Counties!AV278 | W25: =Counties!AY278 | X25: =IF(R25="","not in yet",IF(W25<>"",IF(W25>=0.05,"Great for Turek",IF(W25>=0.01,"Turek on track",IF(W25>-0.01,"Toss-up",IF(W25>-0.05,"Hinson on track","Great for Hinson"))))&" (margin + turnout)",IF((R25-I25)>=0.05,"Great for Turek",IF((R25-I25)>=0.01,"Turek on track",IF((R25-I25)>-0.01,"Toss-up",IF((R25-I25)>-0.05,"Hinson on track","Great for Hinson"))))&IF(Counties!AG278=1,""," (partial count)"))) | Y25: ="Break-even "&IF(I25>=0,"D+","R+")&TEXT(ABS(I25)*100,"0.0")&" ("&IF(N25>=0,"D +","R +")&TEXT(ABS(N25),"#,##0")&" net, about "&TEXT(Q25,"#,##0")&" Turek votes). Turek at "&IF(K25>=0,"D+","R+")&TEXT(ABS(K25)*100,"0.0")&" or better = great night; "&IF(J25>=0,"D+","R+")&TEXT(ABS(J25)*100,"0.0")&" = on track to win. Hinson holding it to "&IF(H25>=0,"D+","R+")&TEXT(ABS(H25)*100,"0.0")&" = Hinson on track; "&IF(G25>=0,"D+","R+")&TEXT(ABS(G25)*100,"0.0")&" or worse for Turek = great for Hinson. Turnout: par is about "&TEXT(D25,"#,##0")&" two-party votes ("&TEXT(Counties!AQ278/SUMIFS(Counties!$AQ:$AQ,Counties!$A:$A,"IA"),"0.0%")&" of the state). At 95% of par the break-even moves to "&IF((I25/0.95)>=0,"D+","R+")&TEXT(ABS((I25/0.95))*100,"0.0")&"; at 105%, to "&IF((I25/1.05)>=0,"D+","R+")&TEXT(ABS((I25/1.05))*100,"0.0")&"."
A26: IA | B26: Woodbury | C26: Mid-size/working metro | D26: =Counties!AT297 | E26: =Counties!O297 | F26: =Counties!R297 | G26: =MAX(-1,MIN(1,Counties!O297+-0.05+Dashboard!$F$8)) | H26: =MAX(-1,MIN(1,Counties!O297+-0.01+Dashboard!$F$8)) | I26: =MAX(-1,MIN(1,Counties!O297+0.0+Dashboard!$F$8)) | J26: =MAX(-1,MIN(1,Counties!O297+0.01+Dashboard!$F$8)) | K26: =MAX(-1,MIN(1,Counties!O297+0.05+Dashboard!$F$8)) | L26: =G26*D26 | M26: =H26*D26 | N26: =I26*D26 | O26: =J26*D26 | P26: =K26*D26 | Q26: =D26*(1+I26)/2 | R26: =Counties!AH297 | S26: =IF(Counties!AH297="","",Counties!AH297*Counties!AF297) | T26: =Counties!AO297 | U26: =Counties!AU297 | V26: =Counties!AV297 | W26: =Counties!AY297 | X26: =IF(R26="","not in yet",IF(W26<>"",IF(W26>=0.05,"Great for Turek",IF(W26>=0.01,"Turek on track",IF(W26>-0.01,"Toss-up",IF(W26>-0.05,"Hinson on track","Great for Hinson"))))&" (margin + turnout)",IF((R26-I26)>=0.05,"Great for Turek",IF((R26-I26)>=0.01,"Turek on track",IF((R26-I26)>-0.01,"Toss-up",IF((R26-I26)>-0.05,"Hinson on track","Great for Hinson"))))&IF(Counties!AG297=1,""," (partial count)"))) | Y26: ="Break-even "&IF(I26>=0,"D+","R+")&TEXT(ABS(I26)*100,"0.0")&" ("&IF(N26>=0,"D +","R +")&TEXT(ABS(N26),"#,##0")&" net, about "&TEXT(Q26,"#,##0")&" Turek votes). Turek at "&IF(K26>=0,"D+","R+")&TEXT(ABS(K26)*100,"0.0")&" or better = great night; "&IF(J26>=0,"D+","R+")&TEXT(ABS(J26)*100,"0.0")&" = on track to win. Hinson holding it to "&IF(H26>=0,"D+","R+")&TEXT(ABS(H26)*100,"0.0")&" = Hinson on track; "&IF(G26>=0,"D+","R+")&TEXT(ABS(G26)*100,"0.0")&" or worse for Turek = great for Hinson. Turnout: par is about "&TEXT(D26,"#,##0")&" two-party votes ("&TEXT(Counties!AQ297/SUMIFS(Counties!$AQ:$AQ,Counties!$A:$A,"IA"),"0.0%")&" of the state). At 95% of par the break-even moves to "&IF((I26/0.95)>=0,"D+","R+")&TEXT(ABS((I26/0.95))*100,"0.0")&"; at 105%, to "&IF((I26/1.05)>=0,"D+","R+")&TEXT(ABS((I26/1.05))*100,"0.0")&"."
A27: IA | B27: Sioux | C27: Small town & rural | D27: =Counties!AT284 | E27: =Counties!O284 | F27: =Counties!R284 | G27: =MAX(-1,MIN(1,Counties!O284+-0.05+Dashboard!$F$8)) | H27: =MAX(-1,MIN(1,Counties!O284+-0.01+Dashboard!$F$8)) | I27: =MAX(-1,MIN(1,Counties!O284+0.0+Dashboard!$F$8)) | J27: =MAX(-1,MIN(1,Counties!O284+0.01+Dashboard!$F$8)) | K27: =MAX(-1,MIN(1,Counties!O284+0.05+Dashboard!$F$8)) | L27: =G27*D27 | M27: =H27*D27 | N27: =I27*D27 | O27: =J27*D27 | P27: =K27*D27 | Q27: =D27*(1+I27)/2 | R27: =Counties!AH284 | S27: =IF(Counties!AH284="","",Counties!AH284*Counties!AF284) | T27: =Counties!AO284 | U27: =Counties!AU284 | V27: =Counties!AV284 | W27: =Counties!AY284 | X27: =IF(R27="","not in yet",IF(W27<>"",IF(W27>=0.05,"Great for Turek",IF(W27>=0.01,"Turek on track",IF(W27>-0.01,"Toss-up",IF(W27>-0.05,"Hinson on track","Great for Hinson"))))&" (margin + turnout)",IF((R27-I27)>=0.05,"Great for Turek",IF((R27-I27)>=0.01,"Turek on track",IF((R27-I27)>-0.01,"Toss-up",IF((R27-I27)>-0.05,"Hinson on track","Great for Hinson"))))&IF(Counties!AG284=1,""," (partial count)"))) | Y27: ="Break-even "&IF(I27>=0,"D+","R+")&TEXT(ABS(I27)*100,"0.0")&" ("&IF(N27>=0,"D +","R +")&TEXT(ABS(N27),"#,##0")&" net, about "&TEXT(Q27,"#,##0")&" Turek votes). Turek at "&IF(K27>=0,"D+","R+")&TEXT(ABS(K27)*100,"0.0")&" or better = great night; "&IF(J27>=0,"D+","R+")&TEXT(ABS(J27)*100,"0.0")&" = on track to win. Hinson holding it to "&IF(H27>=0,"D+","R+")&TEXT(ABS(H27)*100,"0.0")&" = Hinson on track; "&IF(G27>=0,"D+","R+")&TEXT(ABS(G27)*100,"0.0")&" or worse for Turek = great for Hinson. Turnout: par is about "&TEXT(D27,"#,##0")&" two-party votes ("&TEXT(Counties!AQ284/SUMIFS(Counties!$AQ:$AQ,Counties!$A:$A,"IA"),"0.0%")&" of the state). At 95% of par the break-even moves to "&IF((I27/0.95)>=0,"D+","R+")&TEXT(ABS((I27/0.95))*100,"0.0")&"; at 105%, to "&IF((I27/1.05)>=0,"D+","R+")&TEXT(ABS((I27/1.05))*100,"0.0")&"."
A28: Kansas: Adam Hamilton vs Roger Marshall · 2024 statewide R+16.4 (R+16.5 with 2022's turnout pattern)
A29: KS | B29: Johnson | C29: College suburb/metro | D29: =Counties!AT345 | E29: =Counties!O345 | F29: =Counties!R345 | G29: =MAX(-1,MIN(1,Counties!O345+-0.05+Dashboard!$F$9)) | H29: =MAX(-1,MIN(1,Counties!O345+-0.01+Dashboard!$F$9)) | I29: =MAX(-1,MIN(1,Counties!O345+0.0+Dashboard!$F$9)) | J29: =MAX(-1,MIN(1,Counties!O345+0.01+Dashboard!$F$9)) | K29: =MAX(-1,MIN(1,Counties!O345+0.05+Dashboard!$F$9)) | L29: =G29*D29 | M29: =H29*D29 | N29: =I29*D29 | O29: =J29*D29 | P29: =K29*D29 | Q29: =D29*(1+I29)/2 | R29: =Counties!AH345 | S29: =IF(Counties!AH345="","",Counties!AH345*Counties!AF345) | T29: =Counties!AO345 | U29: =Counties!AU345 | V29: =Counties!AV345 | W29: =Counties!AY345 | X29: =IF(R29="","not in yet",IF(W29<>"",IF(W29>=0.05,"Great for Hamilton",IF(W29>=0.01,"Hamilton on track",IF(W29>-0.01,"Toss-up",IF(W29>-0.05,"Marshall on track","Great for Marshall"))))&" (margin + turnout)",IF((R29-I29)>=0.05,"Great for Hamilton",IF((R29-I29)>=0.01,"Hamilton on track",IF((R29-I29)>-0.01,"Toss-up",IF((R29-I29)>-0.05,"Marshall on track","Great for Marshall"))))&IF(Counties!AG345=1,""," (partial count)"))) | Y29: ="Break-even "&IF(I29>=0,"D+","R+")&TEXT(ABS(I29)*100,"0.0")&" ("&IF(N29>=0,"D +","R +")&TEXT(ABS(N29),"#,##0")&" net, about "&TEXT(Q29,"#,##0")&" Hamilton votes). Hamilton at "&IF(K29>=0,"D+","R+")&TEXT(ABS(K29)*100,"0.0")&" or better = great night; "&IF(J29>=0,"D+","R+")&TEXT(ABS(J29)*100,"0.0")&" = on track to win. Marshall holding it to "&IF(H29>=0,"D+","R+")&TEXT(ABS(H29)*100,"0.0")&" = Marshall on track; "&IF(G29>=0,"D+","R+")&TEXT(ABS(G29)*100,"0.0")&" or worse for Hamilton = great for Marshall. Turnout: par is about "&TEXT(D29,"#,##0")&" two-party votes ("&TEXT(Counties!AQ345/SUMIFS(Counties!$AQ:$AQ,Counties!$A:$A,"KS"),"0.0%")&" of the state). At 95% of par the break-even moves to "&IF((I29/0.95)>=0,"D+","R+")&TEXT(ABS((I29/0.95))*100,"0.0")&"; at 105%, to "&IF((I29/1.05)>=0,"D+","R+")&TEXT(ABS((I29/1.05))*100,"0.0")&"."
A30: KS | B30: Sedgwick | C30: Mid-size/working metro | D30: =Counties!AT386 | E30: =Counties!O386 | F30: =Counties!R386 | G30: =MAX(-1,MIN(1,Counties!O386+-0.05+Dashboard!$F$9)) | H30: =MAX(-1,MIN(1,Counties!O386+-0.01+Dashboard!$F$9)) | I30: =MAX(-1,MIN(1,Counties!O386+0.0+Dashboard!$F$9)) | J30: =MAX(-1,MIN(1,Counties!O386+0.01+Dashboard!$F$9)) | K30: =MAX(-1,MIN(1,Counties!O386+0.05+Dashboard!$F$9)) | L30: =G30*D30 | M30: =H30*D30 | N30: =I30*D30 | O30: =J30*D30 | P30: =K30*D30 | Q30: =D30*(1+I30)/2 | R30: =Counties!AH386 | S30: =IF(Counties!AH386="","",Counties!AH386*Counties!AF386) | T30: =Counties!AO386 | U30: =Counties!AU386 | V30: =Counties!AV386 | W30: =Counties!AY386 | X30: =IF(R30="","not in yet",IF(W30<>"",IF(W30>=0.05,"Great for Hamilton",IF(W30>=0.01,"Hamilton on track",IF(W30>-0.01,"Toss-up",IF(W30>-0.05,"Marshall on track","Great for Marshall"))))&" (margin + turnout)",IF((R30-I30)>=0.05,"Great for Hamilton",IF((R30-I30)>=0.01,"Hamilton on track",IF((R30-I30)>-0.01,"Toss-up",IF((R30-I30)>-0.05,"Marshall on track","Great for Marshall"))))&IF(Counties!AG386=1,""," (partial count)"))) | Y30: ="Break-even "&IF(I30>=0,"D+","R+")&TEXT(ABS(I30)*100,"0.0")&" ("&IF(N30>=0,"D +","R +")&TEXT(ABS(N30),"#,##0")&" net, about "&TEXT(Q30,"#,##0")&" Hamilton votes). Hamilton at "&IF(K30>=0,"D+","R+")&TEXT(ABS(K30)*100,"0.0")&" or better = great night; "&IF(J30>=0,"D+","R+")&TEXT(ABS(J30)*100,"0.0")&" = on track to win. Marshall holding it to "&IF(H30>=0,"D+","R+")&TEXT(ABS(H30)*100,"0.0")&" = Marshall on track; "&IF(G30>=0,"D+","R+")&TEXT(ABS(G30)*100,"0.0")&" or worse for Hamilton = great for Marshall. Turnout: par is about "&TEXT(D30,"#,##0")&" two-party votes ("&TEXT(Counties!AQ386/SUMIFS(Counties!$AQ:$AQ,Counties!$A:$A,"KS"),"0.0%")&" of the state). At 95% of par the break-even moves to "&IF((I30/0.95)>=0,"D+","R+")&TEXT(ABS((I30/0.95))*100,"0.0")&"; at 105%, to "&IF((I30/1.05)>=0,"D+","R+")&TEXT(ABS((I30/1.05))*100,"0.0")&"."
A31: KS | B31: Shawnee | C31: Mid-size/working metro | D31: =Counties!AT388 | E31: =Counties!O388 | F31: =Counties!R388 | G31: =MAX(-1,MIN(1,Counties!O388+-0.05+Dashboard!$F$9)) | H31: =MAX(-1,MIN(1,Counties!O388+-0.01+Dashboard!$F$9)) | I31: =MAX(-1,MIN(1,Counties!O388+0.0+Dashboard!$F$9)) | J31: =MAX(-1,MIN(1,Counties!O388+0.01+Dashboard!$F$9)) | K31: =MAX(-1,MIN(1,Counties!O388+0.05+Dashboard!$F$9)) | L31: =G31*D31 | M31: =H31*D31 | N31: =I31*D31 | O31: =J31*D31 | P31: =K31*D31 | Q31: =D31*(1+I31)/2 | R31: =Counties!AH388 | S31: =IF(Counties!AH388="","",Counties!AH388*Counties!AF388) | T31: =Counties!AO388 | U31: =Counties!AU388 | V31: =Counties!AV388 | W31: =Counties!AY388 | X31: =IF(R31="","not in yet",IF(W31<>"",IF(W31>=0.05,"Great for Hamilton",IF(W31>=0.01,"Hamilton on track",IF(W31>-0.01,"Toss-up",IF(W31>-0.05,"Marshall on track","Great for Marshall"))))&" (margin + turnout)",IF((R31-I31)>=0.05,"Great for Hamilton",IF((R31-I31)>=0.01,"Hamilton on track",IF((R31-I31)>-0.01,"Toss-up",IF((R31-I31)>-0.05,"Marshall on track","Great for Marshall"))))&IF(Counties!AG388=1,""," (partial count)"))) | Y31: ="Break-even "&IF(I31>=0,"D+","R+")&TEXT(ABS(I31)*100,"0.0")&" ("&IF(N31>=0,"D +","R +")&TEXT(ABS(N31),"#,##0")&" net, about "&TEXT(Q31,"#,##0")&" Hamilton votes). Hamilton at "&IF(K31>=0,"D+","R+")&TEXT(ABS(K31)*100,"0.0")&" or better = great night; "&IF(J31>=0,"D+","R+")&TEXT(ABS(J31)*100,"0.0")&" = on track to win. Marshall holding it to "&IF(H31>=0,"D+","R+")&TEXT(ABS(H31)*100,"0.0")&" = Marshall on track; "&IF(G31>=0,"D+","R+")&TEXT(ABS(G31)*100,"0.0")&" or worse for Hamilton = great for Marshall. Turnout: par is about "&TEXT(D31,"#,##0")&" two-party votes ("&TEXT(Counties!AQ388/SUMIFS(Counties!$AQ:$AQ,Counties!$A:$A,"KS"),"0.0%")&" of the state). At 95% of par the break-even moves to "&IF((I31/0.95)>=0,"D+","R+")&TEXT(ABS((I31/0.95))*100,"0.0")&"; at 105%, to "&IF((I31/1.05)>=0,"D+","R+")&TEXT(ABS((I31/1.05))*100,"0.0")&"."
A32: KS | B32: Douglas | C32: College suburb/metro | D32: =Counties!AT322 | E32: =Counties!O322 | F32: =Counties!R322 | G32: =MAX(-1,MIN(1,Counties!O322+-0.05+Dashboard!$F$9)) | H32: =MAX(-1,MIN(1,Counties!O322+-0.01+Dashboard!$F$9)) | I32: =MAX(-1,MIN(1,Counties!O322+0.0+Dashboard!$F$9)) | J32: =MAX(-1,MIN(1,Counties!O322+0.01+Dashboard!$F$9)) | K32: =MAX(-1,MIN(1,Counties!O322+0.05+Dashboard!$F$9)) | L32: =G32*D32 | M32: =H32*D32 | N32: =I32*D32 | O32: =J32*D32 | P32: =K32*D32 | Q32: =D32*(1+I32)/2 | R32: =Counties!AH322 | S32: =IF(Counties!AH322="","",Counties!AH322*Counties!AF322) | T32: =Counties!AO322 | U32: =Counties!AU322 | V32: =Counties!AV322 | W32: =Counties!AY322 | X32: =IF(R32="","not in yet",IF(W32<>"",IF(W32>=0.05,"Great for Hamilton",IF(W32>=0.01,"Hamilton on track",IF(W32>-0.01,"Toss-up",IF(W32>-0.05,"Marshall on track","Great for Marshall"))))&" (margin + turnout)",IF((R32-I32)>=0.05,"Great for Hamilton",IF((R32-I32)>=0.01,"Hamilton on track",IF((R32-I32)>-0.01,"Toss-up",IF((R32-I32)>-0.05,"Marshall on track","Great for Marshall"))))&IF(Counties!AG322=1,""," (partial count)"))) | Y32: ="Break-even "&IF(I32>=0,"D+","R+")&TEXT(ABS(I32)*100,"0.0")&" ("&IF(N32>=0,"D +","R +")&TEXT(ABS(N32),"#,##0")&" net, about "&TEXT(Q32,"#,##0")&" Hamilton votes). Hamilton at "&IF(K32>=0,"D+","R+")&TEXT(ABS(K32)*100,"0.0")&" or better = great night; "&IF(J32>=0,"D+","R+")&TEXT(ABS(J32)*100,"0.0")&" = on track to win. Marshall holding it to "&IF(H32>=0,"D+","R+")&TEXT(ABS(H32)*100,"0.0")&" = Marshall on track; "&IF(G32>=0,"D+","R+")&TEXT(ABS(G32)*100,"0.0")&" or worse for Hamilton = great for Marshall. Turnout: par is about "&TEXT(D32,"#,##0")&" two-party votes ("&TEXT(Counties!AQ322/SUMIFS(Counties!$AQ:$AQ,Counties!$A:$A,"KS"),"0.0%")&" of the state). At 95% of par the break-even moves to "&IF((I32/0.95)>=0,"D+","R+")&TEXT(ABS((I32/0.95))*100,"0.0")&"; at 105%, to "&IF((I32/1.05)>=0,"D+","R+")&TEXT(ABS((I32/1.05))*100,"0.0")&"."
A33: KS | B33: Wyandotte | C33: Mid-size/working metro | D33: =Counties!AT404 | E33: =Counties!O404 | F33: =Counties!R404 | G33: =MAX(-1,MIN(1,Counties!O404+-0.05+Dashboard!$F$9)) | H33: =MAX(-1,MIN(1,Counties!O404+-0.01+Dashboard!$F$9)) | I33: =MAX(-1,MIN(1,Counties!O404+0.0+Dashboard!$F$9)) | J33: =MAX(-1,MIN(1,Counties!O404+0.01+Dashboard!$F$9)) | K33: =MAX(-1,MIN(1,Counties!O404+0.05+Dashboard!$F$9)) | L33: =G33*D33 | M33: =H33*D33 | N33: =I33*D33 | O33: =J33*D33 | P33: =K33*D33 | Q33: =D33*(1+I33)/2 | R33: =Counties!AH404 | S33: =IF(Counties!AH404="","",Counties!AH404*Counties!AF404) | T33: =Counties!AO404 | U33: =Counties!AU404 | V33: =Counties!AV404 | W33: =Counties!AY404 | X33: =IF(R33="","not in yet",IF(W33<>"",IF(W33>=0.05,"Great for Hamilton",IF(W33>=0.01,"Hamilton on track",IF(W33>-0.01,"Toss-up",IF(W33>-0.05,"Marshall on track","Great for Marshall"))))&" (margin + turnout)",IF((R33-I33)>=0.05,"Great for Hamilton",IF((R33-I33)>=0.01,"Hamilton on track",IF((R33-I33)>-0.01,"Toss-up",IF((R33-I33)>-0.05,"Marshall on track","Great for Marshall"))))&IF(Counties!AG404=1,""," (partial count)"))) | Y33: ="Break-even "&IF(I33>=0,"D+","R+")&TEXT(ABS(I33)*100,"0.0")&" ("&IF(N33>=0,"D +","R +")&TEXT(ABS(N33),"#,##0")&" net, about "&TEXT(Q33,"#,##0")&" Hamilton votes). Hamilton at "&IF(K33>=0,"D+","R+")&TEXT(ABS(K33)*100,"0.0")&" or better = great night; "&IF(J33>=0,"D+","R+")&TEXT(ABS(J33)*100,"0.0")&" = on track to win. Marshall holding it to "&IF(H33>=0,"D+","R+")&TEXT(ABS(H33)*100,"0.0")&" = Marshall on track; "&IF(G33>=0,"D+","R+")&TEXT(ABS(G33)*100,"0.0")&" or worse for Hamilton = great for Marshall. Turnout: par is about "&TEXT(D33,"#,##0")&" two-party votes ("&TEXT(Counties!AQ404/SUMIFS(Counties!$AQ:$AQ,Counties!$A:$A,"KS"),"0.0%")&" of the state). At 95% of par the break-even moves to "&IF((I33/0.95)>=0,"D+","R+")&TEXT(ABS((I33/0.95))*100,"0.0")&"; at 105%, to "&IF((I33/1.05)>=0,"D+","R+")&TEXT(ABS((I33/1.05))*100,"0.0")&"."
A34: KS | B34: Butler | C34: Small town & rural | D34: =Counties!AT307 | E34: =Counties!O307 | F34: =Counties!R307 | G34: =MAX(-1,MIN(1,Counties!O307+-0.05+Dashboard!$F$9)) | H34: =MAX(-1,MIN(1,Counties!O307+-0.01+Dashboard!$F$9)) | I34: =MAX(-1,MIN(1,Counties!O307+0.0+Dashboard!$F$9)) | J34: =MAX(-1,MIN(1,Counties!O307+0.01+Dashboard!$F$9)) | K34: =MAX(-1,MIN(1,Counties!O307+0.05+Dashboard!$F$9)) | L34: =G34*D34 | M34: =H34*D34 | N34: =I34*D34 | O34: =J34*D34 | P34: =K34*D34 | Q34: =D34*(1+I34)/2 | R34: =Counties!AH307 | S34: =IF(Counties!AH307="","",Counties!AH307*Counties!AF307) | T34: =Counties!AO307 | U34: =Counties!AU307 | V34: =Counties!AV307 | W34: =Counties!AY307 | X34: =IF(R34="","not in yet",IF(W34<>"",IF(W34>=0.05,"Great for Hamilton",IF(W34>=0.01,"Hamilton on track",IF(W34>-0.01,"Toss-up",IF(W34>-0.05,"Marshall on track","Great for Marshall"))))&" (margin + turnout)",IF((R34-I34)>=0.05,"Great for Hamilton",IF((R34-I34)>=0.01,"Hamilton on track",IF((R34-I34)>-0.01,"Toss-up",IF((R34-I34)>-0.05,"Marshall on track","Great for Marshall"))))&IF(Counties!AG307=1,""," (partial count)"))) | Y34: ="Break-even "&IF(I34>=0,"D+","R+")&TEXT(ABS(I34)*100,"0.0")&" ("&IF(N34>=0,"D +","R +")&TEXT(ABS(N34),"#,##0")&" net, about "&TEXT(Q34,"#,##0")&" Hamilton votes). Hamilton at "&IF(K34>=0,"D+","R+")&TEXT(ABS(K34)*100,"0.0")&" or better = great night; "&IF(J34>=0,"D+","R+")&TEXT(ABS(J34)*100,"0.0")&" = on track to win. Marshall holding it to "&IF(H34>=0,"D+","R+")&TEXT(ABS(H34)*100,"0.0")&" = Marshall on track; "&IF(G34>=0,"D+","R+")&TEXT(ABS(G34)*100,"0.0")&" or worse for Hamilton = great for Marshall. Turnout: par is about "&TEXT(D34,"#,##0")&" two-party votes ("&TEXT(Counties!AQ307/SUMIFS(Counties!$AQ:$AQ,Counties!$A:$A,"KS"),"0.0%")&" of the state). At 95% of par the break-even moves to "&IF((I34/0.95)>=0,"D+","R+")&TEXT(ABS((I34/0.95))*100,"0.0")&"; at 105%, to "&IF((I34/1.05)>=0,"D+","R+")&TEXT(ABS((I34/1.05))*100,"0.0")&"."
A35: KS | B35: Reno | C35: Small town & rural | D35: =Counties!AT377 | E35: =Counties!O377 | F35: =Counties!R377 | G35: =MAX(-1,MIN(1,Counties!O377+-0.05+Dashboard!$F$9)) | H35: =MAX(-1,MIN(1,Counties!O377+-0.01+Dashboard!$F$9)) | I35: =MAX(-1,MIN(1,Counties!O377+0.0+Dashboard!$F$9)) | J35: =MAX(-1,MIN(1,Counties!O377+0.01+Dashboard!$F$9)) | K35: =MAX(-1,MIN(1,Counties!O377+0.05+Dashboard!$F$9)) | L35: =G35*D35 | M35: =H35*D35 | N35: =I35*D35 | O35: =J35*D35 | P35: =K35*D35 | Q35: =D35*(1+I35)/2 | R35: =Counties!AH377 | S35: =IF(Counties!AH377="","",Counties!AH377*Counties!AF377) | T35: =Counties!AO377 | U35: =Counties!AU377 | V35: =Counties!AV377 | W35: =Counties!AY377 | X35: =IF(R35="","not in yet",IF(W35<>"",IF(W35>=0.05,"Great for Hamilton",IF(W35>=0.01,"Hamilton on track",IF(W35>-0.01,"Toss-up",IF(W35>-0.05,"Marshall on track","Great for Marshall"))))&" (margin + turnout)",IF((R35-I35)>=0.05,"Great for Hamilton",IF((R35-I35)>=0.01,"Hamilton on track",IF((R35-I35)>-0.01,"Toss-up",IF((R35-I35)>-0.05,"Marshall on track","Great for Marshall"))))&IF(Counties!AG377=1,""," (partial count)"))) | Y35: ="Break-even "&IF(I35>=0,"D+","R+")&TEXT(ABS(I35)*100,"0.0")&" ("&IF(N35>=0,"D +","R +")&TEXT(ABS(N35),"#,##0")&" net, about "&TEXT(Q35,"#,##0")&" Hamilton votes). Hamilton at "&IF(K35>=0,"D+","R+")&TEXT(ABS(K35)*100,"0.0")&" or better = great night; "&IF(J35>=0,"D+","R+")&TEXT(ABS(J35)*100,"0.0")&" = on track to win. Marshall holding it to "&IF(H35>=0,"D+","R+")&TEXT(ABS(H35)*100,"0.0")&" = Marshall on track; "&IF(G35>=0,"D+","R+")&TEXT(ABS(G35)*100,"0.0")&" or worse for Hamilton = great for Marshall. Turnout: par is about "&TEXT(D35,"#,##0")&" two-party votes ("&TEXT(Counties!AQ377/SUMIFS(Counties!$AQ:$AQ,Counties!$A:$A,"KS"),"0.0%")&" of the state). At 95% of par the break-even moves to "&IF((I35/0.95)>=0,"D+","R+")&TEXT(ABS((I35/0.95))*100,"0.0")&"; at 105%, to "&IF((I35/1.05)>=0,"D+","R+")&TEXT(ABS((I35/1.05))*100,"0.0")&"."
A36: KS | B36: Riley | C36: Small town & rural | D36: =Counties!AT380 | E36: =Counties!O380 | F36: =Counties!R380 | G36: =MAX(-1,MIN(1,Counties!O380+-0.05+Dashboard!$F$9)) | H36: =MAX(-1,MIN(1,Counties!O380+-0.01+Dashboard!$F$9)) | I36: =MAX(-1,MIN(1,Counties!O380+0.0+Dashboard!$F$9)) | J36: =MAX(-1,MIN(1,Counties!O380+0.01+Dashboard!$F$9)) | K36: =MAX(-1,MIN(1,Counties!O380+0.05+Dashboard!$F$9)) | L36: =G36*D36 | M36: =H36*D36 | N36: =I36*D36 | O36: =J36*D36 | P36: =K36*D36 | Q36: =D36*(1+I36)/2 | R36: =Counties!AH380 | S36: =IF(Counties!AH380="","",Counties!AH380*Counties!AF380) | T36: =Counties!AO380 | U36: =Counties!AU380 | V36: =Counties!AV380 | W36: =Counties!AY380 | X36: =IF(R36="","not in yet",IF(W36<>"",IF(W36>=0.05,"Great for Hamilton",IF(W36>=0.01,"Hamilton on track",IF(W36>-0.01,"Toss-up",IF(W36>-0.05,"Marshall on track","Great for Marshall"))))&" (margin + turnout)",IF((R36-I36)>=0.05,"Great for Hamilton",IF((R36-I36)>=0.01,"Hamilton on track",IF((R36-I36)>-0.01,"Toss-up",IF((R36-I36)>-0.05,"Marshall on track","Great for Marshall"))))&IF(Counties!AG380=1,""," (partial count)"))) | Y36: ="Break-even "&IF(I36>=0,"D+","R+")&TEXT(ABS(I36)*100,"0.0")&" ("&IF(N36>=0,"D +","R +")&TEXT(ABS(N36),"#,##0")&" net, about "&TEXT(Q36,"#,##0")&" Hamilton votes). Hamilton at "&IF(K36>=0,"D+","R+")&TEXT(ABS(K36)*100,"0.0")&" or better = great night; "&IF(J36>=0,"D+","R+")&TEXT(ABS(J36)*100,"0.0")&" = on track to win. Marshall holding it to "&IF(H36>=0,"D+","R+")&TEXT(ABS(H36)*100,"0.0")&" = Marshall on track; "&IF(G36>=0,"D+","R+")&TEXT(ABS(G36)*100,"0.0")&" or worse for Hamilton = great for Marshall. Turnout: par is about "&TEXT(D36,"#,##0")&" two-party votes ("&TEXT(Counties!AQ380/SUMIFS(Counties!$AQ:$AQ,Counties!$A:$A,"KS"),"0.0%")&" of the state). At 95% of par the break-even moves to "&IF((I36/0.95)>=0,"D+","R+")&TEXT(ABS((I36/0.95))*100,"0.0")&"; at 105%, to "&IF((I36/1.05)>=0,"D+","R+")&TEXT(ABS((I36/1.05))*100,"0.0")&"."
A37: Maine: Troy Jackson vs Susan Collins · 2024 statewide D+7.1 (D+7.2 with 2022's turnout pattern)
A38: ME | B38: Cumberland | C38: College suburb/metro | D38: =Counties!AT407 | E38: =Counties!O407 | F38: =Counties!R407 | G38: =MAX(-1,MIN(1,Counties!O407+-0.05+Dashboard!$F$10)) | H38: =MAX(-1,MIN(1,Counties!O407+-0.01+Dashboard!$F$10)) | I38: =MAX(-1,MIN(1,Counties!O407+0.0+Dashboard!$F$10)) | J38: =MAX(-1,MIN(1,Counties!O407+0.01+Dashboard!$F$10)) | K38: =MAX(-1,MIN(1,Counties!O407+0.05+Dashboard!$F$10)) | L38: =G38*D38 | M38: =H38*D38 | N38: =I38*D38 | O38: =J38*D38 | P38: =K38*D38 | Q38: =D38*(1+I38)/2 | R38: =Counties!AH407 | S38: =IF(Counties!AH407="","",Counties!AH407*Counties!AF407) | T38: =Counties!AO407 | U38: =Counties!AU407 | V38: =Counties!AV407 | W38: =Counties!AY407 | X38: =IF(R38="","not in yet",IF(W38<>"",IF(W38>=0.05,"Great for Jackson",IF(W38>=0.01,"Jackson on track",IF(W38>-0.01,"Toss-up",IF(W38>-0.05,"Collins on track","Great for Collins"))))&" (margin + turnout)",IF((R38-I38)>=0.05,"Great for Jackson",IF((R38-I38)>=0.01,"Jackson on track",IF((R38-I38)>-0.01,"Toss-up",IF((R38-I38)>-0.05,"Collins on track","Great for Collins"))))&IF(Counties!AG407=1,""," (partial count)"))) | Y38: ="Break-even "&IF(I38>=0,"D+","R+")&TEXT(ABS(I38)*100,"0.0")&" ("&IF(N38>=0,"D +","R +")&TEXT(ABS(N38),"#,##0")&" net, about "&TEXT(Q38,"#,##0")&" Jackson votes). Jackson at "&IF(K38>=0,"D+","R+")&TEXT(ABS(K38)*100,"0.0")&" or better = great night; "&IF(J38>=0,"D+","R+")&TEXT(ABS(J38)*100,"0.0")&" = on track to win. Collins holding it to "&IF(H38>=0,"D+","R+")&TEXT(ABS(H38)*100,"0.0")&" = Collins on track; "&IF(G38>=0,"D+","R+")&TEXT(ABS(G38)*100,"0.0")&" or worse for Jackson = great for Collins. Turnout: par is about "&TEXT(D38,"#,##0")&" two-party votes ("&TEXT(Counties!AQ407/SUMIFS(Counties!$AQ:$AQ,Counties!$A:$A,"ME"),"0.0%")&" of the state). At 95% of par the break-even moves to "&IF((I38/0.95)>=0,"D+","R+")&TEXT(ABS((I38/0.95))*100,"0.0")&"; at 105%, to "&IF((I38/1.05)>=0,"D+","R+")&TEXT(ABS((I38/1.05))*100,"0.0")&"."
A39: ME | B39: York | C39: Mid-size/working metro | D39: =Counties!AT420 | E39: =Counties!O420 | F39: =Counties!R420 | G39: =MAX(-1,MIN(1,Counties!O420+-0.05+Dashboard!$F$10)) | H39: =MAX(-1,MIN(1,Counties!O420+-0.01+Dashboard!$F$10)) | I39: =MAX(-1,MIN(1,Counties!O420+0.0+Dashboard!$F$10)) | J39: =MAX(-1,MIN(1,Counties!O420+0.01+Dashboard!$F$10)) | K39: =MAX(-1,MIN(1,Counties!O420+0.05+Dashboard!$F$10)) | L39: =G39*D39 | M39: =H39*D39 | N39: =I39*D39 | O39: =J39*D39 | P39: =K39*D39 | Q39: =D39*(1+I39)/2 | R39: =Counties!AH420 | S39: =IF(Counties!AH420="","",Counties!AH420*Counties!AF420) | T39: =Counties!AO420 | U39: =Counties!AU420 | V39: =Counties!AV420 | W39: =Counties!AY420 | X39: =IF(R39="","not in yet",IF(W39<>"",IF(W39>=0.05,"Great for Jackson",IF(W39>=0.01,"Jackson on track",IF(W39>-0.01,"Toss-up",IF(W39>-0.05,"Collins on track","Great for Collins"))))&" (margin + turnout)",IF((R39-I39)>=0.05,"Great for Jackson",IF((R39-I39)>=0.01,"Jackson on track",IF((R39-I39)>-0.01,"Toss-up",IF((R39-I39)>-0.05,"Collins on track","Great for Collins"))))&IF(Counties!AG420=1,""," (partial count)"))) | Y39: ="Break-even "&IF(I39>=0,"D+","R+")&TEXT(ABS(I39)*100,"0.0")&" ("&IF(N39>=0,"D +","R +")&TEXT(ABS(N39),"#,##0")&" net, about "&TEXT(Q39,"#,##0")&" Jackson votes). Jackson at "&IF(K39>=0,"D+","R+")&TEXT(ABS(K39)*100,"0.0")&" or better = great night; "&IF(J39>=0,"D+","R+")&TEXT(ABS(J39)*100,"0.0")&" = on track to win. Collins holding it to "&IF(H39>=0,"D+","R+")&TEXT(ABS(H39)*100,"0.0")&" = Collins on track; "&IF(G39>=0,"D+","R+")&TEXT(ABS(G39)*100,"0.0")&" or worse for Jackson = great for Collins. Turnout: par is about "&TEXT(D39,"#,##0")&" two-party votes ("&TEXT(Counties!AQ420/SUMIFS(Counties!$AQ:$AQ,Counties!$A:$A,"ME"),"0.0%")&" of the state). At 95% of par the break-even moves to "&IF((I39/0.95)>=0,"D+","R+")&TEXT(ABS((I39/0.95))*100,"0.0")&"; at 105%, to "&IF((I39/1.05)>=0,"D+","R+")&TEXT(ABS((I39/1.05))*100,"0.0")&"."
